Workbook
Name A: #REF!
Name AA: #REF!
Name ACABADO: #REF!
Name ALUMINA: #REF!
Name ALUMINIO: #REF!
Name CLASSIC: #REF!
Name COLOR: #REF!
Name CRISTAL: #REF!
Name ESPESOR: #REF!
Name LINEA: #REF!
Name PREMIUM: #REF!
Name PRIMAVERA: #REF!
Name REFUERZO: #REF!
Name SG3_: #REF!
Name SG40_: #REF!
Name SG40_PB: #REF!
Name SG5_: #REF!
Name TRADICIONAL: #REF!
Name VANO: #REF!
Name VENECIA: #REF!

Sheet BD GN
B1: SISTEMAS | C1: SISTEMAS | E1: CERRADURAS | G1: CRISTALES | I1: ACABADO ALUMINIO | K1: LINEA CLIENTE | M1: FORMA DE PAGO | O1: PROTECCIÓN | Q1: SANDBLASTING | T1: VIS | V1: ALFAJÍA | X1: ELABORADO | Z1: OBSERVACIONES | AB1: SANDBLASTING | AD1: CIUDADES | AF1: UNIDAD DE NEGOCIO | AH1: EMBALAJE | AP1: SILICONA | AW1: PELICULA PROTECCION | BD1: TRANSPORTE | BO1: BACKOFFICE OPERATIVO | BT1: VIATICOS | BY1: VIATICOS INTERMUNICIPALES | CB1: SISTEMAS | CC1: BGA | CD1: BTA | CE1: ANTQ | CF1: VALLE | CG1: COSTA | CI1: 0.1 | CK1: BGA | CL1: BTA | CM1: ANTQ | CN1: VALLE | CO1: COSTA | CQ1: SISTEMAS | CR1: LINEA | CS1: M2 | CT1: VR TOTAL | CU1: VR M2 | CX1: LINEA | CY1: M2 | CZ1: VR TOTAL | DA1: VR M2 | DF1: RAD | DG1: CANTIDAD | DH1: SUBTOTAL | DI1: TOTAL | DJ1: ALU | DK1: ACC | DL1: VIDRIO | DM1: TRANSPORTE | DN1: VIATICOS | DO1: BACKOFFICE | DP1: GAST VENTA | DQ1: GAST FINANC | DR1: COSTOS IND | DS1: ENSAMBLE | DT1: INSTALACION | DU1: M2 INOX | DV1: M2 ALU | DW1: VR INOX | DX1: VR ALU
B2: VENTANA CORREDIZA LINEA PREMIUM TIPO EUROPEO SISTEMA VENECIA SERIE 50 | C2: VENTANA CORREDIZA LINEA PREMIUM TIPO EUROPEO VENECIA MONZA | E2: CIERRE EMBUTIDO DE IMPACTO AUTOMATICO | G2: COMPOSICION LAMINADO CRUDO 4 MM INC + PVB 0,38 MM INC + 4 MM INC | I2: ALUCOLOR POLIESTER NEGRO MATE PP13 | K2: PROFESIONALES | M2: CREDITO | O2: UNA CARA | Q2: SI | T2: SI | V2: SI | X2: IVAN CANDELA | Z2: INCLUYE ENGANCHES TOTALMENTE REFORZADOS | AB2: 50000 | AD2: BGA | AF2: SILVER | AH2: CARTON | AJ2: PROVEEDOR | AK2: PELEX | AM2: PROVEEDOR | AN2: VR ML | AP2: FACTOR CONVERSION | AQ2: ML TUBO | AR2: VR TUBO SILICONA | AS2: VR SILICONA ML | AT2: PROVEEDOR | AU2: VR ML X VEN | AW2: ANCHO M | AX2: ALTO M | AY2: AREA M2 | AZ2: VR ROLLO | BA2: PROVEEDOR | BB2: VR M2 | BD2: CIUDAD | BE2: VR VIAJE | BF2: P/CUESTA | BG2: RUITOQUE | BH2: RUITOQ BAJO | BI2: F/BLANCA | BJ2: CAPACIDAD CARGA KG | BK2: % DE CARGA | BL2: PROVEEDOR | BM2: VR KG | BO2: PARTICIPA | BP2: VR SALARIO | BQ2: VR PRESTACIONES | BR2: VR DIA | BT2: CIUDAD | BU2: VR DIA ALIMENTACION | BV2: VR HAB | BW2: VR DIA | BY2: CIUDAD | BZ2: VR IDA Y VUELTA | CB2: =C2 -> VENTANA CORREDIZA LINEA PREMIUM TIPO EUROPEO VENECIA MONZA | CC2: 622000 | CD2: 715000 | CE2: 872000 | CJ2: M2 REFERENCIA | CK2: =(565000*CI1)+565000 -> 621500 | CL2: =656700+(656700*CI1) -> 722370 | CM2: =802000+(802000*CI1) -> 882200 | CQ2: =C2 -> VENTANA CORREDIZA LINEA PREMIUM TIPO EUROPEO VENECIA MONZA | CR2: LA | CS2: =SUMIF(COTIZACIÓN!$D$15:$L$335,'BD GN'!CQ2,COTIZACIÓN!$L$15:$L$335) -> 0 | CT2: =SUMIF(COTIZACIÓN!$D$15:$O$335,'BD GN'!CQ2,COTIZACIÓN!$O$15:$O$335) -> 0 | CU2: =IFERROR(CT2/CS2,"0") -> 0 | CW2: =IFERROR(CZ2/CZ4,"0%") -> 0% | CX2: LA | CY2: =SUMIF($CR:$CU,CX2,$CS:$CS) -> 0 | CZ2: =SUMIF($CR:$CU,CX2,$CT:$CT) -> 0 | DA2: =IFERROR(CZ2/CY2,"0") -> 0 | DG2: =SUMIF(COTIZACIÓN!DG:DH,'BD GN'!$DF$2,COTIZACIÓN!DH:DH) -> 0 | DH2: =SUMIF(COTIZACIÓN!DG:DI,'BD GN'!$DF$2,COTIZACIÓN!DI:DI) -> 0 | DI2: =SUMIF(COTIZACIÓN!DG:DJ,'BD GN'!$DF$2,COTIZACIÓN!DJ:DJ) -> 0 | DJ2: =SUMIF(COTIZACIÓN!DG:DK,'BD GN'!$DF$2,COTIZACIÓN!DK:DK) -> #VALUE! | DK2: =SUMIF(COTIZACIÓN!DG:DL,'BD GN'!$DF$2,COTIZACIÓN!DL:DL) -> 0.07483939 | DL2: =SUMIF(COTIZACIÓN!DG:DM,'BD GN'!$DF$2,COTIZACIÓN!DM:DM) -> 0.06753794 | DM2: =SUMIF(COTIZACIÓN!DG:DN,'BD GN'!$DF$2,COTIZACIÓN!DN:DN) -> 0.063799022 | DN2: =SUMIF(COTIZACIÓN!DG:DO,'BD GN'!$DF$2,COTIZACIÓN!DO:DO) -> #VALUE! | DO2: =SUMIF(COTIZACIÓN!DG:DP,'BD GN'!$DF$2,COTIZACIÓN!DP:DP) -> #VALUE! | DP2: =SUMIF(COTIZACIÓN!DG:DQ,'BD GN'!$DF$2,COTIZACIÓN!DQ:DQ) -> #VALUE! | DQ2: =SUMIF(COTIZACIÓN!DG:DR,'BD GN'!$DF$2,COTIZACIÓN!DR:DR) -> 0 | DR2: =SUMIF(COTIZACIÓN!DG:DS,'BD GN'!$DF$2,COTIZACIÓN!DS:DS) -> 0 | DS2: =SUMIF(COTIZACIÓN!DG:DT,'BD GN'!$DF$2,COTIZACIÓN!DT:DT) -> 0 | DT2: =SUMIF(COTIZACIÓN!DG:DU,'BD GN'!$DF$2,COTIZACIÓN!DU:DU) -> 0 | DU2: =SUMIF(COTIZACIÓN!DG:DV,'BD GN'!$DF$2,COTIZACIÓN!DV:DV) -> 0 | DV2: =SUMIF(COTIZACIÓN!DG:DW,'BD GN'!$DF$2,COTIZACIÓN!DW:DW) -> 0 | DW2: =SUMIF(COTIZACIÓN!DG:DX,'BD GN'!$DF$2,COTIZACIÓN!DX:DX) -> 0 | DX2: =SUMIF(COTIZACIÓN!DG:DY,'BD GN'!$DF$2,COTIZACIÓN!DY:DY) -> 0
B3: PUERTA CORREDIZA LINEA PREMIUM TIPO EUROPEO SISTEMA VENECIA SERIE 70 | C3: PUERTA CORREDIZA LINEA PREMIUM TIPO EUROPEO VENECIA NAPOLES | E3: CERRADURA MULTI-PUNTO MANIJA ITALIANA | G3: COMPOSICION LAMINADO CRUDO 5 MM INC + PVB 0,38 MM INC + 5 MM INC | I3: ALUCOLOR POLIESTER PINTURA GRIS | K3: CLIENTE FINAL | M3: ACORDADA | O3: DOS CARAS | Q3: NO | T3: NO | V3: NO | X3: LUISA HERNÁNDEZ | Z3: INCLUYE ENGANCHES SENCILLOS | AD3: BTA | AF3: BRONZE | AH3: VR TIRA | AI3: VR ML | AK3: VR ROLLO | AL3: VR ML | AN3: TOTAL | AP3: 0.09 | AQ3: 305 | AR3: 24000 | AS3: =AP3*AR3 -> 2160 | AU3: =AS3 -> 2160 | AW3: 1.22 | AX3: 500 | AY3: =AW3*AX3 -> 610 | AZ3: =775000*1.19 -> 922250 | BB3: =AZ3/AY3 -> 1511.8852 | BD3: BGA | BE3: 300000 | BF3: 170000 | BG3: 190000 | BH3: 170000 | BI3: 140000 | BJ3: 2500 | BK3: 0.8 | BM3: =IFERROR(BE3/(BJ3*BK3),"0") -> 150 | BO3: SISO | BP3: 1500000 | BQ3: =BP3*40% -> 600000 | BR3: =(BP3+BQ3)/30 -> 70000 | BT3: BGA | BU3: 0 | BV3: 0 | BW3: =BU3+BV3 -> 0 | BY3: BGA | BZ3: 10000 | CB3: =C3 -> PUERTA CORREDIZA LINEA PREMIUM TIPO EUROPEO VENECIA NAPOLES | CC3: 576000 | CD3: 539000 | CE3: 777000 | CQ3: =C3 -> PUERTA CORREDIZA LINEA PREMIUM TIPO EUROPEO VENECIA NAPOLES | CR3: LA | CS3: =SUMIF(COTIZACIÓN!$D$15:$L$335,'BD GN'!CQ3,COTIZACIÓN!$L$15:$L$335) -> 0 | CT3: =SUMIF(COTIZACIÓN!$D$15:$O$335,'BD GN'!CQ3,COTIZACIÓN!$O$15:$O$335) -> 0 | CU3: =IFERROR(CT3/CS3,"0") -> 0 | CW3: =IFERROR(CZ3/CZ4,"0%") -> 0% | CX3: LI | CY3: =SUMIF($CR:$CU,CX3,$CS:$CS) -> 0 | CZ3: =SUMIF($CR:$CU,CX3,$CT:$CT) -> 0 | DA3: =IFERROR(CZ3/CY3,"0") -> 0
B4: PUERTA CORREDIZA LINEA PREMIUM TIPO EUROPEO SISTEMA VENECIA SERIE 100 | C4: PUERTA CORREDIZA LINEA PREMIUM TIPO EUROPEO VENECIA MONACO | E4: CERRADURA MULTI-PUNTO MANIJA ITALIANA | G4: COMPOSICION LAMINADO CRUDO 4 MM INC + PVB 0,38 MM GRIS + 4 MM INC | I4: ALUCOLOR POLIESTER BLANCO PP003 | Z4: INCLUYE ENGANCHES MIXTOS | AD4: ANTQ | AF4: GOLD | AH4: =170000/800 -> 212.5 | AI4: =AH4/1.35 -> 157.40741 | AK4: 6800 | AL4: =AK4/305 -> 22.295082 | AN4: =AI4+AL4 -> 179.70249 | BD4: BTA | BE4: 1500000 | BJ4: 6000 | BK4: 0.7 | BM4: =IFERROR(BE4/(BJ4*BK4),"0") -> 357.14286 | BO4: MONTAJE | BP4: 1500000 | BQ4: =BP4*40% -> 600000 | BR4: =(BP4+BQ4)/30 -> 70000 | BT4: BTA | BU4: 45000 | BV4: 65000 | BW4: =BU4+BV4 -> 110000 | BY4: BTA | BZ4: 280000 | CB4: =C4 -> PUERTA CORREDIZA LINEA PREMIUM TIPO EUROPEO VENECIA MONACO | CC4: 863000 | CE4: 1063220 | CQ4: =C4 -> PUERTA CORREDIZA LINEA PREMIUM TIPO EUROPEO VENECIA MONACO | CR4: LA | CS4: =SUMIF(COTIZACIÓN!$D$15:$L$335,'BD GN'!CQ4,COTIZACIÓN!$L$15:$L$335) -> 0 | CT4: =SUMIF(COTIZACIÓN!$D$15:$O$335,'BD GN'!CQ4,COTIZACIÓN!$O$15:$O$335) -> 0 | CU4: =IFERROR(CT4/CS4,"0") -> 0 | CX4: GLB | CY4: =CY2+CY3 -> 0 | CZ4: =CZ2+CZ3 -> 0 | DA4: =IFERROR(CZ4/CY4,"0") -> 0
B5: CUERPO FIJO LINEA PREMIUM TIPO EUROPEO SISTEMA VENECIA SERIE 40 | C5: CUERPO FIJO LINEA PREMIUM TIPO EUROPEO VENECIA FERMO | E5: N.A | G5: COMPOSICION LAMINADO CRUDO 5 MM INC + PVB 0,38 MM GRIS + 5 MM INC | I5: ALUCOLOR POLIESTER PINTURA CHAMPAÑA | Q5: RENDIMIENTO SIKA FORCE | R5: 1.5 | S5: gr/cm3 | X5: VERSIÓN | Z5: NO INCLUYE ALFAJIA | AD5: VALLE | AF5: PLATINUM | BD5: ANTQ | BE5: 1800000 | BJ5: 6000 | BK5: 0.7 | BM5: =IFERROR(BE5/(BJ5*BK5),"0") -> 428.57143 | BT5: ANTQ | BU5: 45000 | BV5: 65000 | BW5: =BU5+BV5 -> 110000 | BY5: ANTQ | BZ5: 280000 | CB5: =C5 -> CUERPO FIJO LINEA PREMIUM TIPO EUROPEO VENECIA FERMO | CC5: 470000 | CD5: 407000 | CE5: 783000 | CQ5: =C5 -> CUERPO FIJO LINEA PREMIUM TIPO EUROPEO VENECIA FERMO | CR5: LA | CS5: =SUMIF(COTIZACIÓN!$D$15:$L$335,'BD GN'!CQ5,COTIZACIÓN!$L$15:$L$335) -> 0 | CT5: =SUMIF(COTIZACIÓN!$D$15:$O$335,'BD GN'!CQ5,COTIZACIÓN!$O$15:$O$335) -> 0 | CU5: =IFERROR(CT5/CS5,"0") -> 0
B6: CUERPO PROYECTANTE LINEA PREMIUM TIPO EUROPEO SISTEMA VENECIA SERIE 40 | C6: CUERPO PROYECTANTE LINEA PREMIUM TIPO EUROPEO VENECIA FERMO | E6: MANIJA CREMONA ITALIANA | G6: COMPOSICION CONTROL SOLAR QUALITY GLASS PREMIUM LAMINADO CRUDO 4 MM INC + PVB 0,38 MM INC + 4 MM CL167 | I6: ANODIZADO BLANCO MATE AN001 | Q6: CUÑETE | R6: 30000 | S6: gr | T6: =(641960+173460)*1.19 -> 970349.8 | X6: SG CLASSIC | Z6: MARCO EN SG47 | AD6: COSTA | AF6: CUSTOM | BD6: CALI | BE6: 2200000 | BJ6: 6000 | BK6: 0.7 | BM6: =IFERROR(BE6/(BJ6*BK6),"0") -> 523.80952 | BT6: CALI | BU6: 45000 | BV6: 65000 | BW6: =BU6+BV6 -> 110000 | BY6: CALI | BZ6: 320000 | CB6: =C6 -> CUERPO PROYECTANTE LINEA PREMIUM TIPO EUROPEO VENECIA FERMO | CC6: 470000 | CD6: 407000 | CE6: 783000 | CQ6: =C6 -> CUERPO PROYECTANTE LINEA PREMIUM TIPO EUROPEO VENECIA FERMO | CR6: LA | CS6: =SUMIF(COTIZACIÓN!$D$15:$L$335,'BD GN'!CQ6,COTIZACIÓN!$L$15:$L$335) -> 0 | CT6: =SUMIF(COTIZACIÓN!$D$15:$O$335,'BD GN'!CQ6,COTIZACIÓN!$O$15:$O$335) -> 0 | CU6: =IFERROR(CT6/CS6,"0") -> 0
B7: PUERTA BATIENTE LINEA PREMIUM TIPO EUROPEO SISTEMA VENECIA SERIE 40 | C7: PUERTA BATIENTE LINEA PREMIUM TIPO EUROPEO VENECIA FERMO | E7: MANIJA DOBLE CONFORT | G7: COMPOSICION CONTROL SOLAR QUALITY GLASS PREMIUM LAMINADO CRUDO 4 MM INC + PVB 0,38 MM INC + 4 MM CL120 | I7: N.A | Q7: medidas del perfil F Para 1m | R7: =10*1.3*100 -> 1300 | S7: cm3 | X7: SG ESENCIAL | Z7: MARCO EN SG58 | AF7: CONFORT | BD7: COSTA | BE7: 1800000 | BJ7: 6000 | BK7: 0.7 | BM7: =IFERROR(BE7/(BJ7*BK7),"0") -> 428.57143 | BT7: COSTA | BU7: 45000 | BV7: 65000 | BW7: =BU7+BV7 -> 110000 | BY7: COSTA | BZ7: 350000 | CB7: =C7 -> PUERTA BATIENTE LINEA PREMIUM TIPO EUROPEO VENECIA FERMO | CQ7: =C7 -> PUERTA BATIENTE LINEA PREMIUM TIPO EUROPEO VENECIA FERMO | CR7: LA | CS7: =SUMIF(COTIZACIÓN!$D$15:$L$335,'BD GN'!CQ7,COTIZACIÓN!$L$15:$L$335) -> 0 | CT7: =SUMIF(COTIZACIÓN!$D$15:$O$335,'BD GN'!CQ7,COTIZACIÓN!$O$15:$O$335) -> 0 | CU7: =IFERROR(CT7/CS7,"0") -> 0
B8: VENTANA CORREDIZA LINEA CLASSIC SISTEMA PRIMAVERA SERIE SG 3 | C8: VENTANA CORREDIZA LINEA CLASSIC SISTEMA PRIMAVERA SERIE SG 3 | E8: CIERRE EMBUTIDO DE IMPACTO AUTOMATICO | G8: COMPOSICION CONTROL SOLAR QUALITY GLASS PREMIUM LAMINADO CRUDO 4 MM INC + PVB 0,38 MM INC + 4 MM CL150 | Q8: valor por mL de pasamanos | R8: =+R7*R5 -> 1950 | S8: gr | T8: =+(R8*T6)/R6 -> 63072.737 | X8: SG BIOCONFORT | Z8: VERTICOS 636 Y 688 | BD8: CUCUTA | BE8: 1200000 | BJ8: 8000 | BK8: 0.7 | BM8: =IFERROR(BE8/(BJ8*BK8),"0") -> 214.28571 | CB8: =C8 -> VENTANA CORREDIZA LINEA CLASSIC SISTEMA PRIMAVERA SERIE SG 3 | CQ8: =C8 -> VENTANA CORREDIZA LINEA CLASSIC SISTEMA PRIMAVERA SERIE SG 3 | CR8: LA | CS8: =SUMIF(COTIZACIÓN!$D$15:$L$335,'BD GN'!CQ8,COTIZACIÓN!$L$15:$L$335) -> 0 | CT8: =SUMIF(COTIZACIÓN!$D$15:$O$335,'BD GN'!CQ8,COTIZACIÓN!$O$15:$O$335) -> 0 | CU8: =IFERROR(CT8/CS8,"0") -> 0
B9: VENTANA CORREDIZA LINEA CLASSIC SISTEMA PRIMAVERA SERIE SG 5 | C9: VENTANA CORREDIZA LINEA CLASSIC PRIMAVERA LAGO | E9: CIERRE EMBUTIDO DE IMPACTO AUTOMATICO | G9: COMPOSICION CONTROL SOLAR QUALITY GLASS CLASSIC LAMINADO CRUDO 4 MM INC + PVB 0,38 MM INC + 4 MM GREEN | X9: SG SIGNATURE | Z9: VERTICOS 688 Y 1860 | CB9: =C9 -> VENTANA CORREDIZA LINEA CLASSIC PRIMAVERA LAGO | CC9: 442000 | CE9: 649000 | CQ9: =C9 -> VENTANA CORREDIZA LINEA CLASSIC PRIMAVERA LAGO | CR9: LA | CS9: =SUMIF(COTIZACIÓN!$D$15:$L$335,'BD GN'!CQ9,COTIZACIÓN!$L$15:$L$335) -> 0 | CT9: =SUMIF(COTIZACIÓN!$D$15:$O$335,'BD GN'!CQ9,COTIZACIÓN!$O$15:$O$335) -> 0 | CU9: =IFERROR(CT9/CS9,"0") -> 0
B10: PUERTA CORREDIZA LINEA CLASSIC SISTEMA PRIMAVERA SERIE SG 5 | C10: PUERTA CORREDIZA LINEA CLASSIC PRIMAVERA LAGO | E10: CIERRE EMBUTIDO DE IMPACTO | G10: COMPOSICION CONTROL SOLAR QUALITY GLASS CLASSIC LAMINADO CRUDO 4 MM INC + PVB 0,38 MM INC + 4 MM BLUE | Z10: SISTEMA DESLIZANTE | CB10: =C10 -> PUERTA CORREDIZA LINEA CLASSIC PRIMAVERA LAGO | CC10: 442000 | CQ10: =C10 -> PUERTA CORREDIZA LINEA CLASSIC PRIMAVERA LAGO | CR10: LA | CS10: =SUMIF(COTIZACIÓN!$D$15:$L$335,'BD GN'!CQ10,COTIZACIÓN!$L$15:$L$335) -> 0 | CT10: =SUMIF(COTIZACIÓN!$D$15:$O$335,'BD GN'!CQ10,COTIZACIÓN!$O$15:$O$335) -> 0 | CU10: =IFERROR(CT10/CS10,"0") -> 0
B11: VENTANA CORREDIZA LINEA CLASSIC SISTEMA PRIMAVERA SERIE SG 8 | C11: VENTANA CORREDIZA LINEA CLASSIC PRIMAVERA LUCCA | E11: CIERRE EMBUTIDO DE IMPACTO AUTOMATICO | G11: COMPOSICION CONTROL SOLAR QUALITY GLASS CLASSIC LAMINADO CRUDO 4 MM INC + PVB 0,38 MM INC + 4 MM BRONZE | Z11: SISTEMA BATIENTE | CB11: =C11 -> VENTANA CORREDIZA LINEA CLASSIC PRIMAVERA LUCCA | CC11: 411000 | CQ11: =C11 -> VENTANA CORREDIZA LINEA CLASSIC PRIMAVERA LUCCA | CR11: LA | CS11: =SUMIF(COTIZACIÓN!$D$15:$L$335,'BD GN'!CQ11,COTIZACIÓN!$L$15:$L$335) -> 0 | CT11: =SUMIF(COTIZACIÓN!$D$15:$O$335,'BD GN'!CQ11,COTIZACIÓN!$O$15:$O$335) -> 0 | CU11: =IFERROR(CT11/CS11,"0") -> 0
B12: PUERTA CORREDIZA LINEA CLASSIC SISTEMA PRIMAVERA SERIE SG 8 | C12: PUERTA CORREDIZA LINEA CLASSIC PRIMAVERA LUCCA | E12: CIERRE EMBUTIDO DE IMPACTO | G12: COMPOSICION MONOLITICO TEMPLADO 10 MM INC | CB12: =C12 -> PUERTA CORREDIZA LINEA CLASSIC PRIMAVERA LUCCA | CC12: 411000 | CQ12: =C12 -> PUERTA CORREDIZA LINEA CLASSIC PRIMAVERA LUCCA | CR12: LA | CS12: =SUMIF(COTIZACIÓN!$D$15:$L$335,'BD GN'!CQ12,COTIZACIÓN!$L$15:$L$335) -> 0 | CT12: =SUMIF(COTIZACIÓN!$D$15:$O$335,'BD GN'!CQ12,COTIZACIÓN!$O$15:$O$335) -> 0 | CU12: =IFERROR(CT12/CS12,"0") -> 0
B13: CUERPO BATIENTE LINEA PREMIUM TIPO EUROPEO SISTEMA VENECIA SERIE 40 | C13: CUERPO BATIENTE LINEA PREMIUM TIPO EUROPEO VENECIA FERMO | E13: MANIJA CREMONA ITALIANA | G13: COMPOSICION MONOLITICO TEMPLADO 8 MM INC | Z13: INCLUYE TUBULAR SGT-101-103-117 | CB13: =C13 -> CUERPO BATIENTE LINEA PREMIUM TIPO EUROPEO VENECIA FERMO | CC13: 470000 | CD13: 407000 | CE13: 738000 | CQ13: =C13 -> CUERPO BATIENTE LINEA PREMIUM TIPO EUROPEO VENECIA FERMO | CR13: LA | CS13: =SUMIF(COTIZACIÓN!$D$15:$L$335,'BD GN'!CQ13,COTIZACIÓN!$L$15:$L$335) -> 0 | CT13: =SUMIF(COTIZACIÓN!$D$15:$O$335,'BD GN'!CQ13,COTIZACIÓN!$O$15:$O$335) -> 0 | CU13: =IFERROR(CT13/CS13,"0") -> 0
B14: PUERTA DOBLE BATIENTE LINEA PREMIUM TIPO EUROPEO SISTEMA VENECIA SERIE 40 | C14: PUERTA DOBLE BATIENTE LINEA PREMIUM TIPO EUROPEO VENECIA FERMO | E14: MANIJA CREMONA ITALIANA | G14: COMPOSICION MONOLITICO TEMPLADO 6 MM INC | Z14: INCLUYE DIVISORES | CB14: =C14 -> PUERTA DOBLE BATIENTE LINEA PREMIUM TIPO EUROPEO VENECIA FERMO | CQ14: =C14 -> PUERTA DOBLE BATIENTE LINEA PREMIUM TIPO EUROPEO VENECIA FERMO | CR14: LA | CS14: =SUMIF(COTIZACIÓN!$D$15:$L$335,'BD GN'!CQ14,COTIZACIÓN!$L$15:$L$335) -> 0 | CT14: =SUMIF(COTIZACIÓN!$D$15:$O$335,'BD GN'!CQ14,COTIZACIÓN!$O$15:$O$335) -> 0 | CU14: =IFERROR(CT14/CS14,"0") -> 0
B15: FACHADA FLOTANTE LINEA STICK SISTEMA SG45 TAPA Y PISAVIDRIO | C15: FACHADA FLOTANTE LINEA STICK SISTEMA SG45 TAPA Y PISAVIDRIO | E15: N.A | G15: COMPOSICION MONOLITICO TEMPLADO 5 MM INC | Z15: NO INCLUYE TUBO SUPERIOR | CB15: =C15 -> FACHADA FLOTANTE LINEA STICK SISTEMA SG45 TAPA Y PISAVIDRIO | CC15: 841900 | CD15: 614000 | CQ15: =C15 -> FACHADA FLOTANTE LINEA STICK SISTEMA SG45 TAPA Y PISAVIDRIO | CR15: LA | CS15: =SUMIF(COTIZACIÓN!$D$15:$L$335,'BD GN'!CQ15,COTIZACIÓN!$L$15:$L$335) -> 0 | CT15: =SUMIF(COTIZACIÓN!$D$15:$O$335,'BD GN'!CQ15,COTIZACIÓN!$O$15:$O$335) -> 0 | CU15: =IFERROR(CT15/CS15,"0") -> 0
B16: FACHADA ENTRE PLACAS LINEA STICK SISTEMA SG45 TAPA Y PISAVIDRIO | C16: FACHADA ENTRE PLACAS LINEA STICK SISTEMA SG45 TAPA Y PISAVIDRIO | E16: N.A | G16: COMPOSICION MONOLITICO TEMPLADO 4 MM INC | Z16: SISTEMA DE BARANDA EMBEBIDA, SE REQUIERE BOLSILLO CON PROFUNDIDAD MINIMA DE 15 CM, NO INCLUYE FIJACIÓN, SE ENTREGA INSTALADO Y LISTO PARA FIJAR, NO INCLUYE TUBO SUPERIOR | CB16: =C16 -> FACHADA ENTRE PLACAS LINEA STICK SISTEMA SG45 TAPA Y PISAVIDRIO | CC16: 841900 | CD16: 614000 | CQ16: =C16 -> FACHADA ENTRE PLACAS LINEA STICK SISTEMA SG45 TAPA Y PISAVIDRIO | CR16: LA | CS16: =SUMIF(COTIZACIÓN!$D$15:$L$335,'BD GN'!CQ16,COTIZACIÓN!$L$15:$L$335) -> 0 | CT16: =SUMIF(COTIZACIÓN!$D$15:$O$335,'BD GN'!CQ16,COTIZACIÓN!$O$15:$O$335) -> 0 | CU16: =IFERROR(CT16/CS16,"0") -> 0
B17: FACHADA FLOTANTE LINEA STICK SISTEMA SG45 PIEL DE VIDRIO | C17: FACHADA FLOTANTE LINEA STICK SISTEMA SG45 PIEL DE VIDRIO | E17: N.A | G17: COMPOSICION MONOLITICO CRUDO 6 MM INC | Z17: CON PERSIANA SGB0315 | CB17: =C17 -> FACHADA FLOTANTE LINEA STICK SISTEMA SG45 PIEL DE VIDRIO | CC17: 841900 | CD17: 614000 | CQ17: =C17 -> FACHADA FLOTANTE LINEA STICK SISTEMA SG45 PIEL DE VIDRIO | CR17: LA | CS17: =SUMIF(COTIZACIÓN!$D$15:$L$335,'BD GN'!CQ17,COTIZACIÓN!$L$15:$L$335) -> 0 | CT17: =SUMIF(COTIZACIÓN!$D$15:$O$335,'BD GN'!CQ17,COTIZACIÓN!$O$15:$O$335) -> 0 | CU17: =IFERROR(CT17/CS17,"0") -> 0
B18: FACHADA ENTRE PLACAS LINEA STICK SISTEMA SG45 PIEL DE VIDRIO | C18: FACHADA ENTRE PLACAS LINEA STICK SISTEMA SG45 PIEL DE VIDRIO | E18: N.A | G18: COMPOSICION MONOLITICO CRUDO 5 MM INC | CB18: =C18 -> FACHADA ENTRE PLACAS LINEA STICK SISTEMA SG45 PIEL DE VIDRIO | CC18: 841900 | CD18: 614000 | CQ18: =C18 -> FACHADA ENTRE PLACAS LINEA STICK SISTEMA SG45 PIEL DE VIDRIO | CR18: LA | CS18: =SUMIF(COTIZACIÓN!$D$15:$L$335,'BD GN'!CQ18,COTIZACIÓN!$L$15:$L$335) -> 0 | CT18: =SUMIF(COTIZACIÓN!$D$15:$O$335,'BD GN'!CQ18,COTIZACIÓN!$O$15:$O$335) -> 0 | CU18: =IFERROR(CT18/CS18,"0") -> 0
B19: CUERPO FIJO LINEA CLASSIC SISTEMA PRIMAVERA SERIE SG 4 | C19: CUERPO FIJO LINEA CLASSIC PRIMAVERA SIENA | E19: N.A | G19: COMPOSICION MONOLITICO CRUDO 4 MM MINI BOREAL | CB19: =C19 -> CUERPO FIJO LINEA CLASSIC PRIMAVERA SIENA | CC19: 455000 | CQ19: =C19 -> CUERPO FIJO LINEA CLASSIC PRIMAVERA SIENA | CR19: LA | CS19: =SUMIF(COTIZACIÓN!$D$15:$L$335,'BD GN'!CQ19,COTIZACIÓN!$L$15:$L$335) -> 0 | CT19: =SUMIF(COTIZACIÓN!$D$15:$O$335,'BD GN'!CQ19,COTIZACIÓN!$O$15:$O$335) -> 0 | CU19: =IFERROR(CT19/CS19,"0") -> 0
B20: CUERPO PROYECTANTE LINEA CLASSIC SISTEMA PRIMAVERA SERIE SG 4 | C20: CUERPO PROYECTANTE LINEA CLASSIC PRIMAVERA SIENA | E20: MANIJA LUJO BASIC | G20: COMPOSICION MONOLITICO CRUDO 4 MM INC | CB20: =C20 -> CUERPO PROYECTANTE LINEA CLASSIC PRIMAVERA SIENA | CC20: 455000 | CE20: 578000 | CQ20: =C20 -> CUERPO PROYECTANTE LINEA CLASSIC PRIMAVERA SIENA | CR20: LA | CS20: =SUMIF(COTIZACIÓN!$D$15:$L$335,'BD GN'!CQ20,COTIZACIÓN!$L$15:$L$335) -> 0 | CT20: =SUMIF(COTIZACIÓN!$D$15:$O$335,'BD GN'!CQ20,COTIZACIÓN!$O$15:$O$335) -> 0 | CU20: =IFERROR(CT20/CS20,"0") -> 0
B21: CUERPO BATIENTE LINEA CLASSIC SISTEMA PRIMAVERA SERIE SG 4 | C21: CUERPO BATIENTE LINEA CLASSIC PRIMAVERA SIENA | E21: MANIJA LUJO BASIC | G21: N.A. | CB21: =C21 -> CUERPO BATIENTE LINEA CLASSIC PRIMAVERA SIENA | CC21: 455000 | CE21: 578000 | CQ21: =C21 -> CUERPO BATIENTE LINEA CLASSIC PRIMAVERA SIENA | CR21: LA | CS21: =SUMIF(COTIZACIÓN!$D$15:$L$335,'BD GN'!CQ21,COTIZACIÓN!$L$15:$L$335) -> 0 | CT21: =SUMIF(COTIZACIÓN!$D$15:$O$335,'BD GN'!CQ21,COTIZACIÓN!$O$15:$O$335) -> 0 | CU21: =IFERROR(CT21/CS21,"0") -> 0
B22: PUERTA BATIENTE LINEA CLASSIC SISTEMA PRIMAVERA SERIE SG 4 | C22: PUERTA BATIENTE LINEA CLASSIC PRIMAVERA SIENA | E22: MANIJA LUJO BASIC | CB22: =C22 -> PUERTA BATIENTE LINEA CLASSIC PRIMAVERA SIENA | CC22: 455000 | CQ22: =C22 -> PUERTA BATIENTE LINEA CLASSIC PRIMAVERA SIENA | CR22: LA | CS22: =SUMIF(COTIZACIÓN!$D$15:$L$335,'BD GN'!CQ22,COTIZACIÓN!$L$15:$L$335) -> 0 | CT22: =SUMIF(COTIZACIÓN!$D$15:$O$335,'BD GN'!CQ22,COTIZACIÓN!$O$15:$O$335) -> 0 | CU22: =IFERROR(CT22/CS22,"0") -> 0
B23: CUERPO FIJO LINEA CLASSIC SISTEMA PRIMAVERA SERIE SG 3 | C23: CUERPO FIJO LINEA CLASSIC SISTEMA PRIMAVERA SERIE SG 3 | E23: N.A | CB23: =C23 -> CUERPO FIJO LINEA CLASSIC SISTEMA PRIMAVERA SERIE SG 3 | CQ23: =C23 -> CUERPO FIJO LINEA CLASSIC SISTEMA PRIMAVERA SERIE SG 3 | CR23: LA | CS23: =SUMIF(COTIZACIÓN!$D$15:$L$335,'BD GN'!CQ23,COTIZACIÓN!$L$15:$L$335) -> 0 | CT23: =SUMIF(COTIZACIÓN!$D$15:$O$335,'BD GN'!CQ23,COTIZACIÓN!$O$15:$O$335) -> 0 | CU23: =IFERROR(CT23/CS23,"0") -> 0
B24: SISTEMA REJILLA | C24: SISTEMA REJILLA | E24: N.A | CB24: =C24 -> SISTEMA REJILLA | CQ24: =C24 -> SISTEMA REJILLA | CR24: LA | CS24: =SUMIF(COTIZACIÓN!$D$15:$L$335,'BD GN'!CQ24,COTIZACIÓN!$L$15:$L$335) -> 0 | CT24: =SUMIF(COTIZACIÓN!$D$15:$O$335,'BD GN'!CQ24,COTIZACIÓN!$O$15:$O$335) -> 0 | CU24: =IFERROR(CT24/CS24,"0") -> 0
B25: PUERTA CORREDIZA CON ACCESIORIOS INOX | C25: PUERTA CORREDIZA CON ACCESIORIOS INOX | E25: MANIJA INOX | CB25: =C25 -> PUERTA CORREDIZA CON ACCESIORIOS INOX | CQ25: =C25 -> PUERTA CORREDIZA CON ACCESIORIOS INOX | CR25: LI | CS25: =SUMIF(COTIZACIÓN!$D$15:$L$335,'BD GN'!CQ25,COTIZACIÓN!$L$15:$L$335) -> 0 | CT25: =SUMIF(COTIZACIÓN!$D$15:$O$335,'BD GN'!CQ25,COTIZACIÓN!$O$15:$O$335) -> 0 | CU25: =IFERROR(CT25/CS25,"0") -> 0
B26: CUERPO FIJO CON ACCESORIOS INOX | C26: CUERPO FIJO CON ACCESORIOS INOX | E26: N.A | CB26: =C26 -> CUERPO FIJO CON ACCESORIOS INOX | CQ26: =C26 -> CUERPO FIJO CON ACCESORIOS INOX | CR26: LI | CS26: =SUMIF(COTIZACIÓN!$D$15:$L$335,'BD GN'!CQ26,COTIZACIÓN!$L$15:$L$335) -> 0 | CT26: =SUMIF(COTIZACIÓN!$D$15:$O$335,'BD GN'!CQ26,COTIZACIÓN!$O$15:$O$335) -> 0 | CU26: =IFERROR(CT26/CS26,"0") -> 0
B27: PUERTA BATIENTE CON ACCESORIOS INOX | C27: PUERTA BATIENTE CON ACCESORIOS INOX | E27: MANIJA INOX | CB27: =C27 -> PUERTA BATIENTE CON ACCESORIOS INOX | CQ27: =C27 -> PUERTA BATIENTE CON ACCESORIOS INOX | CR27: LI | CS27: =SUMIF(COTIZACIÓN!$D$15:$L$335,'BD GN'!CQ27,COTIZACIÓN!$L$15:$L$335) -> 0 | CT27: =SUMIF(COTIZACIÓN!$D$15:$O$335,'BD GN'!CQ27,COTIZACIÓN!$O$15:$O$335) -> 0 | CU27: =IFERROR(CT27/CS27,"0") -> 0
B28: PUERTA DOBLE BATIENTE CON ACCESORIOS INOX | C28: PUERTA DOBLE BATIENTE CON ACCESORIOS INOX | E28: MANIJA INOX | CB28: =C28 -> PUERTA DOBLE BATIENTE CON ACCESORIOS INOX | CQ28: =C28 -> PUERTA DOBLE BATIENTE CON ACCESORIOS INOX | CR28: LI | CS28: =SUMIF(COTIZACIÓN!$D$15:$L$335,'BD GN'!CQ28,COTIZACIÓN!$L$15:$L$335) -> 0 | CT28: =SUMIF(COTIZACIÓN!$D$15:$O$335,'BD GN'!CQ28,COTIZACIÓN!$O$15:$O$335) -> 0 | CU28: =IFERROR(CT28/CS28,"0") -> 0
B29: DIVISIONES DE BAÑO CON ACCESORIOS EN ACERO INOXIDABLE | C29: DIVISIONES DE BAÑO CON ACCESORIOS EN ACERO INOXIDABLE | E29: N.A | CB29: =C29 -> DIVISIONES DE BAÑO CON ACCESORIOS EN ACERO INOXIDABLE | CC29: 390000 | CQ29: =C29 -> DIVISIONES DE BAÑO CON ACCESORIOS EN ACERO INOXIDABLE | CR29: LI | CS29: =SUMIF(COTIZACIÓN!$D$15:$L$335,'BD GN'!CQ29,COTIZACIÓN!$L$15:$L$335) -> 0 | CT29: =SUMIF(COTIZACIÓN!$D$15:$O$335,'BD GN'!CQ29,COTIZACIÓN!$O$15:$O$335) -> 0 | CU29: =IFERROR(CT29/CS29,"0") -> 0
B30: PUERTA CORREDIZA LINEA PREMIUM TIPO EUROPEO SISTEMA VENECIA SERIE 70 TIPO POKET | C30: PUERTA CORREDIZA LINEA PREMIUM TIPO EUROPEO VENECIA NAPOLES TIPO POKET | E30: CERRADURA MULTI-PUNTO MANIJA ITALIANA | CB30: =C30 -> PUERTA CORREDIZA LINEA PREMIUM TIPO EUROPEO VENECIA NAPOLES TIPO POKET | CC30: 576000 | CD30: 539000 | CE30: 777000 | CQ30: =C30 -> PUERTA CORREDIZA LINEA PREMIUM TIPO EUROPEO VENECIA NAPOLES TIPO POKET | CR30: LA | CS30: =SUMIF(COTIZACIÓN!$D$15:$L$335,'BD GN'!CQ30,COTIZACIÓN!$L$15:$L$335) -> 0 | CT30: =SUMIF(COTIZACIÓN!$D$15:$O$335,'BD GN'!CQ30,COTIZACIÓN!$O$15:$O$335) -> 0 | CU30: =IFERROR(CT30/CS30,"0") -> 0
B31: PUERTA CORREDIZA LINEA CLASSIC SISTEMA 8025 | C31: PUERTA CORREDIZA LINEA CLASSIC SISTEMA 8025 | E31: CIERRE EMBUTIDO DE IMPACTO | CB31: =C31 -> PUERTA CORREDIZA LINEA CLASSIC SISTEMA 8025 | CQ31: =C31 -> PUERTA CORREDIZA LINEA CLASSIC SISTEMA 8025 | CR31: LA | CS31: =SUMIF(COTIZACIÓN!$D$15:$L$335,'BD GN'!CQ31,COTIZACIÓN!$L$15:$L$335) -> 0 | CT31: =SUMIF(COTIZACIÓN!$D$15:$O$335,'BD GN'!CQ31,COTIZACIÓN!$O$15:$O$335) -> 0 | CU31: =IFERROR(CT31/CS31,"0") -> 0
B32: N.A | C32: N.A | E32: N.A | CB32: =C32 -> N.A | CQ32: =C32 -> N.A | CR32: LI | CS32: =SUMIF(COTIZACIÓN!$D$15:$L$335,'BD GN'!CQ32,COTIZACIÓN!$L$15:$L$335) -> 0 | CT32: =SUMIF(COTIZACIÓN!$D$15:$O$335,'BD GN'!CQ32,COTIZACIÓN!$O$15:$O$335) -> 0 | CU32: =IFERROR(CT32/CS32,"0") -> 0
B33: CUERPO PROYECTANTE LINEA CLASSIC SISTEMA 3831 | C33: CUERPO PROYECTANTE LINEA CLASSIC SISTEMA 3831 | E33: MANIJA LUJO BASIC | CB33: =C33 -> CUERPO PROYECTANTE LINEA CLASSIC SISTEMA 3831 | CQ33: =C33 -> CUERPO PROYECTANTE LINEA CLASSIC SISTEMA 3831 | CR33: LA | CS33: =SUMIF(COTIZACIÓN!$D$15:$L$335,'BD GN'!CQ33,COTIZACIÓN!$L$15:$L$335) -> 0 | CT33: =SUMIF(COTIZACIÓN!$D$15:$O$335,'BD GN'!CQ33,COTIZACIÓN!$O$15:$O$335) -> 0 | CU33: =IFERROR(CT33/CS33,"0") -> 0
B34: CUERPO FIJO LINEA CLASSIC SISTEMA 3831 | C34: CUERPO FIJO LINEA CLASSIC SISTEMA 3831 | E34: N.A | CB34: =C34 -> CUERPO FIJO LINEA CLASSIC SISTEMA 3831 | CQ34: =C34 -> CUERPO FIJO LINEA CLASSIC SISTEMA 3831 | CR34: LA | CS34: =SUMIF(COTIZACIÓN!$D$15:$L$335,'BD GN'!CQ34,COTIZACIÓN!$L$15:$L$335) -> 0 | CT34: =SUMIF(COTIZACIÓN!$D$15:$O$335,'BD GN'!CQ34,COTIZACIÓN!$O$15:$O$335) -> 0 | CU34: =IFERROR(CT34/CS34,"0") -> 0
B35: BARANDA EMBEBIDA SIN TUBO SUPERIOR | C35: BARANDA EMBEBIDA SIN TUBO SUPERIOR | E35: N.A | CB35: =C35 -> BARANDA EMBEBIDA SIN TUBO SUPERIOR | CC35: 456000 | CE35: 474000 | CQ35: =C35 -> BARANDA EMBEBIDA SIN TUBO SUPERIOR | CR35: LI | CS35: =SUMIF(COTIZACIÓN!$D$15:$L$335,'BD GN'!CQ35,COTIZACIÓN!$L$15:$L$335) -> 0 | CT35: =SUMIF(COTIZACIÓN!$D$15:$O$335,'BD GN'!CQ35,COTIZACIÓN!$O$15:$O$335) -> 0 | CU35: =IFERROR(CT35/CS35,"0") -> 0
B36: BARANDA EMBEBIDA CON TUBO SUPERIOR EN INOX | C36: BARANDA EMBEBIDA CON TUBO SUPERIOR EN INOX | E36: N.A | CB36: =C36 -> BARANDA EMBEBIDA CON TUBO SUPERIOR EN INOX | CC36: 456000 | CQ36: =C36 -> BARANDA EMBEBIDA CON TUBO SUPERIOR EN INOX | CR36: LI | CS36: =SUMIF(COTIZACIÓN!$D$15:$L$335,'BD GN'!CQ36,COTIZACIÓN!$L$15:$L$335) -> 0 | CT36: =SUMIF(COTIZACIÓN!$D$15:$O$335,'BD GN'!CQ36,COTIZACIÓN!$O$15:$O$335) -> 0 | CU36: =IFERROR(CT36/CS36,"0") -> 0
B37: BARANDA EMBEBIDA CON TUBO SUPERIOR EN ALUMINIO SG | C37: BARANDA EMBEBIDA CON TUBO SUPERIOR EN ALUMINIO SG | E37: N.A | CB37: =C37 -> BARANDA EMBEBIDA CON TUBO SUPERIOR EN ALUMINIO SG | CC37: 456000 | CQ37: =C37 -> BARANDA EMBEBIDA CON TUBO SUPERIOR EN ALUMINIO SG | CR37: LI | CS37: =SUMIF(COTIZACIÓN!$D$15:$L$335,'BD GN'!CQ37,COTIZACIÓN!$L$15:$L$335) -> 0 | CT37: =SUMIF(COTIZACIÓN!$D$15:$O$335,'BD GN'!CQ37,COTIZACIÓN!$O$15:$O$335) -> 0 | CU37: =IFERROR(CT37/CS37,"0") -> 0
B38: BARANDILLA CON TUBO SUPERIOR EN INOX | C38: BARANDILLA CON TUBO SUPERIOR EN INOX | E38: N.A | CB38: =C38 -> BARANDILLA CON TUBO SUPERIOR EN INOX | CC38: 339150 | CQ38: =C38 -> BARANDILLA CON TUBO SUPERIOR EN INOX | CR38: LI | CS38: =SUMIF(COTIZACIÓN!$D$15:$L$335,'BD GN'!CQ38,COTIZACIÓN!$L$15:$L$335) -> 0 | CT38: =SUMIF(COTIZACIÓN!$D$15:$O$335,'BD GN'!CQ38,COTIZACIÓN!$O$15:$O$335) -> 0 | CU38: =IFERROR(CT38/CS38,"0") -> 0
B39: BARANDILLA SIN TUBO SUPERIOR | C39: BARANDILLA SIN TUBO SUPERIOR | E39: N.A | CB39: =C39 -> BARANDILLA SIN TUBO SUPERIOR | CC39: 339150 | CQ39: =C39 -> BARANDILLA SIN TUBO SUPERIOR | CR39: LI | CS39: =SUMIF(COTIZACIÓN!$D$15:$L$335,'BD GN'!CQ39,COTIZACIÓN!$L$15:$L$335) -> 0 | CT39: =SUMIF(COTIZACIÓN!$D$15:$O$335,'BD GN'!CQ39,COTIZACIÓN!$O$15:$O$335) -> 0 | CU39: =IFERROR(CT39/CS39,"0") -> 0
B40: BARANDA DE APLIQUE CON ACCESORIOS INOX SIN TUBO SUPERIOR | C40: BARANDA DE APLIQUE CON ACCESORIOS INOX SIN TUBO SUPERIOR | E40: N.A | CB40: =C40 -> BARANDA DE APLIQUE CON ACCESORIOS INOX SIN TUBO SUPERIOR | CC40: 475000 | CQ40: =C40 -> BARANDA DE APLIQUE CON ACCESORIOS INOX SIN TUBO SUPERIOR | CR40: LI | CS40: =SUMIF(COTIZACIÓN!$D$15:$L$335,'BD GN'!CQ40,COTIZACIÓN!$L$15:$L$335) -> 0 | CT40: =SUMIF(COTIZACIÓN!$D$15:$O$335,'BD GN'!CQ40,COTIZACIÓN!$O$15:$O$335) -> 0 | CU40: =IFERROR(CT40/CS40,"0") -> 0
B41: BARANDA DE APLIQUE CON ACCESORIOS INOX CON TUBO SUPERIOR INOX | C41: BARANDA DE APLIQUE CON ACCESORIOS INOX CON TUBO SUPERIOR INOX | E41: N.A | CB41: =C41 -> BARANDA DE APLIQUE CON ACCESORIOS INOX CON TUBO SUPERIOR INOX | CC41: 475000 | CQ41: =C41 -> BARANDA DE APLIQUE CON ACCESORIOS INOX CON TUBO SUPERIOR INOX | CR41: LI | CS41: =SUMIF(COTIZACIÓN!$D$15:$L$335,'BD GN'!CQ41,COTIZACIÓN!$L$15:$L$335) -> 0 | CT41: =SUMIF(COTIZACIÓN!$D$15:$O$335,'BD GN'!CQ41,COTIZACIÓN!$O$15:$O$335) -> 0 | CU41: =IFERROR(CT41/CS41,"0") -> 0
B42: BARANDA DE APLIQUE CON ACCESORIOS INOX CON TUBO SUPERIOR EN ALUMINIO SG | C42: BARANDA DE APLIQUE CON ACCESORIOS INOX CON TUBO SUPERIOR EN ALUMINIO SG | E42: N.A | CB42: =C42 -> BARANDA DE APLIQUE CON ACCESORIOS INOX CON TUBO SUPERIOR EN ALUMINIO SG | CC42: 475000 | CQ42: =C42 -> BARANDA DE APLIQUE CON ACCESORIOS INOX CON TUBO SUPERIOR EN ALUMINIO SG | CR42: LI | CS42: =SUMIF(COTIZACIÓN!$D$15:$L$335,'BD GN'!CQ42,COTIZACIÓN!$L$15:$L$335) -> 0 | CT42: =SUMIF(COTIZACIÓN!$D$15:$O$335,'BD GN'!CQ42,COTIZACIÓN!$O$15:$O$335) -> 0 | CU42: =IFERROR(CT42/CS42,"0") -> 0
B43: FACHADA FLOTANTE LINEA STICK SISTEMA SG101 | C43: FACHADA FLOTANTE LINEA STICK SISTEMA SG101 | E43: N.A | CB43: =C43 -> FACHADA FLOTANTE LINEA STICK SISTEMA SG101 | CQ43: =C43 -> FACHADA FLOTANTE LINEA STICK SISTEMA SG101 | CR43: LA | CS43: =SUMIF(COTIZACIÓN!$D$15:$L$335,'BD GN'!CQ43,COTIZACIÓN!$L$15:$L$335) -> 0 | CT43: =SUMIF(COTIZACIÓN!$D$15:$O$335,'BD GN'!CQ43,COTIZACIÓN!$O$15:$O$335) -> 0 | CU43: =IFERROR(CT43/CS43,"0") -> 0
B44: FACHADA FLOTANTE LINEA STICK SISTEMA SG103 | C44: FACHADA FLOTANTE LINEA STICK SISTEMA SG103 | E44: N.A | CB44: =C44 -> FACHADA FLOTANTE LINEA STICK SISTEMA SG103 | CQ44: =C44 -> FACHADA FLOTANTE LINEA STICK SISTEMA SG103 | CR44: LA | CS44: =SUMIF(COTIZACIÓN!$D$15:$L$335,'BD GN'!CQ44,COTIZACIÓN!$L$15:$L$335) -> 0 | CT44: =SUMIF(COTIZACIÓN!$D$15:$O$335,'BD GN'!CQ44,COTIZACIÓN!$O$15:$O$335) -> 0 | CU44: =IFERROR(CT44/CS44,"0") -> 0
B45: PUERTA BATIENTE LINEA CLASSIC SISTEMA SERIE SG 3890 | C45: PUERTA BATIENTE LINEA CLASSIC SISTEMA SERIE SG 3890 | E45: MANIJA LUJO BASIC | CB45: =C45 -> PUERTA BATIENTE LINEA CLASSIC SISTEMA SERIE SG 3890 | CQ45: =C45 -> PUERTA BATIENTE LINEA CLASSIC SISTEMA SERIE SG 3890 | CR45: LA | CS45: =SUMIF(COTIZACIÓN!$D$15:$L$335,'BD GN'!CQ45,COTIZACIÓN!$L$15:$L$335) -> 0 | CT45: =SUMIF(COTIZACIÓN!$D$15:$O$335,'BD GN'!CQ45,COTIZACIÓN!$O$15:$O$335) -> 0 | CU45: =IFERROR(CT45/CS45,"0") -> 0
B46: PUERTA DOBLE BATIENTE LINEA CLASSIC SISTEMA SERIE SG 3890 | C46: PUERTA DOBLE BATIENTE LINEA CLASSIC SISTEMA SERIE SG 3890 | E46: MANIJA LUJO BASIC | CB46: =C46 -> PUERTA DOBLE BATIENTE LINEA CLASSIC SISTEMA SERIE SG 3890 | CC46: 735000 | CE46: 576000 | CQ46: =C46 -> PUERTA DOBLE BATIENTE LINEA CLASSIC SISTEMA SERIE SG 3890 | CR46: LA | CS46: =SUMIF(COTIZACIÓN!$D$15:$L$335,'BD GN'!CQ46,COTIZACIÓN!$L$15:$L$335) -> 0 | CT46: =SUMIF(COTIZACIÓN!$D$15:$O$335,'BD GN'!CQ46,COTIZACIÓN!$O$15:$O$335) -> 0 | CU46: =IFERROR(CT46/CS46,"0") -> 0
B47: VENTANA CORREDIZA LINEA PREMIUM TIPO EUROPEO SISTEMA VENECIA SERIE 70 | C47: VENTANA CORREDIZA LINEA PREMIUM TIPO EUROPEO VENECIA NAPOLES | E47: CIERRE EMBUTIDO DE IMPACTO AUTOMATICO | CB47: =C47 -> VENTANA CORREDIZA LINEA PREMIUM TIPO EUROPEO VENECIA NAPOLES | CC47: 576000 | CD47: 539000 | CE47: 777000 | CQ47: =C47 -> VENTANA CORREDIZA LINEA PREMIUM TIPO EUROPEO VENECIA NAPOLES | CR47: LA | CS47: =SUMIF(COTIZACIÓN!$D$15:$L$335,'BD GN'!CQ47,COTIZACIÓN!$L$15:$L$335) -> 0 | CT47: =SUMIF(COTIZACIÓN!$D$15:$O$335,'BD GN'!CQ47,COTIZACIÓN!$O$15:$O$335) -> 0 | CU47: =IFERROR(CT47/CS47,"0") -> 0
B48: VENTANA CORREDIZA LINEA CLASSIC SISTEMA PRIMAVERA SERIE SG 5 | C48: VENTANA CORREDIZA LINEA CLASSIC PRIMAVERA LAGO | E48: CIERRE EMBUTIDO DE IMPACTO AUTOMATICO | CB48: =C48 -> VENTANA CORREDIZA LINEA CLASSIC PRIMAVERA LAGO | CC48: 442000 | CE48: 649000 | CQ48: =C48 -> VENTANA CORREDIZA LINEA CLASSIC PRIMAVERA LAGO | CR48: LA | CS48: =SUMIF(COTIZACIÓN!$D$15:$L$335,'BD GN'!CQ48,COTIZACIÓN!$L$15:$L$335) -> 0 | CT48: =SUMIF(COTIZACIÓN!$D$15:$O$335,'BD GN'!CQ48,COTIZACIÓN!$O$15:$O$335) -> 0 | CU48: =IFERROR(CT48/CS48,"0") -> 0
B49: SISTEMA DESLIZANTE TWIN DN | C49: SISTEMA DESLIZANTE TWIN DN | E49: CIERRADURA TWIN DN | CB49: =C49 -> SISTEMA DESLIZANTE TWIN DN | CQ49: =C49 -> SISTEMA DESLIZANTE TWIN DN | CR49: LA | CS49: =SUMIF(COTIZACIÓN!$D$15:$L$335,'BD GN'!CQ49,COTIZACIÓN!$L$15:$L$335) -> 0 | CT49: =SUMIF(COTIZACIÓN!$D$15:$O$335,'BD GN'!CQ49,COTIZACIÓN!$O$15:$O$335) -> 0 | CU49: =IFERROR(CT49/CS49,"0") -> 0
B50: SISTEMA PLEGABLE TAURO | C50: SISTEMA PLEGABLE TAURO | E50: CERRADURA TAURO | CB50: =C50 -> SISTEMA PLEGABLE TAURO | CQ50: =C50 -> SISTEMA PLEGABLE TAURO | CR50: LA | CS50: =SUMIF(COTIZACIÓN!$D$15:$L$335,'BD GN'!CQ50,COTIZACIÓN!$L$15:$L$335) -> 0 | CT50: =SUMIF(COTIZACIÓN!$D$15:$O$335,'BD GN'!CQ50,COTIZACIÓN!$O$15:$O$335) -> 0 | CU50: =IFERROR(CT50/CS50,"0") -> 0
B51: SISTEMA APILABLE SIGMA | C51: SISTEMA APILABLE SIGMA | E51: CERRADURA SIGMA | CB51: =C51 -> SISTEMA APILABLE SIGMA | CQ51: =C51 -> SISTEMA APILABLE SIGMA | CR51: LA | CS51: =SUMIF(COTIZACIÓN!$D$15:$L$335,'BD GN'!CQ51,COTIZACIÓN!$L$15:$L$335) -> 0 | CT51: =SUMIF(COTIZACIÓN!$D$15:$O$335,'BD GN'!CQ51,COTIZACIÓN!$O$15:$O$335) -> 0 | CU51: =IFERROR(CT51/CS51,"0") -> 0
B52: SISTEMA SG CLARABOYA | C52: SISTEMA SG CLARABOYA | E52: N.A | CB52: =C52 -> SISTEMA SG CLARABOYA | CQ52: =C52 -> SISTEMA SG CLARABOYA | CR52: LA | CS52: =SUMIF(COTIZACIÓN!$D$15:$L$335,'BD GN'!CQ52,COTIZACIÓN!$L$15:$L$335) -> 0 | CT52: =SUMIF(COTIZACIÓN!$D$15:$O$335,'BD GN'!CQ52,COTIZACIÓN!$O$15:$O$335) -> 0 | CU52: =IFERROR(CT52/CS52,"0") -> 0
B53: VENTANA CORREDIZA LINEA PREMIUM TIPO EUROPEO SISTEMA VENECIA SERIE 100 | C53: VENTANA CORREDIZA LINEA PREMIUM TIPO EUROPEO VENECIA MONACO | E53: CIERRE EMBUTIDO DE IMPACTO AUTOMATICO | CB53: =C53 -> VENTANA CORREDIZA LINEA PREMIUM TIPO EUROPEO VENECIA MONACO | CC53: 863000 | CQ53: =C53 -> VENTANA CORREDIZA LINEA PREMIUM TIPO EUROPEO VENECIA MONACO | CR53: LA | CS53: =SUMIF(COTIZACIÓN!$D$15:$L$335,'BD GN'!CQ53,COTIZACIÓN!$L$15:$L$335) -> 0 | CT53: =SUMIF(COTIZACIÓN!$D$15:$O$335,'BD GN'!CQ53,COTIZACIÓN!$O$15:$O$335) -> 0 | CU53: =IFERROR(CT53/CS53,"0") -> 0
B54: CUERPO PROYECTANTE LINEA PREMIUM EUROPEO SISTEMA LSA 0932 | C54: CUERPO PROYECTANTE LINEA PREMIUM EUROPEO SISTEMA LSA 0932 | E54: CERRADURA MONO-PUNTO | CB54: =C54 -> CUERPO PROYECTANTE LINEA PREMIUM EUROPEO SISTEMA LSA 0932 | CQ54: =C54 -> CUERPO PROYECTANTE LINEA PREMIUM EUROPEO SISTEMA LSA 0932 | CR54: LA | CS54: =SUMIF(COTIZACIÓN!$D$15:$L$335,'BD GN'!CQ54,COTIZACIÓN!$L$15:$L$335) -> 0 | CT54: =SUMIF(COTIZACIÓN!$D$15:$O$335,'BD GN'!CQ54,COTIZACIÓN!$O$15:$O$335) -> 0 | CU54: =IFERROR(CT54/CS54,"0") -> 0
B55: VENTANA CORREDIZA LINEA PREMIUM EUROPEO SISTEMA LSA 9060 | C55: VENTANA CORREDIZA LINEA PREMIUM EUROPEO SISTEMA LSA 9060 | E55: CERRADURA MONO-PUNTO | CB55: =C55 -> VENTANA CORREDIZA LINEA PREMIUM EUROPEO SISTEMA LSA 9060 | CQ55: =C55 -> VENTANA CORREDIZA LINEA PREMIUM EUROPEO SISTEMA LSA 9060 | CR55: LA | CS55: =SUMIF(COTIZACIÓN!$D$15:$L$335,'BD GN'!CQ55,COTIZACIÓN!$L$15:$L$335) -> 0 | CT55: =SUMIF(COTIZACIÓN!$D$15:$O$335,'BD GN'!CQ55,COTIZACIÓN!$O$15:$O$335) -> 0 | CU55: =IFERROR(CT55/CS55,"0") -> 0
B56: PUERTA CORREDIZA LINEA PREMIUM EUROPEO SISTEMA LSA 9052 | C56: PUERTA CORREDIZA LINEA PREMIUM EUROPEO SISTEMA LSA 9052 | E56: CERRADURA MULTI-PUNTO | CB56: =C56 -> PUERTA CORREDIZA LINEA PREMIUM EUROPEO SISTEMA LSA 9052 | CQ56: =C56 -> PUERTA CORREDIZA LINEA PREMIUM EUROPEO SISTEMA LSA 9052 | CR56: LA | CS56: =SUMIF(COTIZACIÓN!$D$15:$L$335,'BD GN'!CQ56,COTIZACIÓN!$L$15:$L$335) -> 0 | CT56: =SUMIF(COTIZACIÓN!$D$15:$O$335,'BD GN'!CQ56,COTIZACIÓN!$O$15:$O$335) -> 0 | CU56: =IFERROR(CT56/CS56,"0") -> 0
B57: CUERPO FIJO LINEA PREMIUM EUROPEO SISTEMA LSA 0932 | C57: CUERPO FIJO LINEA PREMIUM EUROPEO SISTEMA LSA 0932 | E57: N.A | CB57: =C57 -> CUERPO FIJO LINEA PREMIUM EUROPEO SISTEMA LSA 0932 | CQ57: =C57 -> CUERPO FIJO LINEA PREMIUM EUROPEO SISTEMA LSA 0932 | CR57: LA | CS57: =SUMIF(COTIZACIÓN!$D$15:$L$335,'BD GN'!CQ57,COTIZACIÓN!$L$15:$L$335) -> 0 | CT57: =SUMIF(COTIZACIÓN!$D$15:$O$335,'BD GN'!CQ57,COTIZACIÓN!$O$15:$O$335) -> 0 | CU57: =IFERROR(CT57/CS57,"0") -> 0
B58: VENTANA CORREDIZA LINEA TRADICIONAL SISTEMA SG 5020 | C58: VENTANA CORREDIZA LINEA TRADICIONAL SISTEMA SG 5020 | E58: CERRADURA TIPO DUMMY | CB58: =C58 -> VENTANA CORREDIZA LINEA TRADICIONAL SISTEMA SG 5020 | CQ58: =C58 -> VENTANA CORREDIZA LINEA TRADICIONAL SISTEMA SG 5020 | CR58: LA | CS58: =SUMIF(COTIZACIÓN!$D$15:$L$335,'BD GN'!CQ58,COTIZACIÓN!$L$15:$L$335) -> 0 | CT58: =SUMIF(COTIZACIÓN!$D$15:$O$335,'BD GN'!CQ58,COTIZACIÓN!$O$15:$O$335) -> 0 | CU58: =IFERROR(CT58/CS58,"0") -> 0
B59: PUERTA CORREDIZA LINEA TRADICIONAL SISTEMA SG 744 | C59: PUERTA CORREDIZA LINEA TRADICIONAL SISTEMA SG 744 | E59: CERRADURA TIPO DUMMY | CB59: =C59 -> PUERTA CORREDIZA LINEA TRADICIONAL SISTEMA SG 744 | CQ59: =C59 -> PUERTA CORREDIZA LINEA TRADICIONAL SISTEMA SG 744 | CR59: LA | CS59: =SUMIF(COTIZACIÓN!$D$15:$L$335,'BD GN'!CQ59,COTIZACIÓN!$L$15:$L$335) -> 0 | CT59: =SUMIF(COTIZACIÓN!$D$15:$O$335,'BD GN'!CQ59,COTIZACIÓN!$O$15:$O$335) -> 0 | CU59: =IFERROR(CT59/CS59,"0") -> 0
B60: VENTANA CORREDIZA LINEA TRADICIONAL SISTEMA SG 744 | C60: VENTANA CORREDIZA LINEA TRADICIONAL SISTEMA SG 744 | E60: CERRADURA TIPO DUMMY | CB60: =C60 -> VENTANA CORREDIZA LINEA TRADICIONAL SISTEMA SG 744 | CQ60: =C60 -> VENTANA CORREDIZA LINEA TRADICIONAL SISTEMA SG 744 | CR60: LA | CS60: =SUMIF(COTIZACIÓN!$D$15:$L$335,'BD GN'!CQ60,COTIZACIÓN!$L$15:$L$335) -> 0 | CT60: =SUMIF(COTIZACIÓN!$D$15:$O$335,'BD GN'!CQ60,COTIZACIÓN!$O$15:$O$335) -> 0 | CU60: =IFERROR(CT60/CS60,"0") -> 0
B61: VENTANA CORREDIZA LINEA TRADICIONAL SISTEMA SG 8025 | C61: VENTANA CORREDIZA LINEA TRADICIONAL SISTEMA SG 8025 | E61: CERRADURA TIPO DUMMY | CB61: =C61 -> VENTANA CORREDIZA LINEA TRADICIONAL SISTEMA SG 8025 | CQ61: =C61 -> VENTANA CORREDIZA LINEA TRADICIONAL SISTEMA SG 8025 | CR61: LA | CS61: =SUMIF(COTIZACIÓN!$D$15:$L$335,'BD GN'!CQ61,COTIZACIÓN!$L$15:$L$335) -> 0 | CT61: =SUMIF(COTIZACIÓN!$D$15:$O$335,'BD GN'!CQ61,COTIZACIÓN!$O$15:$O$335) -> 0 | CU61: =IFERROR(CT61/CS61,"0") -> 0
B62: PUERTA CORREDIZA LINEA TRADICIONAL SISTEMA SG 8025 | C62: PUERTA CORREDIZA LINEA TRADICIONAL SISTEMA SG 8025 | E62: CERRADURA TIPO DUMMY | CB62: =C62 -> PUERTA CORREDIZA LINEA TRADICIONAL SISTEMA SG 8025 | CQ62: =C62 -> PUERTA CORREDIZA LINEA TRADICIONAL SISTEMA SG 8025 | CR62: LA | CS62: =SUMIF(COTIZACIÓN!$D$15:$L$335,'BD GN'!CQ62,COTIZACIÓN!$L$15:$L$335) -> 0 | CT62: =SUMIF(COTIZACIÓN!$D$15:$O$335,'BD GN'!CQ62,COTIZACIÓN!$O$15:$O$335) -> 0 | CU62: =IFERROR(CT62/CS62,"0") -> 0
B63: PUERTA CORREDIZA LINEA TRADICIONAL SISTEMA SG 7038 | C63: PUERTA CORREDIZA LINEA TRADICIONAL SISTEMA SG 7038 | E63: CERRADURA TIPO DUMMY | CB63: =C63 -> PUERTA CORREDIZA LINEA TRADICIONAL SISTEMA SG 7038 | CQ63: =C63 -> PUERTA CORREDIZA LINEA TRADICIONAL SISTEMA SG 7038 | CR63: LA | CS63: =SUMIF(COTIZACIÓN!$D$15:$L$335,'BD GN'!CQ63,COTIZACIÓN!$L$15:$L$335) -> 0 | CT63: =SUMIF(COTIZACIÓN!$D$15:$O$335,'BD GN'!CQ63,COTIZACIÓN!$O$15:$O$335) -> 0 | CU63: =IFERROR(CT63/CS63,"0") -> 0
B64: CUERPO FIJO LINEA TRADICIONAL SISTEMA SG 3831 | C64: CUERPO FIJO LINEA TRADICIONAL SISTEMA SG 3831 | E64: N.A | CB64: =C64 -> CUERPO FIJO LINEA TRADICIONAL SISTEMA SG 3831 | CQ64: =C64 -> CUERPO FIJO LINEA TRADICIONAL SISTEMA SG 3831 | CR64: LA | CS64: =SUMIF(COTIZACIÓN!$D$15:$L$335,'BD GN'!CQ64,COTIZACIÓN!$L$15:$L$335) -> 0 | CT64: =SUMIF(COTIZACIÓN!$D$15:$O$335,'BD GN'!CQ64,COTIZACIÓN!$O$15:$O$335) -> 0 | CU64: =IFERROR(CT64/CS64,"0") -> 0
B65: CUERPO PROYECTANTE LINEA TRADICIONAL SISTEMA SG 3831 | C65: CUERPO PROYECTANTE LINEA TRADICIONAL SISTEMA SG 3831 | E65: MANIJA VIRAGE | CB65: =C65 -> CUERPO PROYECTANTE LINEA TRADICIONAL SISTEMA SG 3831 | CQ65: =C65 -> CUERPO PROYECTANTE LINEA TRADICIONAL SISTEMA SG 3831 | CR65: LA | CS65: =SUMIF(COTIZACIÓN!$D$15:$L$335,'BD GN'!CQ65,COTIZACIÓN!$L$15:$L$335) -> 0 | CT65: =SUMIF(COTIZACIÓN!$D$15:$O$335,'BD GN'!CQ65,COTIZACIÓN!$O$15:$O$335) -> 0 | CU65: =IFERROR(CT65/CS65,"0") -> 0
B66: CUERPO FIJO TUBULAR SG | C66: CUERPO FIJO TUBULAR SG | E66: N.A | CB66: =C66 -> CUERPO FIJO TUBULAR SG | CC66: 443000 | CE66: 746000 | CQ66: =C66 -> CUERPO FIJO TUBULAR SG | CR66: LA | CS66: =SUMIF(COTIZACIÓN!$D$15:$L$335,'BD GN'!CQ66,COTIZACIÓN!$L$15:$L$335) -> 0 | CT66: =SUMIF(COTIZACIÓN!$D$15:$O$335,'BD GN'!CQ66,COTIZACIÓN!$O$15:$O$335) -> 0 | CU66: =IFERROR(CT66/CS66,"0") -> 0
B67: SISTEMA PERGOLA SG | C67: SISTEMA PERGOLA SG | E67: N.A | CB67: =C67 -> SISTEMA PERGOLA SG | CQ67: =C67 -> SISTEMA PERGOLA SG | CR67: LA | CS67: =SUMIF(COTIZACIÓN!$D$15:$L$335,'BD GN'!CQ67,COTIZACIÓN!$L$15:$L$335) -> 0 | CT67: =SUMIF(COTIZACIÓN!$D$15:$O$335,'BD GN'!CQ67,COTIZACIÓN!$O$15:$O$335) -> 0 | CU67: =IFERROR(CT67/CS67,"0") -> 0
B68: BARANDA EN BOTELLAS CON ACCESORIOS INOX SIN TUBO SUPERIOR | C68: BARANDA EN BOTELLAS CON ACCESORIOS INOX SIN TUBO SUPERIOR | CQ68: =C68 -> BARANDA EN BOTELLAS CON ACCESORIOS INOX SIN TUBO SUPERIOR | CS68: =SUMIF(COTIZACIÓN!$D$15:$L$335,'BD GN'!CQ68,COTIZACIÓN!$L$15:$L$335) -> 0 | CT68: =SUMIF(COTIZACIÓN!$D$15:$O$335,'BD GN'!CQ68,COTIZACIÓN!$O$15:$O$335) -> 0 | CU68: =IFERROR(CT68/CS68,"0") -> 0
B69: BARANDA EN BOTELLAS CON ACCESORIOS INOX CON TUBO SUPERIOR | C69: BARANDA EN BOTELLAS CON ACCESORIOS INOX CON TUBO SUPERIOR | CQ69: =C69 -> BARANDA EN BOTELLAS CON ACCESORIOS INOX CON TUBO SUPERIOR | CS69: =SUMIF(COTIZACIÓN!$D$15:$L$335,'BD GN'!CQ69,COTIZACIÓN!$L$15:$L$335) -> 0 | CT69: =SUMIF(COTIZACIÓN!$D$15:$O$335,'BD GN'!CQ69,COTIZACIÓN!$O$15:$O$335) -> 0 | CU69: =IFERROR(CT69/CS69,"0") -> 0
CQ70: =C70 -> 0 | CS70: =SUMIF(COTIZACIÓN!$D$15:$L$335,'BD GN'!CQ70,COTIZACIÓN!$L$15:$L$335) -> 0 | CT70: =SUMIF(COTIZACIÓN!$D$15:$O$335,'BD GN'!CQ70,COTIZACIÓN!$O$15:$O$335) -> 0 | CU70: =IFERROR(CT70/CS70,"0") -> 0
CQ71: =C71 -> 0 | CS71: =SUMIF(COTIZACIÓN!$D$15:$L$335,'BD GN'!CQ71,COTIZACIÓN!$L$15:$L$335) -> 0 | CT71: =SUMIF(COTIZACIÓN!$D$15:$O$335,'BD GN'!CQ71,COTIZACIÓN!$O$15:$O$335) -> 0 | CU71: =IFERROR(CT71/CS71,"0") -> 0
CQ72: =C72 -> 0 | CS72: =SUMIF(COTIZACIÓN!$D$15:$L$335,'BD GN'!CQ72,COTIZACIÓN!$L$15:$L$335) -> 0 | CT72: =SUMIF(COTIZACIÓN!$D$15:$O$335,'BD GN'!CQ72,COTIZACIÓN!$O$15:$O$335) -> 0 | CU72: =IFERROR(CT72/CS72,"0") -> 0
CQ73: =C73 -> 0 | CS73: =SUMIF(COTIZACIÓN!$D$15:$L$335,'BD GN'!CQ73,COTIZACIÓN!$L$15:$L$335) -> 0 | CT73: =SUMIF(COTIZACIÓN!$D$15:$O$335,'BD GN'!CQ73,COTIZACIÓN!$O$15:$O$335) -> 0 | CU73: =IFERROR(CT73/CS73,"0") -> 0
CQ74: =C74 -> 0 | CS74: =SUMIF(COTIZACIÓN!$D$15:$L$335,'BD GN'!CQ74,COTIZACIÓN!$L$15:$L$335) -> 0 | CT74: =SUMIF(COTIZACIÓN!$D$15:$O$335,'BD GN'!CQ74,COTIZACIÓN!$O$15:$O$335) -> 0 | CU74: =IFERROR(CT74/CS74,"0") -> 0
CQ75: =C75 -> 0 | CS75: =SUMIF(COTIZACIÓN!$D$15:$L$335,'BD GN'!CQ75,COTIZACIÓN!$L$15:$L$335) -> 0 | CT75: =SUMIF(COTIZACIÓN!$D$15:$O$335,'BD GN'!CQ75,COTIZACIÓN!$O$15:$O$335) -> 0 | CU75: =IFERROR(CT75/CS75,"0") -> 0
CQ76: =C76 -> 0 | CS76: =SUMIF(COTIZACIÓN!$D$15:$L$335,'BD GN'!CQ76,COTIZACIÓN!$L$15:$L$335) -> 0 | CT76: =SUMIF(COTIZACIÓN!$D$15:$O$335,'BD GN'!CQ76,COTIZACIÓN!$O$15:$O$335) -> 0 | CU76: =IFERROR(CT76/CS76,"0") -> 0
CQ77: =C77 -> 0 | CS77: =SUMIF(COTIZACIÓN!$D$15:$L$335,'BD GN'!CQ77,COTIZACIÓN!$L$15:$L$335) -> 0 | CT77: =SUMIF(COTIZACIÓN!$D$15:$O$335,'BD GN'!CQ77,COTIZACIÓN!$O$15:$O$335) -> 0 | CU77: =IFERROR(CT77/CS77,"0") -> 0
CQ78: =C78 -> 0 | CS78: =SUMIF(COTIZACIÓN!$D$15:$L$335,'BD GN'!CQ78,COTIZACIÓN!$L$15:$L$335) -> 0 | CT78: =SUMIF(COTIZACIÓN!$D$15:$O$335,'BD GN'!CQ78,COTIZACIÓN!$O$15:$O$335) -> 0 | CU78: =IFERROR(CT78/CS78,"0") -> 0
CQ79: =C79 -> 0 | CS79: =SUMIF(COTIZACIÓN!$D$15:$L$335,'BD GN'!CQ79,COTIZACIÓN!$L$15:$L$335) -> 0 | CT79: =SUMIF(COTIZACIÓN!$D$15:$O$335,'BD GN'!CQ79,COTIZACIÓN!$O$15:$O$335) -> 0 | CU79: =IFERROR(CT79/CS79,"0") -> 0
CQ80: =C80 -> 0 | CS80: =SUMIF(COTIZACIÓN!$D$15:$L$335,'BD GN'!CQ80,COTIZACIÓN!$L$15:$L$335) -> 0 | CT80: =SUMIF(COTIZACIÓN!$D$15:$O$335,'BD GN'!CQ80,COTIZACIÓN!$O$15:$O$335) -> 0 | CU80: =IFERROR(CT80/CS80,"0") -> 0
CQ81: =C81 -> 0 | CS81: =SUMIF(COTIZACIÓN!$D$15:$L$335,'BD GN'!CQ81,COTIZACIÓN!$L$15:$L$335) -> 0 | CT81: =SUMIF(COTIZACIÓN!$D$15:$O$335,'BD GN'!CQ81,COTIZACIÓN!$O$15:$O$335) -> 0 | CU81: =IFERROR(CT81/CS81,"0") -> 0
... CQ88: =C88 -> 0 | CS88: =SUMIF(COTIZACIÓN!$D$15:$L$335,'BD GN'!CQ88,COTIZACIÓN!$L$15:$L$335) -> 0 | CT88: =SUMIF(COTIZACIÓN!$D$15:$O$335,'BD GN'!CQ88,COTIZACIÓN!$O$15:$O$335) -> 0 | CU88: =IFERROR(CT88/CS88,"0") -> 0

Sheet BD P&G
B2: CONSTRUCTOR Y RESIDENCIAL PREMIUM | H2: CONSTRUCTOR Y RESIDENCIAL CLASSIC
B4: GASTOS DE VENTA | H4: GASTOS DE VENTA
B5: RUBRO | C5: =SUM(C7:C11) -> 21966430 | D5: =SUM(D7:D11) -> 263597160 | E5: =SUM(E7:E11) -> 0.026359716 | F5: OBSERVACIONES | H5: RUBRO | I5: =SUM(I7:I11) -> 6666666.7 | J5: =SUM(J7:J11) -> 80000000 | K5: =SUM(K7:K11) -> 0.02 | L5: OBSERVACIONES
C6: VR MES | D6: VR ANUAL | E6: % PESO PP | I6: VR MES | J6: VR ANUAL | K6: % PESO PP
B7: GASTOS DE PERSONAL | C7: 17866430 | D7: =C7*12 -> 214397160 | E7: =D7/$N$7 -> 0.021439716 | H7: GASTOS DE PERSONAL | I7: 0 | J7: 0 | K7: 0 | N7: 10000000000
B8: COMISIONES | C8: 0 | D8: =C8*12 -> 0 | E8: =D8/$N$7 -> 0 | H8: COMISIONES | I8: 6666666.7 | J8: 80000000 | K8: 0.02
B9: MANTENIMIENTOS VEHICULO | C9: 1100000 | D9: =C9*12 -> 13200000 | E9: =D9/$N$7 -> 0.00132 | H9: MANTENIMIENTOS VEHICULO | I9: 0 | J9: 0 | K9: 0
B10: GASTOS DE VIAJE | C10: 2000000 | D10: =C10*12 -> 24000000 | E10: =D10/$N$7 -> 0.0024 | H10: GASTOS DE VIAJE | I10: 0 | J10: 0 | K10: 0
B11: DIVERSOS (PUBLICIDAD Y MERCADEO | C11: 1000000 | D11: =C11*12 -> 12000000 | E11: =D11/$N$7 -> 0.0012 | H11: DIVERSOS (PUBLICIDAD Y MERCADEO | I11: 0 | J11: 0 | K11: 0
B13: GASTOS ADM | H13: GASTOS ADM
B14: RUBRO | C14: =SUM(C16:C23) -> 22654530 | D14: =SUM(D16:D23) -> 271854360 | E14: =SUM(E16:E23) -> 0.027185436 | F14: OBSERVACIONES | H14: RUBRO | I14: =SUM(I16:I23) -> 0 | J14: =SUM(J16:J23) -> 0 | K14: =SUM(K16:K23) -> 0 | L14: OBSERVACIONES
C15: VR MES | D15: VR ANUAL | E15: % PESO PP | I15: VR MES | J15: VR ANUAL | K15: % PESO PP
B16: GASTOS DE PERSONAL | C16: 6454081 | D16: =C16*12 -> 77448972 | E16: =D16/$N$7 -> 0.0077448972 | F16: AUX CONTABLE | H16: GASTOS DE PERSONAL | I16: 0 | J16: 0 | K16: 0 | L16: AUX CONTABLE
B17: HONORARIOS | C17: 10172000 | D17: =C17*12 -> 122064000 | E17: =D17/$N$7 -> 0.0122064 | H17: HONORARIOS | I17: 0 | J17: 0 | K17: 0
B18: ARRENDAMIENTOS | C18: 2299028 | D18: =C18*12 -> 27588336 | E18: =D18/$N$7 -> 0.0027588336 | H18: ARRENDAMIENTOS | I18: 0 | J18: 0 | K18: 0
B19: SERVICIOS | C19: 688315 | D19: =C19*12 -> 8259780 | E19: =D19/$N$7 -> 0.000825978 | H19: SERVICIOS | I19: 0 | J19: 0 | K19: 0
B20: SEGUROS | C20: 2596106 | D20: =C20*12 -> 31153272 | E20: =D20/$N$7 -> 0.0031153272 | H20: SEGUROS | I20: 0 | J20: 0 | K20: 0
B21: DIVERSOS | C21: 445000 | D21: =C21*12 -> 5340000 | E21: =D21/$N$7 -> 0.000534 | H21: DIVERSOS | I21: 0 | J21: 0 | K21: 0
B22: GASTOS LEGALES | C22: 0 | D22: =C22*12 -> 0 | E22: =D22/$N$7 -> 0 | H22: GASTOS LEGALES | I22: 0 | J22: 0 | K22: 0
B23: ADECUACION E INSTALACION | C23: 0 | D23: =C23*12 -> 0 | E23: =D23/$N$7 -> 0 | H23: ADECUACION E INSTALACION | I23: 0 | J23: 0 | K23: 0
B25: COSTOS INDIRECTOS | H25: COSTOS INDIRECTOS
B26: RUBRO | C26: =SUM(C28:C39) -> 49162117 | D26: =SUM(D28:D39) -> 589945404 | E26: =SUM(E28:E39) -> 0.05899454 | F26: OBSERVACIONES | H26: RUBRO | I26: =SUM(I28:I39) -> 18487784 | J26: =SUM(J28:J39) -> 2.2185341e+08 | K26: =SUM(K28:K39) -> 0.055463352 | L26: OBSERVACIONES
C27: VR MES | D27: VR ANUAL | E27: % PESO PP | I27: VR MES | J27: VR ANUAL | K27: % PESO PP
B28: HONORARIOS ENSAMBLE | C28: 17617879 | D28: =C28*12 -> 211414548 | E28: =D28/$N$7 -> 0.021141455 | F28: SE COMPARA CON COTIZACION | H28: HONORARIOS ENSAMBLE | I28: 12960215 | J28: 1.5552259e+08 | K28: 0.038880646 | L28: SE COMPARA CON COTIZACION
B29: HONORARIOS INSTALACION | C29: 4874425 | D29: =C29*12 -> 58493100 | E29: =D29/$N$7 -> 0.00584931 | H29: HONORARIOS INSTALACION | I29: 2490084.8 | J29: 29881018 | K29: 0.0074702545
B30: HONORARIOS TECNICOS | C30: 17649293 | D30: =C30*12 -> 211791516 | E30: =D30/$N$7 -> 0.021179152
B31: FLETES, TRANSPORTE Y ACARREOS | C31: 0 | D31: =C31*12 -> 0 | E31: =D31/$N$7 -> 0 | F31: COTIZACION | H31: FLETES, TRANSPORTE Y ACARREOS | I31: 0 | J31: 0 | K31: 0 | L31: COTIZACION
B32: ARRENDAMIENTOS | C32: 756250 | D32: =C32*12 -> 9075000 | E32: =D32/$N$7 -> 0.0009075 | H32: ARRENDAMIENTOS | I32: 0 | J32: 0 | K32: 0
B33: SERVICIOS | C33: 1175200 | D33: =C33*12 -> 14102400 | E33: =D33/$N$7 -> 0.00141024 | H33: SERVICIOS | I33: 0 | J33: 0 | K33: 0
B34: MANTENIMIENTO Y REPARACIONES | C34: 400000 | D34: =C34*12 -> 4800000 | E34: =D34/$N$7 -> 0.00048
B35: DEPRECIACION | C35: 4411462 | D35: =C35*12 -> 52937544 | E35: =D35/$N$7 -> 0.0052937544 | H35: DEPRECIACION | I35: 0 | J35: 0 | K35: 0
B36: COMBUSTIBLES | C36: 1400000 | D36: =C36*12 -> 16800000 | E36: =D36/$N$7 -> 0.00168 | H36: COMBUSTIBLES | I36: 1341816 | J36: 16101792 | K36: 0.004025448
B37: UTENSILIOS SST | C37: 877608 | D37: =C37*12 -> 10531296 | E37: =D37/$N$7 -> 0.0010531296 | H37: UTENSILIOS SST | I37: 1695667.6 | J37: 20348011 | K37: 0.0050870027
B38: GASTOS DE REPRESENTACION | C38: 0 | D38: =C38*12 -> 0 | E38: =D38/$N$7 -> 0
B39: EMPAQUE Y CINTA PROTECCION | C39: 0 | D39: =C39*12 -> 0 | E39: =D39/$N$7 -> 0 | F39: COTIZACION | H39: EMPAQUE Y CINTA PROTECCION | I39: 0 | J39: 0 | K39: 0
B41: IMPUESTOS | H41: IMPUESTOS
B42: RUBRO | C42: =SUM(C44:C52) -> 4650000 | D42: =SUM(D44:D52) -> 55800000 | E42: =SUM(E44:E52) -> 0.00558 | F42: OBSERVACIONES | H42: RUBRO | I42: =SUM(I44:I52) -> 2000000 | J42: =SUM(J44:J52) -> 24000000 | K42: =SUM(K44:K52) -> 0.004 | L42: OBSERVACIONES
C43: VR MES | D43: VR ANUAL | E43: % PESO PP | I43: VR MES | J43: VR ANUAL | K43: % PESO PP
B44: INDUSTRIA Y COMERCIO | C44: 4400000 | D44: =C44*12 -> 52800000 | E44: =D44/$N$7 -> 0.00528 | H44: INDUSTRIA Y COMERCIO | I44: 2000000 | J44: 24000000 | K44: 0.004
B45: CAMARA DE COMERCIO | C45: 250000 | D45: =C45*12 -> 3000000 | E45: =D45/$N$7 -> 0.0003 | H45: CAMARA DE COMERCIO | I45: 0 | J45: 0 | K45: 0

Sheet BD M.O
D1: INCREMENTO MANO DE OBRA | E1: 0.2
B2: Ventaneria | C2: SISTEMA | D2: Concepto | E2: Intalación (m2) | F2: Ensamble (2h) | G2: Ensamble (3h) | H2: Ensamble (4h) | I2: Hoja Adic | K2: Intalación (m2) | L2: Ensamble (2h) | M2: Ensamble (3h) | N2: Ensamble (4h) | O2: Hoja Adic
B3: Ventanas y Puertas Corredizas | C3: VENTANA CORREDIZA LINEA TRADICIONAL SISTEMA SG 5020 | D3: Incluye: Lucetas, alfajias, tubulares, cristal, armada de marcos, recibidores y/o seguros. | E3: =+K3+(K3*$E$1) -> 38640 | F3: =+L3+(L3*$E$1) -> 18000 | G3: =+M3+(M3*$E$1) -> 26400 | H3: =+N3+(N3*$E$1) -> 30000 | I3: =+O3+(O3*$E$1) -> 9600 | K3: 32200 | L3: 15000 | M3: 22000 | N3: 25000 | O3: 8000
C4: VENTANA CORREDIZA LINEA TRADICIONAL SISTEMA SG 744 | E4: =+K4+(K4*$E$1) -> 38640 | F4: =+L4+(L4*$E$1) -> 18000 | G4: =+M4+(M4*$E$1) -> 26400 | H4: =+N4+(N4*$E$1) -> 31200 | I4: =+O4+(O4*$E$1) -> 9600 | K4: 32200 | L4: 15000 | M4: 22000 | N4: 26000 | O4: 8000
C5: PUERTA CORREDIZA LINEA TRADICIONAL SISTEMA SG 744 | E5: =+K5+(K5*$E$1) -> 38640 | F5: =+L5+(L5*$E$1) -> 42000 | G5: =+M5+(M5*$E$1) -> 54000 | H5: =+N5+(N5*$E$1) -> 66000 | I5: =+O5+(O5*$E$1) -> 9600 | K5: 32200 | L5: 35000 | M5: 45000 | N5: 55000 | O5: 8000
C6: VENTANA CORREDIZA LINEA TRADICIONAL SISTEMA SG 8025 | E6: =+K6+(K6*$E$1) -> 38640 | F6: =+L6+(L6*$E$1) -> 36000 | G6: =+M6+(M6*$E$1) -> 48000 | H6: =+N6+(N6*$E$1) -> 60000 | I6: =+O6+(O6*$E$1) -> 10800 | K6: 32200 | L6: 30000 | M6: 40000 | N6: 50000 | O6: 9000
C7: PUERTA CORREDIZA LINEA TRADICIONAL SISTEMA SG 8025 | E7: =+K7+(K7*$E$1) -> 38640 | F7: =+L7+(L7*$E$1) -> 42000 | G7: =+M7+(M7*$E$1) -> 54000 | H7: =+N7+(N7*$E$1) -> 66000 | I7: =+O7+(O7*$E$1) -> 10800 | K7: 32200 | L7: 35000 | M7: 45000 | N7: 55000 | O7: 9000
C8: PUERTA CORREDIZA LINEA TRADICIONAL SISTEMA SG 7038 | E8: =+K8+(K8*$E$1) -> 38640 | F8: =+L8+(L8*$E$1) -> 66000 | G8: =+M8+(M8*$E$1) -> 78000 | H8: =+N8+(N8*$E$1) -> 90000 | I8: =+O8+(O8*$E$1) -> 12000 | K8: 32200 | L8: 55000 | M8: 65000 | N8: 75000 | O8: 10000
C9: VENTANA CORREDIZA LINEA CLASSIC SISTEMA PRIMAVERA SERIE SG 3 | E9: =+K9+(K9*$E$1) -> 38640 | F9: =+L9+(L9*$E$1) -> 22800 | G9: =+M9+(M9*$E$1) -> 26400 | H9: =+N9+(N9*$E$1) -> 31200 | I9: =+O9+(O9*$E$1) -> 9600 | K9: 32200 | L9: 19000 | M9: 22000 | N9: 26000 | O9: 8000
C10: VENTANA CORREDIZA LINEA CLASSIC PRIMAVERA LAGO | E10: =+K10+(K10*$E$1) -> 38640 | F10: =+L10+(L10*$E$1) -> 22800 | G10: =+M10+(M10*$E$1) -> 26400 | H10: =+N10+(N10*$E$1) -> 31200 | I10: =+O10+(O10*$E$1) -> 9600 | K10: 32200 | L10: 19000 | M10: 22000 | N10: 26000 | O10: 8000
C11: PUERTA CORREDIZA LINEA CLASSIC PRIMAVERA LAGO | E11: =+K11+(K11*$E$1) -> 38640 | F11: =+L11+(L11*$E$1) -> 30000 | G11: =+M11+(M11*$E$1) -> 32400 | H11: =+N11+(N11*$E$1) -> 39600 | I11: =+O11+(O11*$E$1) -> 10800 | K11: 32200 | L11: 25000 | M11: 27000 | N11: 33000 | O11: 9000
C12: PUERTA CORREDIZA LINEA CLASSIC PRIMAVERA LUCCA | E12: =+K12+(K12*$E$1) -> 38640 | F12: =+L12+(L12*$E$1) -> 26400 | G12: =+M12+(M12*$E$1) -> 32400 | H12: =+N12+(N12*$E$1) -> 39600 | I12: =+O12+(O12*$E$1) -> 10800 | K12: 32200 | L12: 22000 | M12: 27000 | N12: 33000 | O12: 9000
C13: PUERTA CORREDIZA LINEA CLASSIC SISTEMA 8025 | E13: =+K13+(K13*$E$1) -> 38640 | F13: =+L13+(L13*$E$1) -> 26400 | G13: =+M13+(M13*$E$1) -> 32400 | H13: =+N13+(N13*$E$1) -> 39600 | I13: =+O13+(O13*$E$1) -> 10800 | K13: 32200 | L13: 22000 | M13: 27000 | N13: 33000 | O13: 9000
C14: VENTANA CORREDIZA LINEA PREMIUM EUROPEO SISTEMA LSA 9060 | E14: =+K14+(K14*$E$1) -> 38640 | F14: =+L14+(L14*$E$1) -> 26400 | G14: =+M14+(M14*$E$1) -> 32400 | H14: =+N14+(N14*$E$1) -> 39600 | I14: =+O14+(O14*$E$1) -> 10800 | K14: 32200 | L14: 22000 | M14: 27000 | N14: 33000 | O14: 9000
C15: VENTANA CORREDIZA LINEA PREMIUM TIPO EUROPEO VENECIA MONZA | E15: =+K15+(K15*$E$1) -> 38640 | F15: =+L15+(L15*$E$1) -> 26400 | G15: =+M15+(M15*$E$1) -> 32400 | H15: =+N15+(N15*$E$1) -> 39600 | I15: =+O15+(O15*$E$1) -> 10800 | K15: 32200 | L15: 22000 | M15: 27000 | N15: 33000 | O15: 9000
B16: Ventanas Proyectantes | C16: CUERPO PROYECTANTE LINEA PREMIUM TIPO EUROPEO VENECIA FERMO | D16: Sistemas combinados de naves y fijos, Incluye cuadre de accesorios. | E16: =+K16+(K16*$E$1) -> 38640 | F16: =+L16+(L16*$E$1) -> 26400 | G16: =+M16+(M16*$E$1) -> 31200 | H16: =+N16+(N16*$E$1) -> 36000 | I16: =+O16+(O16*$E$1) -> 10800 | K16: 32200 | L16: 22000 | M16: 26000 | N16: 30000 | O16: 9000
C17: CUERPO BATIENTE LINEA PREMIUM TIPO EUROPEO VENECIA FERMO | E17: =+K17+(K17*$E$1) -> 38640 | F17: =+L17+(L17*$E$1) -> 26400 | G17: =+M17+(M17*$E$1) -> 31200 | H17: =+N17+(N17*$E$1) -> 36000 | I17: =+O17+(O17*$E$1) -> 10800 | K17: 32200 | L17: 22000 | M17: 26000 | N17: 30000 | O17: 9000
C18: CUERPO PROYECTANTE LINEA PREMIUM EUROPEO SISTEMA LSA 0932 | E18: =+K18+(K18*$E$1) -> 38640 | F18: =+L18+(L18*$E$1) -> 26400 | G18: =+M18+(M18*$E$1) -> 31200 | H18: =+N18+(N18*$E$1) -> 36000 | I18: =+O18+(O18*$E$1) -> 10800 | K18: 32200 | L18: 22000 | M18: 26000 | N18: 30000 | O18: 9000
C19: CUERPO BATIENTE LINEA CLASSIC PRIMAVERA SIENA | E19: =+K19+(K19*$E$1) -> 38640 | F19: =+L19+(L19*$E$1) -> 26400 | G19: =+M19+(M19*$E$1) -> 31200 | H19: =+N19+(N19*$E$1) -> 36000 | I19: =+O19+(O19*$E$1) -> 10800 | K19: 32200 | L19: 22000 | M19: 26000 | N19: 30000 | O19: 9000
C20: CUERPO PROYECTANTE LINEA CLASSIC PRIMAVERA SIENA | E20: =+K20+(K20*$E$1) -> 38640 | F20: =+L20+(L20*$E$1) -> 26400 | G20: =+M20+(M20*$E$1) -> 31200 | H20: =+N20+(N20*$E$1) -> 36000 | I20: =+O20+(O20*$E$1) -> 10800 | K20: 32200 | L20: 22000 | M20: 26000 | N20: 30000 | O20: 9000
C21: CUERPO PROYECTANTE LINEA CLASSIC SISTEMA 3831 | E21: =+K21+(K21*$E$1) -> 38640 | F21: =+L21+(L21*$E$1) -> 42000 | G21: =+M21+(M21*$E$1) -> 48000 | H21: =+N21+(N21*$E$1) -> 54000 | I21: =+O21+(O21*$E$1) -> 10800 | K21: 32200 | L21: 35000 | M21: 40000 | N21: 45000 | O21: 9000
B22: Ventanas Fijas | C22: CUERPO FIJO LINEA PREMIUM TIPO EUROPEO VENECIA FERMO | D22: Incluye: Lucetas, alfajias, tubulares, cristal, armada de marcos, recibidores y/o seguros. Hasta 3 m2 | E22: =+K22+(K22*$E$1) -> 38640 | F22: =+L22+(L22*$E$1) -> 16800 | G22: =+M22+(M22*$E$1) -> 21600 | H22: =+N22+(N22*$E$1) -> 26400 | I22: =+O22+(O22*$E$1) -> 10800 | K22: 32200 | L22: 14000 | M22: 18000 | N22: 22000 | O22: 9000
C23: CUERPO FIJO LINEA CLASSIC PRIMAVERA SIENA | E23: =+K23+(K23*$E$1) -> 38640 | F23: =+L23+(L23*$E$1) -> 16800 | G23: =+M23+(M23*$E$1) -> 21600 | H23: =+N23+(N23*$E$1) -> 26400 | I23: =+O23+(O23*$E$1) -> 10800 | K23: 32200 | L23: 14000 | M23: 18000 | N23: 22000 | O23: 9000
C24: CUERPO FIJO TUBULAR SG | E24: =+K24+(K24*$E$1) -> 38640 | F24: =+L24+(L24*$E$1) -> 16800 | G24: =+M24+(M24*$E$1) -> 21600 | H24: =+N24+(N24*$E$1) -> 26400 | I24: =+O24+(O24*$E$1) -> 10800 | K24: 32200 | L24: 14000 | M24: 18000 | N24: 22000 | O24: 9000
C25: CUERPO FIJO LINEA PREMIUM EUROPEO SISTEMA LSA 0932 | E25: =+K25+(K25*$E$1) -> 38640 | F25: =+L25+(L25*$E$1) -> 16800 | G25: =+M25+(M25*$E$1) -> 21600 | H25: =+N25+(N25*$E$1) -> 26400 | I25: =+O25+(O25*$E$1) -> 10800 | K25: 32200 | L25: 14000 | M25: 18000 | N25: 22000 | O25: 9000
C26: CUERPO FIJO LINEA CLASSIC SISTEMA PRIMAVERA SERIE SG 3 | E26: =+K26+(K26*$E$1) -> 38640 | F26: =+L26+(L26*$E$1) -> 16800 | G26: =+M26+(M26*$E$1) -> 21600 | H26: =+N26+(N26*$E$1) -> 26400 | I26: =+O26+(O26*$E$1) -> 10800 | K26: 32200 | L26: 14000 | M26: 18000 | N26: 22000 | O26: 9000
C27: SISTEMA REJILLA | E27: =+K27+(K27*$E$1) -> 38640 | F27: =+L27+(L27*$E$1) -> 16800 | G27: =+M27+(M27*$E$1) -> 21600 | H27: =+N27+(N27*$E$1) -> 26400 | I27: =+O27+(O27*$E$1) -> 10800 | K27: 32200 | L27: 14000 | M27: 18000 | N27: 22000 | O27: 9000
C28: SISTEMA SG CLARABOYA | E28: =+K28+(K28*$E$1) -> 38640 | F28: =+L28+(L28*$E$1) -> 16800 | G28: =+M28+(M28*$E$1) -> 21600 | H28: =+N28+(N28*$E$1) -> 26400 | I28: =+O28+(O28*$E$1) -> 10800 | K28: 32200 | L28: 14000 | M28: 18000 | N28: 22000 | O28: 9000
C29: CUERPO FIJO LINEA CLASSIC SISTEMA 3831 | E29: =+K29+(K29*$E$1) -> 38640 | F29: =+L29+(L29*$E$1) -> 16800 | G29: =+M29+(M29*$E$1) -> 21600 | H29: =+N29+(N29*$E$1) -> 26400 | I29: =+O29+(O29*$E$1) -> 10800 | K29: 32200 | L29: 14000 | M29: 18000 | N29: 22000 | O29: 9000
B30: DIVISIONES DE BAÑO | C30: DIVISIONES DE BAÑO CON ACCESORIOS EN ACERO INOXIDABLE | D30: Sistemas de lujo (cristal templado y accesorios), Corredizos y Embisagrados INOX | E30: =+K30+(K30*$E$1) -> 38640 | K30: 32200
B31: PUERTAS CORREDIZAS | C31: PUERTA CORREDIZA LINEA PREMIUM TIPO EUROPEO VENECIA NAPOLES | D31: Incluye: Lucetas, alfajias, tubulares, cristal, armada de marcos, recibidores y/o seguros. | E31: =+K31+(K31*$E$1) -> 38640 | F31: =+L31+(L31*$E$1) -> 55200 | G31: =+M31+(M31*$E$1) -> 69600 | H31: =+N31+(N31*$E$1) -> 84000 | I31: =+O31+(O31*$E$1) -> 31200 | K31: 32200 | L31: 46000 | M31: 58000 | N31: 70000 | O31: 26000
C32: VENTANA CORREDIZA LINEA PREMIUM TIPO EUROPEO VENECIA NAPOLES | E32: =+K32+(K32*$E$1) -> 38640 | F32: =+L32+(L32*$E$1) -> 55200 | G32: =+M32+(M32*$E$1) -> 69600 | H32: =+N32+(N32*$E$1) -> 84000 | I32: =+O32+(O32*$E$1) -> 31200 | K32: 32200 | L32: 46000 | M32: 58000 | N32: 70000 | O32: 26000
C33: PUERTA CORREDIZA LINEA PREMIUM TIPO EUROPEO VENECIA NAPOLES TIPO POKET | E33: =+K33+(K33*$E$1) -> 38640 | F33: =+L33+(L33*$E$1) -> 55200 | G33: =+M33+(M33*$E$1) -> 69600 | H33: =+N33+(N33*$E$1) -> 84000 | I33: =+O33+(O33*$E$1) -> 31200 | K33: 32200 | L33: 46000 | M33: 58000 | N33: 70000 | O33: 26000
C34: PUERTA CORREDIZA LINEA PREMIUM EUROPEO SISTEMA LSA 9052 | E34: =+K34+(K34*$E$1) -> 38640 | F34: =+L34+(L34*$E$1) -> 60000 | G34: =+M34+(M34*$E$1) -> 78000 | H34: =+N34+(N34*$E$1) -> 96000 | I34: =+O34+(O34*$E$1) -> 31200 | K34: 32200 | L34: 50000 | M34: 65000 | N34: 80000 | O34: 26000
C35: PUERTA CORREDIZA LINEA PREMIUM TIPO EUROPEO VENECIA MONACO | E35: =+K35+(K35*$E$1) -> 38640 | F35: =+L35+(L35*$E$1) -> 60000 | G35: =+M35+(M35*$E$1) -> 78000 | H35: =+N35+(N35*$E$1) -> 96000 | I35: =+O35+(O35*$E$1) -> 31200 | K35: 32200 | L35: 50000 | M35: 65000 | N35: 80000 | O35: 26000
B36: Puertas con marco de aluminio, no corredizas | C36: PUERTA BATIENTE LINEA PREMIUM TIPO EUROPEO VENECIA FERMO | D36: Sistemas colgante, plegable, embisagrada y pivotantes | E36: =+K36+(K36*$E$1) -> 38640 | F36: =+L36+(L36*$E$1) -> 72000 | G36: =+M36+(M36*$E$1) -> 114000 | H36: =+N36+(N36*$E$1) -> 150000 | I36: =+O36+(O36*$E$1) -> 10800 | K36: 32200 | L36: 60000 | M36: 95000 | N36: 125000 | O36: 9000
C37: PUERTA DOBLE BATIENTE LINEA PREMIUM TIPO EUROPEO VENECIA FERMO | E37: =+K37+(K37*$E$1) -> 38640 | F37: =+L37+(L37*$E$1) -> 72000 | G37: =+M37+(M37*$E$1) -> 114000 | H37: =+N37+(N37*$E$1) -> 150000 | I37: =+O37+(O37*$E$1) -> 10800 | K37: 32200 | L37: 60000 | M37: 95000 | N37: 125000 | O37: 9000
C38: PUERTA BATIENTE LINEA CLASSIC PRIMAVERA SIENA | E38: =+K38+(K38*$E$1) -> 38640 | F38: =+L38+(L38*$E$1) -> 60000 | G38: =+M38+(M38*$E$1) -> 105600 | H38: =+N38+(N38*$E$1) -> 117600 | I38: =+O38+(O38*$E$1) -> 10800 | K38: 32200 | L38: 50000 | M38: 88000 | N38: 98000 | O38: 9000
C39: PUERTA DOBLE BATIENTE LINEA CLASSIC SISTEMA SERIE SG 3890 | E39: =+K39+(K39*$E$1) -> 38640 | F39: =+L39+(L39*$E$1) -> 60000 | G39: =+M39+(M39*$E$1) -> 105600 | H39: =+N39+(N39*$E$1) -> 117600 | I39: =+O39+(O39*$E$1) -> 10800 | K39: 32200 | L39: 50000 | M39: 88000 | N39: 98000 | O39: 9000
C40: PUERTA BATIENTE LINEA CLASSIC SISTEMA SERIE SG 3890 | E40: =+K40+(K40*$E$1) -> 38640 | F40: =+L40+(L40*$E$1) -> 60000 | G40: =+M40+(M40*$E$1) -> 105600 | H40: =+N40+(N40*$E$1) -> 117600 | I40: =+O40+(O40*$E$1) -> 10800 | K40: 32200 | L40: 50000 | M40: 88000 | N40: 98000 | O40: 9000
B41: PASAMANOS | C41: BARANDA DE APLIQUE CON ACCESORIOS INOX SIN TUBO SUPERIOR | D41: incluye vidrio o barandillas, epoxico y anclajes) | E41: =+K41+(K41*$E$1) -> 45540 | K41: 37950
C42: BARANDA DE APLIQUE CON ACCESORIOS INOX CON TUBO SUPERIOR INOX | E42: =+K42+(K42*$E$1) -> 45540 | K42: 37950
C43: BARANDA DE APLIQUE CON ACCESORIOS INOX CON TUBO SUPERIOR EN ALUMINIO SG | E43: =+K43+(K43*$E$1) -> 45540 | K43: 37950
C44: BARANDA EMBEBIDA SIN TUBO SUPERIOR | E44: =+K44+(K44*$E$1) -> 45540 | K44: 37950
C45: BARANDA EMBEBIDA CON TUBO SUPERIOR EN INOX | E45: =+K45+(K45*$E$1) -> 45540 | K45: 37950
C46: BARANDA EMBEBIDA CON TUBO SUPERIOR EN ALUMINIO SG | E46: =+K46+(K46*$E$1) -> 45540 | K46: 37950
C47: BARANDILLA CON TUBO SUPERIOR EN INOX | E47: =+K47+(K47*$E$1) -> 51060 | K47: 42550
C48: BARANDILLA SIN TUBO SUPERIOR | E48: =+K48+(K48*$E$1) -> 51060 | K48: 42550
C49: BARANDA EN BOTELLAS CON ACCESORIOS INOX SIN TUBO SUPERIOR | E49: =+K49+(K49*$E$1) -> 45540 | K49: 37950
C50: BARANDA EN BOTELLAS CON ACCESORIOS INOX CON TUBO SUPERIOR | E50: =+K50+(K50*$E$1) -> 45540 | K50: 37950
B51: SISTEMAS CON ACCESORIOS EN ACERO INOX | C51: PUERTA CORREDIZA CON ACCESIORIOS INOX | D51: Incluye Cristal Templado, Zócalo, Accesorios, bisagras hidraulicas, pivotes, manijas, cerraduras, cajas y todo elemento que lleve Hasta cristal de 10mm | E51: =+K51+(K51*$E$1) -> 45540 | K51: 37950
C52: CUERPO FIJO CON ACCESORIOS INOX | E52: =+K52+(K52*$E$1) -> 45540 | K52: 37950
C53: PUERTA BATIENTE CON ACCESORIOS INOX | E53: =+K53+(K53*$E$1) -> 45540 | K53: 37950
C54: SISTEMA DESLIZANTE TWIN DN | E54: =+K54+(K54*$E$1) -> 45540 | K54: 37950
C55: SISTEMA PLEGABLE TAURO | E55: =+K55+(K55*$E$1) -> 45540 | K55: 37950
C56: SISTEMA APILABLE SIGMA | E56: =+K56+(K56*$E$1) -> 45540 | K56: 37950
C57: PUERTA DOBLE BATIENTE CON ACCESORIOS INOX | E57: =+K57+(K57*$E$1) -> 45540 | K57: 37950
F58: Ensamble (m2) | L58: Ensamble (m2)
B59: FACHADAS | C59: FACHADA FLOTANTE LINEA STICK SISTEMA SG45 TAPA Y PISAVIDRIO | D59: con horizontales y verticales a la vista, silicona perimetral y en uniones, anclajes, chazos expansivos, tornos, basculantes o cualquier apertura o ventilación, rejillas, niveles, plomos, cortafuego estándar con lata inferior, lana, tubo adicional, con chapeta deslizable. | E59: =+K59+(K59*$E$1) -> 50646 | F59: =+L59+(L59*$E$1) -> 14400 | K59: 42205 | L59: 12000
C60: FACHADA ENTRE PLACAS LINEA STICK SISTEMA SG45 TAPA Y PISAVIDRIO | D60: con horizontales y verticales a la vista, silicona perimetral y en uniones, anclajes, chazos expansivos, tornos, basculantes o cualquier apertura o ventilación, rejillas, niveles, plomos, cortafuego estándar con lata inferior, lana, tubo adicional, con chapeta deslizable. | E60: =+K60+(K60*$E$1) -> 50646 | F60: =+L60+(L60*$E$1) -> 14400 | K60: 42205 | L60: 12000
C61: FACHADA FLOTANTE LINEA STICK SISTEMA S&G45 PIEL DE VIDRIO | D61: con siliconas en las juntas obligatorio, (Incluye: Tapas sellos totales, silicona perimetral y en uniones, anclajes, chazos expansivos, tornos, basculantes o cualquier apertura o ventilació, rejillas, niveles, plomos, cortafuego estándar con lata inferior, lana, tubo adicional, con chapeta deslizable. | E61: =+K61+(K61*$E$1) -> 50646 | F61: =+L61+(L61*$E$1) -> 36000 | K61: 42205 | L61: 30000
C62: FACHADA ENTRE PLACAS LINEA STICK SISTEMA S&G45 PIEL DE VIDRIO | D62: con siliconas en las juntas obligatorio, (Incluye: Tapas sellos totales, silicona perimetral y en uniones, anclajes, chazos expansivos, tornos, basculantes o cualquier apertura o ventilació, rejillas, niveles, plomos, cortafuego estándar con lata inferior, lana, tubo adicional, con chapeta deslizable. | E62: =+K62+(K62*$E$1) -> 50646 | F62: =+L62+(L62*$E$1) -> 36000 | K62: 42205 | L62: 30000
C63: FACHADA FLOTANTE LINEA STICK SISTEMA SG101 | D63: con siliconas en las juntas obligatorio, (Incluye: Tapas sellos totales, silicona perimetral y en uniones, anclajes, chazos expansivos, tornos, basculantes o cualquier apertura o ventilació, rejillas, niveles, plomos, cortafuego estándar con lata inferior, lana, tubo adicional, con chapeta deslizable. | E63: =+K63+(K63*$E$1) -> 50646 | F63: =+L63+(L63*$E$1) -> 14400 | K63: 42205 | L63: 12000
C64: SISTEMA PERGOLA SG | E64: =+K64+(K64*$E$1) -> 45540 | F64: =+L64+(L64*3.5%) -> 0 | K64: 37950
C65: FACHADA FLOTANTE LINEA STICK SISTEMA SG103 | D65: con siliconas en las juntas obligatorio, (Incluye: Tapas sellos totales, silicona perimetral y en uniones, anclajes, chazos expansivos, tornos, basculantes o cualquier apertura o ventilació, rejillas, niveles, plomos, cortafuego estándar con lata inferior, lana, tubo adicional, con chapeta deslizable. | E65: =+K65+(K65*$E$1) -> 50646 | F65: =+L65+(L65*$E$1) -> 14400 | K65: 42205 | L65: 12000

Sheet COTIZACIÓN
BP2: BACKOFFICE OPERATIVO | BX2: VIATICOS | CF2: TRANSPORTES INTERMUNICIPALES
BP3: PARTICIPA | BQ3: VR SALARIO | BR3: VR PRESTACIONES | BS3: VR DIA | BT3: % CARGA | BU3: OCUPACIÓN DIAS | BV3: VR ACTIVIDAD | BX3: CIUDAD | BY3: VR DÍA ALIMENTACIÓN | BZ3: VR HAB, MOVILIZACION | CA3: VR DÍA | CB3: Nº DÍAS | CC3: VR TOTAL ALIMENTACIÓN | CD3: VR TOTAL HAB | CF3: CIUDAD | CG3: VR IDA Y VUELTA | CH3: Nº RETORNOS | CI3: VR TOTAL
N4: CODIGO | O4: FPP 002 | BP4: SISO | BQ4: =VLOOKUP(BP4,[1]Hoja1!$AE$5:$AH$93,2,FALSE) -> 1500000 | BR4: =BQ4*40% -> 600000 | BS4: =(BQ4+BR4)/20 -> 105000 | BU4: =IFERROR(ROUNDUP(BT14,0),"") -> 8 | BV4: =BS4*BU4*BT4 -> 0 | BX4: BGA | BY4: =VLOOKUP(BX4,[1]Hoja1!$AR$5:$AU$559,2,FALSE) -> 0 | BZ4: =VLOOKUP(BX4,[1]Hoja1!$AR$5:$AU$559,3,FALSE) -> 0 | CA4: =VLOOKUP(BX4,[1]Hoja1!$AR$5:$AU$559,4,FALSE) -> 0 | CC4: =BY4*CB4 -> 0 | CD4: =BZ4*CB4 -> 0 | CF4: BGA | CG4: =VLOOKUP(CF4,[1]Hoja1!$AW$5:$AX$1333,2,FALSE) -> 10000 | CI4: =CG4*CH4 -> 0 | CU4: RESUMEN
N5: VERSION | O5: V1 | BP5: MONTAJE | BQ5: 1700000 | BR5: =BQ5*40% -> 680000 | BS5: =(BQ5+BR5)/20 -> 119000 | BU5: =IFERROR(ROUNDUP(BT14,0),"") -> 8 | BV5: =BS5*BU5*BT5 -> 0 | BX5: BTA | BY5: =VLOOKUP(BX5,'BD GN'!BT:BW,2,FALSE) -> 45000 | BZ5: 65000 | CA5: =VLOOKUP(BX5,'BD GN'!BT:BW,4,FALSE) -> 110000 | CC5: =BY5*CB5 -> 0 | CD5: =BZ5*CB5 -> 0 | CF5: BTA | CG5: =VLOOKUP(CF5,[1]Hoja1!$AW$5:$AX$1333,2,FALSE) -> 180000 | CI5: =CG5*CH5 -> 0 | CU5: VR CONTRATO | CW5: 0 | CY5: VR EJECUTADO | DA5: =DB13 -> 0 | DC5: =IFERROR(DA5/$CW$9,"0%") -> 0%
N6: FECHA | O6: 44579 | BX6: ANTQ | BY6: =VLOOKUP(BX6,'BD GN'!BT:BW,2,FALSE) -> 45000 | BZ6: 65000 | CA6: =VLOOKUP(BX6,'BD GN'!BT:BW,4,FALSE) -> 110000 | CC6: =BY6*CB6 -> 0 | CD6: =BZ6*CB6 -> 0 | CF6: ANTQ | CG6: =VLOOKUP(CF6,'BD GN'!BY:BZ,2,FALSE) -> 280000 | CI6: =CG6*CH6 -> 0 | CU6: VR MODIFICACIONES | CW6: =(O343-CW5) -> 0 | CY6: VR PTE EJECUCION | DA6: =DD13 -> 0 | DC6: =IFERROR(DA6/$CW$9,"0%") -> 0%
A7: PROPUESTA ECONOMICA | N7: ELABORO | O7: ING ANDRES C. | Q7: CENTRO DE COSTOS UNT | AM7: CENTRO DE COSTOS TOTALES | BB7: CORTE 1 | BC7: V1 | BP7: M2 | BR7: VR | BX7: CALI | BY7: =VLOOKUP(BX7,'BD GN'!BT:BW,2,FALSE) -> 45000 | BZ7: 65000 | CA7: =VLOOKUP(BX7,'BD GN'!BT:BW,4,FALSE) -> 110000 | CC7: =BY7*CB7 -> 0 | CD7: =BZ7*CB7 -> 0 | CF7: CALI | CG7: =VLOOKUP(CF7,'BD GN'!BY:BZ,2,FALSE) -> 320000 | CI7: =CG7*CH7 -> 0 | CU7: VR ADICIONALES | CW7: =O1432 -> 0 | CY7: VR PAGADO | DA7: 0 | DC7: =IFERROR(DA7/$CW$9,"0%") -> 0%
N8: APROBO | O8: JUNTA D. | BP8: 0 | BQ8: 200 | BR8: 26000 | BX8: COSTA | BY8: =VLOOKUP(BX8,'BD GN'!BT:BW,2,FALSE) -> 45000 | BZ8: 65000 | CA8: =VLOOKUP(BX8,'BD GN'!BT:BW,4,FALSE) -> 110000 | CC8: =BY8*CB8 -> 0 | CD8: =BZ8*CB8 -> 0 | CF8: COSTA | CG8: =VLOOKUP(CF8,'BD GN'!BY:BZ,2,FALSE) -> 350000 | CI8: =CG8*CH8 -> 0 | CU8: VR ELIMINADOS | CW8: 0 | CY8: VR FACTURADO | DA8: 0 | DC8: =IFERROR(DA8/$CW$9,"0%") -> 0%
BB9: CORTE 2 | BC9: V2 | BF9: VIS | BG9: NO | BP9: 201 | BQ9: 550 | BR9: 13000 | CU9: VR FINAL | CW9: =CW5+CW6+CW7 -> 0 | CY9: VR PTE PAGO | DA9: =DA5-DA7 -> 0 | DC9: =IFERROR(DA9/$CW$9,"0%") -> 0%
A10: CLIENTE | E10: VERSIÓN | M10: ID PRESUPUESTO | BB10: CORTE 3 | BC10: V3 | BP10: 551 | BQ10: >1000 | BR10: 7000 | BU10: VR BACK ADM | BX10: NOTA. SI EL PROYECTO ES FUERA DE BGA SE DEBE CONTEMPLAR LOS VIATICOS DEL SUPERVISOR DE MONTAJE POR EL TIEMPO QUE DURE EL MISMO | CG10: Nº PERSONAS | CH10: VR VIATICOS | CI10: VR VIATICOS M2
A11: PROYECTO | E11: LINEA PRODUCCION | I11: ACORDADA | M11: FECHA ELABORACIÓN | O11: =+TODAY() -> 46203 | BB11: CORTE 4 | BC11: V4 | BF11: CINTA DE PROTECCIÓN | BG11: UNA CARA | BU11: =+IF(F339<=200,BR8,IF(AND(F339>200,F339<=550),BR9,BR10)) -> 26000 | CH11: =(SUM(CC4:CC8)+SUM(CD4:CD8)+SUM(CI4:CI8))*CG11 -> 0 | CI11: =IFERROR(CH11/F339,"")
A12: UBICACIÓN | E12: ELABORADO POR | I12: IVAN CANDELA | M12: VALIDEZ DE OFERTA | O12: 5 DIAS C | Q12: COSTO MATERIA PRIMA | T12: COSTO LOGÍSTICO | W12: M.O | AB12: COSTO ADM | AG12: COSTO VENTA | AM12: COSTO MATERIA PRIMA | AP12: COSTO LOGISTICO | AT12: M.O | AV12: COSTO ADM | AX12: PRECIO VENTA | BB12: CORTE 5 | BC12: V5 | BE12: INSUMOS VARIOS | BJ12: TRANSPORTE | BP12: TIEMPOS TEORICOS | CG12: MATERIALES Y EQUIPOS | CI12: VR MAT Y EQU M2 | CK12: PROCESO EJECUCION | CU12: CORTE 1 | CW12: CORTE 2 | CY12: CORTE 3 | DA12: LIQUIDADO | DC12: PTE X LIQUIDAR | DG12: RAD | DH12: CANTIDAD | DI12: SUBTOTAL | DJ12: TOTAL | DK12: ALU | DL12: ACC | DM12: VIDRIO | DN12: TRANSPORTE | DO12: VIATICOS | DP12: BACKOFFICE | DQ12: GAST VENTA | DR12: GAST FINANC | DS12: COSTOS IND | DT12: ENSAMBLE | DU12: INSTALACION | DV12: M2 INOX | DW12: M2 ALU | DX12: VR INOX | DY12: VR ALU
T13: 0.14 | U13: EMPQ | V13: TRANS | W13: LISTA PRECIOS | Y13: ='BD P&G'!E28+'BD P&G'!E30 -> 0.042320606 | Z13: ='BD P&G'!E29 -> 0.00584931 | AB13: 0.02 | AC13: IMPREV PYG | AD13: BACKOFFICE | AE13: ='BD P&G'!E7+'BD P&G'!E9+'BD P&G'!E10+'BD P&G'!E11+'BD P&G'!E16+'BD P&G'!E17+'BD P&G'!E18+'BD P&G'!E19+'BD P&G'!E20+'BD P&G'!E21+'BD P&G'!E22+'BD P&G'!E23+'BD P&G'!E32+'BD P&G'!E33+'BD P&G'!E34+'BD P&G'!E35+'BD P&G'!E36+'BD P&G'!E37+'BD P&G'!E38+'BD P&G'!E39 -> 0.064369776 | AF13: VIATICOS | AG13: 0.5 | AH13: BENEFICIO PYG | AI13: 0.02 | AJ13: ='BD P&G'!E44+'BD P&G'!E45 -> 0.00558 | AK13: VENTA SIN PYG | AL13: VENTA FINAL | AP13: 0.28 | AQ13: 0.01 | AR13: 0.02 | AS13: 0.055 | AV13: 0.01 | AW13: 0.03 | AX13: 0.6 | AY13: 0.03 | BB13: CORTE 6 | BC13: V6 | BE13: Nº MÓDULOS | BF13: VR SILICONA | BG13: VR PELÍCULA | BH13: VR EMBALAJE | BJ13: ESP. CRISTAL | BK13: PESO KG | BN13: VR TRANSP | BP13: FECHA INICIO | BQ13: FECHA FIN | BR13: DURACIÓN TOTAL | BS13: DURACIÓN PRODUCCIÓN | BT13: DURACIÓN MONTAJE | BU13: VR BACK | BV13: VR BACK/M2 | CH13: Extraido del formato equipos | CI13: =IFERROR(CG13/F339,"") | CK13: =SUM(CK14:CK2066) -> 0 | CL13: =SUM(CL14:CL2066) -> 0 | CM13: =SUM(CM14:CM2066) -> 0 | CN13: =SUM(CN14:CN2066) -> 0 | CO13: =SUM(CO14:CO2066) -> 0 | CP13: =SUM(CP14:CP2066) -> 0 | CQ13: =SUM(CQ14:CQ2066) -> 0 | CR13: =SUM(CR14:CR2066) -> 0 | ... CT13: =SUM(CT14:CT2066) -> 0 | CU13: =SUM(CU15:CU1996) -> 0 | CV13: =SUM(CV15:CV1996) -> 0 | CW13: =SUM(CW15:CW1996) -> 0 | CX13: =SUM(CX15:CX1996) -> 0 | CY13: =SUM(CY15:CY1996) -> 0 | CZ13: =SUM(CZ15:CZ1996) -> 0 | DA13: =SUM(DA15:DA1996) -> 0 | DB13: =SUM(DB15:DB1996) -> 0 | ... DD13: =SUM(DD15:DD1996) -> 0
A14: ÍTEM | B14: UBICACIÓN | C14: CONFIGURACIÓN | D14: DESCRIPCIÓN | J14: AN (MT) | K14: AL (MT) | L14: M2 | M14: CNT | N14: VR UNT | O14: VR TOTAL | Q14: ACCE | R14: ALUMINIO | S14: CRISTAL | T14: % DESP ALU | W14: ENSAMBLE | X14: INSTA | Y14: ENSAM PYG | Z14: INST PYG | AA14: TOTAL M.O PYG | AB14: IMPREV | AE14: PYG | AG14: BENEFICIO | AI14: COMISIÓN | AJ14: IMPUESTOS | AM14: ACCE | AN14: ALUMINIO | AO14: CRISTAL | AP14: % DESP ALU | AQ14: MAQ | AR14: EMPQ | AS14: TRANS | AT14: ENSAMBLE | AU14: INSTA | AV14: IMPREV | AW14: BACKOFFICE | AX14: UTILIDAD | AY14: COMISIÓN | AZ14: VENTA | BB14: CORTE 7 | BC14: V7 | BK14: ESTRUCTURA | BL14: CRISTAL | BM14: TOTAL | BR14: =(ROUNDUP(+F339*0.05,0)+7)+1.5 -> 8.5 | BS14: =ROUNDUP(BR14,0)*0.4 -> 3.6 | BT14: =(ROUNDUP(BR14,0)*0.6)+(2) -> 7.4 | BU14: =((SUM(BV4:BV5))) -> 0 | BV14: =IFERROR((BU14/F339)+BU11,"") | CK14: OR | CL14: MD | CM14: AD | CN14: EL | CO14: MD | CP14: PL | CQ14: PRO | CR14: DESP | CS14: MT | CT14: ENT | CU14: CNT | CV14: VR TOTAL | CW14: CNT | CX14: VR TOTAL | CY14: CNT | CZ14: VR TOTAL | DA14: CNT | DB14: VR TOTAL | DC14: CNT | DD14: VR TOTAL
C15: SISTEMA | L15: =J15*K15*M15 -> 0 | N15: =IFERROR(AL15,"") -> 1.0765547 | O15: =IFERROR(N15*M15,"") -> 0 | Q15: =Q16+BF15+($R$350*Q16) -> 0 | R15: =IFERROR(R16+($R$348*R16),"") -> 0 | S15: =+IF(R17="SI",((W19*'BD GN'!$AB$2)+S16)*1,COTIZACIÓN!S16*1)+(P16*S16) -> 0 | T15: =R15*T13 -> 0 | U15: =BH15+BG15 -> 0 | V15: =IFERROR(BN15,0) | W15: =IFERROR(IF(X17="SI",W18*J15*K15,IF(BE15=3,BE17,IF(BE15=4,BE18,IF(BE15=5,BE19,IF(BE15>5,BE19+(BE20*(BE15-5)),"")))))*0,"") | X15: =IFERROR(IF(X16="NO",(VLOOKUP(D15,'BD M.O'!C:E,3,FALSE))*W19,((VLOOKUP(D15,'BD M.O'!C:E,3,FALSE))+7500)*W19),"") | Y15: =IFERROR($Y$13*AK15,"") -> 0.042084457 | Z15: =IFERROR(($Z$13*AK15)+X15,"") | AA15: =IFERROR(Y15+Z15,"") | AB15: =IFERROR((SUM(Q15:X15)-T15+T17)*$AB$13,"") -> 0 | AC15: =IFERROR(((SUM(Q15:V15,IF(X20>AA15,AVERAGE(X20,AA15),AA15))-T15+T17))*$AB$13,"") -> 0 | AD15: =IFERROR((J15*K15*$BV$14),"") | AE15: =IFERROR($AE$13*AK15,"") -> 0.064010593 | AF15: =IFERROR(($CI$11+$CI$13)*W19,"") | AG15: =IFERROR((SUM(Q15:X15,AB15,AD15,AF15)-T15+T17)*$AG$13,"") -> 0 | AH15: =IFERROR((SUM(Q15:V15,(IF(X20>AA15,AVERAGE(X20,AA15),AA15)),AC15,AE15,AF15)-T15+T17)*$AG$13,"") -> 0.032005296 | AI15: =IFERROR(AL15*$AI$13,"") -> 0.021531093 | AJ15: =IFERROR($AJ$13*AL15,"") -> 0.006007175 | AK15: =IFERROR(SUM(Q15:X15,AB15,AD15,AG15,AF15)/(1-$AI$13)+(1-$AJ$13)-T15+T17,"") -> 0.99442 | AL15: =IFERROR(SUM(Q15:V15,AC15,(IF(AD15>AE15,AVERAGE(AD15,AE15),AE15)),AF15,,AH15,(IF(SUM(X20)>AA15,AVERAGE(AA15,X20),AA15)))/(1-$AJ$13)+(1-$AI$13)-T15+T17,"") -> 1.0765547 | AM15: =$M$15*Q15 -> 0 | AN15: =$M$15*R15 -> 0 | AO15: =$M$15*S15 -> 0 | AP15: =$M$15*T15 -> 0 | AQ15: =$M$15*#REF! -> #REF! | AR15: =$M$15*U15 -> 0 | AS15: =$M$15*V15 -> #VALUE! | AT15: =$M$15*W15 -> #VALUE! | AU15: =$M$15*X15 -> #VALUE! | AV15: =$M$15*AB15 -> 0 | AW15: =$M$15*AE15 -> 0 | AX15: =$M$15*AG15 -> 0 | AY15: =$M$15*AI15 -> 0 | AZ15: =$M$15*AK15 -> 0 | BB15: CORTE 8 | BC15: V8 | BF15: =IF(BH16="NO",((2*J15)+(2*K15))*'BD GN'!$AU$3,((3*J15)+(2*K15))*'BD GN'!$AU$3) -> 0 | BG15: ='BD GN'!$BB$3*J15*K15 -> 0 | BH15: =((J15*2*BE15)+(K15*2*BE15))*'BD GN'!$AN$4 -> 0 | BL15: =J15*K15*2.5*BJ15 -> 0 | BM15: =BK15+BL15 -> 0 | BN15: =IFERROR((VLOOKUP($C$12,'BD GN'!BD:BM,10,FALSE)*BM15)+$BR$338,"") | CV15: =IFERROR(N15*CU15,"") -> 0 | CX15: =IFERROR(P15*CW15,"") -> 0 | CZ15: =IFERROR(R15*CY15,"") -> 0 | DA15: =CU15+CW15+CY15 -> 0 | DB15: =IFERROR(CV15+CX15+CZ15,"") -> 0 | DC15: =M15-(CU15+CW15+CY15) -> 0 | DD15: =IFERROR(O15-(CV15+CX15+CZ15),"") -> 0 | DG15: 10001 | DH15: 1 | DI15: =IFERROR(IF(DG15>0,(((N15)/(1+10%+19%*5%)+((N15)/(1+10%+19%*5%))*10%)*DH15),0),0) -> 1.0673368 | DJ15: =IFERROR(IF(DG15>0,(N15*DH15),0),0) -> 1.0765547 | DK15: =IF(DG15>0,((R15+T15)*DH15),0) -> 0 | DL15: =IF(DG15>0,(Q15*DH15),0) -> 0 | DM15: =IF(DG15>0,(S15*DH15),0) -> 0 | DN15: =IF(DG15>0,(BN15*DH15),0) -> #VALUE! | DO15: =IF(DG15>0,(AF15*DH15),0) -> #VALUE! | DP15: =IF(DG15>0,((DI15)*('BD P&G'!$E$16+'BD P&G'!$E$17+'BD P&G'!$E$18+'BD P&G'!$E$19+'BD P&G'!$E$20+'BD P&G'!$E$21+'BD P&G'!$E$22+'BD P&G'!$E$23)*DH15),0) -> 0.029016015 | DQ15: =IFERROR(IF(DG15>0,((DI15*'BD P&G'!$E$7)+(DI15*'BD P&G'!$E$9)+AI15),0),0) -> 0.045823375 | DR15: =IFERROR(IF(DG15>0,((DI15*1%)),0),0) -> 0.010673368 | DS15: =IFERROR(IF(DG15>0,(((DI15*'BD P&G'!$E$32+DI15*'BD P&G'!$E$33+DI15*'BD P&G'!$E$35+DI15*'BD P&G'!$E$36+DI15*'BD P&G'!$E$37))),0),0) -> 0.011041197 | DT15: =IF(DG15>0,(Y15*DH15),0) -> 0.042084457 | DU15: =IF(DG15>0,(Z15*DH15),0) -> #VALUE! | DV15: =IF(DG15>0,(Y19*DH15),0) -> 0 | DW15: =IF(DG15>0,(Z19*DH15),0) -> 0 | DX15: =IF(DV15>0,DJ15,0) -> 0 | DY15: =IF(DW15>0,DJ15,0) -> 0
C16: CRISTAL | T16: =IFERROR(T15/$R$353,"") -> 0 | W16: ANGEO | X16: NO | BB16: CORTE 9 | BC16: V9 | BE16: ALFAJÍA | BF16: NO | BG16: LUCETA | BH16: NO | BP16: TIEMPOS PYG
C17: ACABADO ALUMINIO | Q17: SANDBLASTING | R17: NO | T17: =IFERROR(($R$353-8000)*T16,"") -> 0 | W17: FACHADA | X17: NO | BB17: CORTE 10 | BC17: V10 | BE17: =IFERROR(VLOOKUP(D15,'BD M.O'!C:H,4,FALSE),"") | BF17: 2HOJAS | BP17: FECHA INICIO | BQ17: FECHA FIN | BR17: DURACIÓN TOTAL | BS17: DURACIÓN PRODUCCIÓN | BT17: DURACIÓN MONTAJE
C18: PELÍCULA PROTECCIÓN | D18: PERFILES | F18: X | G18: CRISTAL | I18: =+IF($BG$9="SI","","X") -> X | R18: VIDRIO M2 | S18: =IF(S16="","",S16/(J15*K15)) | W18: =IFERROR(IF(X17="SI",VLOOKUP(D15,'BD M.O'!C:F,4,FALSE),""),"") | X18: FACHADA | Y18: M2 INOX | Z18: M2 ALU | BC18: V11 | BE18: =IFERROR(VLOOKUP(COTIZACIÓN!D15,'BD M.O'!C:I,5,FALSE),"") | BF18: 3HOJAS | BR18: =IFERROR((SUM(Y340:Z340)),"") -> 0 | BS18: =Y340 -> 0 | BT18: =Z340 -> 0 | DI18: =IFERROR(IF(DG18>0,(((N15)/(1+10%+19%*5%)+((N15)/(1+10%+19%*5%))*10%)*DH18),0),0) -> 0 | DJ18: =IFERROR(IF(DG18>0,(N15*DH18),0),0) -> 0 | DK18: =IF(DG18>0,((R15+T15)*DH18),0) -> 0 | DL18: =IF(DG18>0,(Q15*DH18),0) -> 0 | DM18: =IF(DG18>0,(S15*DH18),0) -> 0 | DN18: =IF(DG18>0,(BN15*DH18),0) -> 0 | DO18: =IF(DG18>0,(AF15*DH18),0) -> 0 | DP18: =IF(DG18>0,((DI18)*('BD P&G'!$E$16+'BD P&G'!$E$17+'BD P&G'!$E$18+'BD P&G'!$E$19+'BD P&G'!$E$20+'BD P&G'!$E$21+'BD P&G'!$E$22+'BD P&G'!$E$23)*DH18),0) -> 0 | DQ18: =IFERROR(IF(DG18>0,((DI18*'BD P&G'!$E$7)+(DI18*'BD P&G'!$E$9)+AI15),0),0) -> 0 | DR18: =IFERROR(IF(DG18>0,((DI18*1%)),0),0) -> 0 | DS18: =IFERROR(IF(DG18>0,(((DI18*'BD P&G'!$E$32+DI18*'BD P&G'!$E$33+DI18*'BD P&G'!$E$35+DI18*'BD P&G'!$E$36+DI18*'BD P&G'!$E$37))),0),0) -> 0 | DT18: =IF(DG18>0,(Y15*DH18),0) -> 0 | DU18: =IF(DG18>0,(Z15*DH18),0) -> 0 | DV18: =IF(DG18>0,(Y19*DH18),0) -> 0 | DW18: =IF(DG18>0,(Z19*DH18),0) -> 0 | DX18: =IF(DV18>0,DJ18,0) -> 0 | DY18: =IF(DW18>0,DJ18,0) -> 0
C19: CERRADURA | D19: =IFERROR(VLOOKUP(D15,'BD GN'!C:E,3,),"") | R19: SISTEMA M2 | S19: =IFERROR(IF(N15="","",N15/W19),"") | W19: =+IF(J15*K15>=1,J15*K15,IF(AND(J15*K15>0,J15*K15<1),1,"")) | X19: AREA | Y19: =IFERROR(IF(D15='BD GN'!$C$25,COTIZACIÓN!W19,IF(D15='BD GN'!$C$26,COTIZACIÓN!W19,IF(D15='BD GN'!$C$27,COTIZACIÓN!W19,IF(COTIZACIÓN!D15='BD GN'!$C$28,COTIZACIÓN!W19,IF(COTIZACIÓN!D15='BD GN'!$C$29,COTIZACIÓN!W19,IF(COTIZACIÓN!D15='BD GN'!$C$35,COTIZACIÓN!W19,IF(COTIZACIÓN!D15='BD GN'!$C$36,COTIZACIÓN!W19,IF(COTIZACIÓN!D15='BD GN'!$C$37,COTIZACIÓN!W19,IF(COTIZACIÓN!D15='BD GN'!$C$38,COTIZACIÓN!W19,IF(COTIZACIÓN!D15='BD GN'!$C$39,COTIZACIÓN!W19,IF(COTIZACIÓN!D15='BD GN'!$C$40,COTIZACIÓN!W19,IF(COTIZACIÓN!D15='BD GN'!$C$41,COTIZACIÓN!W19,IF(COTIZACIÓN!D15='BD GN'!$C$42,COTIZACIÓN!W19,IF(COTIZACIÓN!D15='BD GN'!$C$49,COTIZACIÓN!W19,IF(COTIZACIÓN!D15='BD GN'!$C$50,COTIZACIÓN!W19,IF(COTIZACIÓN!D15='BD GN'!$C$51,COTIZACIÓN!W19,IF(COTIZACIÓN!D15='BD GN'!$C$67,COTIZACIÓN!W19,0))))))))))))))))),0) -> 0 | Z19: =IFERROR(W19-Y19,0) -> 0 | BC19: V12 | BE19: =IFERROR(VLOOKUP(D15,'BD M.O'!C:I,6,FALSE),"") | BF19: 4HOJAS
C20: OBSERVACIONES | D20: N.A | R20: VR REF SIS M2 | S20: =IFERROR(IF($C$12='BD GN'!$CC$1,VLOOKUP(COTIZACIÓN!D15,'BD GN'!CB:CG,2,FALSE),IF(COTIZACIÓN!$C$12='BD GN'!$CD$1,VLOOKUP(COTIZACIÓN!D15,'BD GN'!CB:CG,3,FALSE),IF($C$12='BD GN'!$CE$1,VLOOKUP(COTIZACIÓN!D15,'BD GN'!CB:CG,4,FALSE),IF(COTIZACIÓN!$C$12='BD GN'!$CF$1,VLOOKUP(COTIZACIÓN!D15,'BD GN'!CB:CG,5,FALSE),IF(COTIZACIÓN!$C$12='BD GN'!$CG$1,VLOOKUP(COTIZACIÓN!D15,'BD GN'!CB:CG,6,FALSE),""))))),"-") | W20: TOTAL M.O | X20: =IFERROR(SUM(W15:X15),"") -> 0 | Y20: TOTAL M.O PYG | Z20: =IFERROR(Y15+Z15,"") | BC20: V13 | BE20: =IFERROR(VLOOKUP(D15,'BD M.O'!C:I,7,FALSE),"") | BF20: HOJA ADIC
A21: ÍTEM | B21: UBICACIÓN | C21: CONFIGURACIÓN | D21: DESCRIPCIÓN | J21: AN (MT) | K21: AL (MT) | L21: M2 | M21: CNT | N21: VR UNT | O21: VR TOTAL | Q21: ACCE | R21: ALUMINIO | S21: CRISTAL | T21: % DESP ALU | U21: EMPQ | V21: TRANS | W21: ENSAMBLE | X21: INSTA | Y21: ENSAM PYG | Z21: INST PYG | AA21: TOTAL M.O PYG | AB21: IMPREV | AC21: IMPREV PYG | AD21: BACKOFFICE | AE21: PYG | AF21: VIATICOS | AG21: BENEFICIO | AH21: BENEFICIO PYG | AI21: COMISIÓN | AJ21: IMPUESTOS | AK21: VENTA SIN PYG | AL21: VENTA FINAL | AM21: ACCE | AN21: ALUMINIO | AO21: CRISTAL | AP21: % DESP ALU | AQ21: MAQ | AR21: EMPQ | AS21: TRANS | AT21: ENSAMBLE | AU21: INSTA | AV21: IMPREV | AW21: BACKOFFICE | AX21: UTILIDAD | AY21: COMISIÓN | AZ21: VENTA | BC21: V14 | BE21: Nº MÓDULOS | BF21: =$BF$13 -> VR SILICONA | BG21: =$BG$13 -> VR PELÍCULA | BH21: =$BH$13 -> VR EMBALAJE | BJ21: =$BJ$13 -> ESP. CRISTAL | BK21: ESTRUCTURA | BL21: CRISTAL | BM21: =BM14 -> TOTAL | BN21: VR TRANSP | CK21: OR | CL21: MD | CM21: AD | CN21: EL | CO21: MD | CP21: PL | CQ21: PRO | CR21: DESP | CS21: MT | CT21: ENT | CU21: CNT | CV21: VR TOTAL | CW21: CNT | CX21: VR TOTAL | CY21: CNT | CZ21: VR TOTAL | DA21: CNT | DB21: VR TOTAL | DC21: CNT | DD21: VR TOTAL | DG21: RAD | DH21: CANTIDAD | DI21: SUBTOTAL | DJ21: TOTAL | DK21: ALU | DL21: ACC | DM21: VIDRIO | DN21: TRANSPORTE | DO21: VIATICOS | DP21: BACKOFFICE | DQ21: GAST VENTA | DR21: GAST FINANC | DS21: COSTOS IND | DT21: ENSAMBLE | DU21: INSTALACION | DV21: M2 INOX | DW21: M2 ALU | DX21: VR INOX | DY21: VR ALU
C22: SISTEMA | L22: =J22*K22*M22 -> 0 | N22: =IFERROR(AL22,"") -> 1.0765547 | O22: =IFERROR(N22*M22,"") -> 0 | Q22: =Q23+BF22+($R$350*Q23) -> 0 | R22: =IFERROR(R23+($R$348*R23),"") -> 0 | S22: =+IF(R24="SI",((W26*'BD GN'!$AB$2)+S23)*1,COTIZACIÓN!S23*1)+(P23*S23) -> 0 | T22: =IFERROR(R22*IF(K22<=3,$T$13,15%),"") -> 0 | U22: =BH22+BG22 -> 0 | V22: =IFERROR(BN22,0) | W22: =IFERROR(IF(X24="SI",W25*J22*K22,IF(BE22=3,BE24,IF(BE22=4,BE25,IF(BE22=5,BE26,IF(BE22>5,BE26+(BE27*(BE22-5)),"")))))*0,"") | X22: =IFERROR(IF(X23="NO",(VLOOKUP(D22,'BD M.O'!C:E,3,FALSE))*W26,((VLOOKUP(D22,'BD M.O'!C:E,3,FALSE))+7500)*W26),"") | Y22: =IFERROR($Y$13*AK22,"") -> 0.042084457 | Z22: =IFERROR(($Z$13*AK22)+X22,"") | AA22: =IFERROR(Y22+Z22,"") | AB22: =IFERROR((SUM(Q22:X22)-T22+T24)*$AB$13,"") -> 0 | AC22: =IFERROR(((SUM(Q22:V22,IF(X27>AA22,AVERAGE(X27,AA22),AA22))-T22+T24))*$AB$13,"") -> 0 | AD22: =IFERROR((J22*K22*$BV$14),"") | AE22: =IFERROR($AE$13*AK22,"") -> 0.064010593 | AF22: =IFERROR(($CI$11+$CI$13)*W26,"") | AG22: =IFERROR((SUM(Q22:X22,AB22,AD22,AF22)-T22+T24)*$AG$13,"") -> 0 | AH22: =IFERROR((SUM(Q22:V22,(IF(X27>AA22,AVERAGE(X27,AA22),AA22)),AC22,AE22,AF22)-T22+T24)*$AG$13,"") -> 0.032005296 | AI22: =IFERROR(AL22*$AI$13,"") -> 0.021531093 | AJ22: =IFERROR($AJ$13*AL22,"") -> 0.006007175 | AK22: =IFERROR(SUM(Q22:X22,AB22,AD22,AG22,AF22)/(1-$AI$13)+(1-$AJ$13)-T22+T24,"") -> 0.99442 | AL22: =IFERROR(SUM(Q22:V22,AC22,(IF(AD22>AE22,AVERAGE(AD22,AE22),AE22)),AF22,,AH22,(IF(SUM(X27)>AA22,AVERAGE(AA22,X27),AA22)))/(1-$AJ$13)+(1-$AI$13)-T22+T24,"") -> 1.0765547 | AM22: =$M$15*Q22 -> 0 | AN22: =$M$15*R22 -> 0 | AO22: =$M$15*S22 -> 0 | AP22: =$M$15*T22 -> 0 | AQ22: =$M$15*#REF! -> #REF! | AR22: =$M$15*U22 -> 0 | AS22: =$M$15*V22 -> #VALUE! | AT22: =$M$15*W22 -> #VALUE! | AU22: =$M$15*X22 -> #VALUE! | AV22: =$M$15*AB22 -> 0 | AW22: =$M$15*AE22 -> 0 | AX22: =$M$15*AG22 -> 0 | AY22: =$M$15*AI22 -> 0 | AZ22: =$M$15*AK22 -> 0 | BB22: CORTE 8 | BC22: V8 | BF22: =IF(BH23="NO",((2*J22)+(2*K22))*'BD GN'!$AU$3,((3*J22)+(2*K22))*'BD GN'!$AU$3) -> 0 | BG22: ='BD GN'!$BB$3*J22*K22 -> 0 | BH22: =((J22*2*BE22)+(K22*2*BE22))*'BD GN'!$AN$4 -> 0 | BL22: =J22*K22*2.5*BJ22 -> 0 | BM22: =BK22+BL22 -> 0 | BN22: =IFERROR((VLOOKUP($C$12,'BD GN'!BD:BM,10,FALSE)*BM22)+$BR$338,"") | CV22: =IFERROR(N22*CU22,"") -> 0 | CX22: =IFERROR(P22*CW22,"") -> 0 | CZ22: =IFERROR(R22*CY22,"") -> 0 | DA22: =CU22+CW22+CY22 -> 0 | DB22: =IFERROR(CV22+CX22+CZ22,"") -> 0 | DC22: =M22-(CU22+CW22+CY22) -> 0 | DD22: =IFERROR(O22-(CV22+CX22+CZ22),"") -> 0 | DI22: =IFERROR(IF(DG22>0,(((N22)/(1+10%+19%*5%)+((N22)/(1+10%+19%*5%))*10%)*DH22),0),0) -> 0 | DJ22: =IFERROR(IF(DG22>0,(N22*DH22),0),0) -> 0 | DK22: =IF(DG22>0,((R22+T22)*DH22),0) -> 0 | DL22: =IF(DG22>0,(Q22*DH22),0) -> 0 | DM22: =IF(DG22>0,(S22*DH22),0) -> 0 | DN22: =IF(DG22>0,(BN22*DH22),0) -> 0 | DO22: =IF(DG22>0,(AF22*DH22),0) -> 0 | DP22: =IF(DG22>0,((DI22)*('BD P&G'!$E$16+'BD P&G'!$E$17+'BD P&G'!$E$18+'BD P&G'!$E$19+'BD P&G'!$E$20+'BD P&G'!$E$21+'BD P&G'!$E$22+'BD P&G'!$E$23)*DH22),0) -> 0 | DQ22: =IFERROR(IF(DG22>0,((DI22*'BD P&G'!$E$7)+(DI22*'BD P&G'!$E$9)+AI22),0),0) -> 0 | DR22: =IFERROR(IF(DG22>0,((DI22*1%)),0),0) -> 0 | DS22: =IFERROR(IF(DG22>0,(((DI22*'BD P&G'!$E$32+DI22*'BD P&G'!$E$33+DI22*'BD P&G'!$E$35+DI22*'BD P&G'!$E$36+DI22*'BD P&G'!$E$37))),0),0) -> 0 | DT22: =IF(DG22>0,(Y22*DH22),0) -> 0 | DU22: =IF(DG22>0,(Z22*DH22),0) -> 0 | DV22: =IF(DG22>0,(Y26*DH22),0) -> 0 | DW22: =IF(DG22>0,(Z26*DH22),0) -> 0 | DX22: =IF(DV22>0,DJ22,0) -> 0 | DY22: =IF(DW22>0,DJ22,0) -> 0
C23: CRISTAL | T23: =IFERROR(T22/$R$353,"") -> 0 | W23: ANGEO | X23: NO | BB23: CORTE 9 | BC23: V9 | BE23: ALFAJÍA | BF23: NO | BG23: LUCETA | BH23: NO
C24: ACABADO ALUMINIO | Q24: SANDBLASTING | R24: NO | T24: =IFERROR(($R$353-8000)*T23,"") -> 0 | W24: FACHADA | X24: NO | BB24: CORTE 10 | BC24: V10 | BE24: =IFERROR(VLOOKUP(D22,'BD M.O'!C:H,4,FALSE),"") | BF24: 2HOJAS
C25: PELÍCULA PROTECCIÓN | D25: PERFILES | F25: X | G25: CRISTAL | I25: =+IF($BG$9="SI","","X") -> X | R25: VIDRIO M2 | S25: =IF(S23="","",S23/(J22*K22)) | W25: =IFERROR(IF(X24="SI",VLOOKUP(D22,'BD M.O'!C:F,4,FALSE),""),"") | X25: FACHADA | Y25: M2 INOX | Z25: M2 ALU | BC25: V11 | BE25: =IFERROR(VLOOKUP(COTIZACIÓN!D22,'BD M.O'!C:I,5,FALSE),"") | BF25: 3HOJAS | DI25: =IFERROR(IF(DG25>0,(((N22)/(1+10%+19%*5%)+((N22)/(1+10%+19%*5%))*10%)*DH25),0),0) -> 0 | DJ25: =IFERROR(IF(DG25>0,(N22*DH25),0),0) -> 0 | DK25: =IF(DG25>0,((R22+T22)*DH25),0) -> 0 | DL25: =IF(DG25>0,(Q22*DH25),0) -> 0 | DM25: =IF(DG25>0,(S22*DH25),0) -> 0 | DN25: =IF(DG25>0,(BN22*DH25),0) -> 0 | DO25: =IF(DG25>0,(AF22*DH25),0) -> 0 | DP25: =IF(DG25>0,((DI25)*('BD P&G'!$E$16+'BD P&G'!$E$17+'BD P&G'!$E$18+'BD P&G'!$E$19+'BD P&G'!$E$20+'BD P&G'!$E$21+'BD P&G'!$E$22+'BD P&G'!$E$23)*DH25),0) -> 0 | DQ25: =IFERROR(IF(DG25>0,((DI25*'BD P&G'!$E$7)+(DI25*'BD P&G'!$E$9)+AI22),0),0) -> 0 | DR25: =IFERROR(IF(DG25>0,((DI25*1%)),0),0) -> 0 | DS25: =IFERROR(IF(DG25>0,(((DI25*'BD P&G'!$E$32+DI25*'BD P&G'!$E$33+DI25*'BD P&G'!$E$35+DI25*'BD P&G'!$E$36+DI25*'BD P&G'!$E$37))),0),0) -> 0 | DT25: =IF(DG25>0,(Y22*DH25),0) -> 0 | DU25: =IF(DG25>0,(Z22*DH25),0) -> 0 | DV25: =IF(DG25>0,(Y26*DH25),0) -> 0 | DW25: =IF(DG25>0,(Z26*DH25),0) -> 0 | DX25: =IF(DV25>0,DJ25,0) -> 0 | DY25: =IF(DW25>0,DJ25,0) -> 0
C26: CERRADURA | D26: =IFERROR(VLOOKUP(D22,'BD GN'!C:E,3,),"") | R26: SISTEMA M2 | S26: =IFERROR(IF(N22="","",N22/W26),"") | W26: =+IF(J22*K22>=1,J22*K22,IF(AND(J22*K22>0,J22*K22<1),1,"")) | X26: AREA | Y26: =IFERROR(IF(D22='BD GN'!$C$25,COTIZACIÓN!W26,IF(D22='BD GN'!$C$26,COTIZACIÓN!W26,IF(D22='BD GN'!$C$27,COTIZACIÓN!W26,IF(COTIZACIÓN!D22='BD GN'!$C$28,COTIZACIÓN!W26,IF(COTIZACIÓN!D22='BD GN'!$C$29,COTIZACIÓN!W26,IF(COTIZACIÓN!D22='BD GN'!$C$35,COTIZACIÓN!W26,IF(COTIZACIÓN!D22='BD GN'!$C$36,COTIZACIÓN!W26,IF(COTIZACIÓN!D22='BD GN'!$C$37,COTIZACIÓN!W26,IF(COTIZACIÓN!D22='BD GN'!$C$38,COTIZACIÓN!W26,IF(COTIZACIÓN!D22='BD GN'!$C$39,COTIZACIÓN!W26,IF(COTIZACIÓN!D22='BD GN'!$C$40,COTIZACIÓN!W26,IF(COTIZACIÓN!D22='BD GN'!$C$41,COTIZACIÓN!W26,IF(COTIZACIÓN!D22='BD GN'!$C$42,COTIZACIÓN!W26,IF(COTIZACIÓN!D22='BD GN'!$C$49,COTIZACIÓN!W26,IF(COTIZACIÓN!D22='BD GN'!$C$50,COTIZACIÓN!W26,IF(COTIZACIÓN!D22='BD GN'!$C$51,COTIZACIÓN!W26,IF(COTIZACIÓN!D22='BD GN'!$C$67,COTIZACIÓN!W26,0))))))))))))))))),0) -> 0 | Z26: =IFERROR(W26-Y26,0) -> 0 | BC26: V12 | BE26: =IFERROR(VLOOKUP(D22,'BD M.O'!C:I,6,FALSE),"") | BF26: 4HOJAS
C27: OBSERVACIONES | D27: N.A | R27: VR REF SIS M2 | S27: =IFERROR(IF($C$12='BD GN'!$CC$1,VLOOKUP(COTIZACIÓN!D22,'BD GN'!CB:CG,2,FALSE),IF(COTIZACIÓN!$C$12='BD GN'!$CD$1,VLOOKUP(COTIZACIÓN!D22,'BD GN'!CB:CG,3,FALSE),IF($C$12='BD GN'!$CE$1,VLOOKUP(COTIZACIÓN!D22,'BD GN'!CB:CG,4,FALSE),IF(COTIZACIÓN!$C$12='BD GN'!$CF$1,VLOOKUP(COTIZACIÓN!D22,'BD GN'!CB:CG,5,FALSE),IF(COTIZACIÓN!$C$12='BD GN'!$CG$1,VLOOKUP(COTIZACIÓN!D22,'BD GN'!CB:CG,6,FALSE),""))))),"-") | W27: TOTAL M.O | X27: =IFERROR(SUM(W22:X22),"") -> 0 | Y27: TOTAL M.O PYG | Z27: =IFERROR(Y22+Z22,"") | BC27: V13 | BE27: =IFERROR(VLOOKUP(D22,'BD M.O'!C:I,7,FALSE),"") | BF27: HOJA ADIC
A28: ÍTEM | B28: UBICACIÓN | C28: CONFIGURACIÓN | D28: DESCRIPCIÓN | J28: AN (MT) | K28: AL (MT) | L28: M2 | M28: CNT | N28: VR UNT | O28: VR TOTAL | Q28: ACCE | R28: ALUMINIO | S28: CRISTAL | T28: % DESP ALU | U28: EMPQ | V28: TRANS | W28: ENSAMBLE | X28: INSTA | Y28: ENSAM PYG | Z28: INST PYG | AA28: TOTAL M.O PYG | AB28: IMPREV | AC28: IMPREV PYG | AD28: BACKOFFICE | AE28: PYG | AF28: VIATICOS | AG28: BENEFICIO | AH28: BENEFICIO PYG | AI28: COMISIÓN | AJ28: IMPUESTOS | AK28: VENTA SIN PYG | AL28: VENTA FINAL | AM28: ACCE | AN28: ALUMINIO | AO28: CRISTAL | AP28: % DESP ALU | AQ28: MAQ | AR28: EMPQ | AS28: TRANS | AT28: ENSAMBLE | AU28: INSTA | AV28: IMPREV | AW28: BACKOFFICE | AX28: UTILIDAD | AY28: COMISIÓN | AZ28: VENTA | BC28: V14 | BE28: Nº MÓDULOS | BF28: =$BF$13 -> VR SILICONA | BG28: =$BG$13 -> VR PELÍCULA | BH28: =$BH$13 -> VR EMBALAJE | BJ28: =$BJ$13 -> ESP. CRISTAL | BK28: ESTRUCTURA | BL28: CRISTAL | BM28: =BM21 -> TOTAL | BN28: VR TRANSP | CK28: OR | CL28: MD | CM28: AD | CN28: EL | CO28: MD | CP28: PL | CQ28: PRO | CR28: DESP | CS28: MT | CT28: ENT | CU28: CNT | CV28: VR TOTAL | CW28: CNT | CX28: VR TOTAL | CY28: CNT | CZ28: VR TOTAL | DA28: CNT | DB28: VR TOTAL | DC28: CNT | DD28: VR TOTAL | DG28: RAD | DH28: CANTIDAD | DI28: SUBTOTAL | DJ28: TOTAL | DK28: ALU | DL28: ACC | DM28: VIDRIO | DN28: TRANSPORTE | DO28: VIATICOS | DP28: BACKOFFICE | DQ28: GAST VENTA | DR28: GAST FINANC | DS28: COSTOS IND | DT28: ENSAMBLE | DU28: INSTALACION | DV28: M2 INOX | DW28: M2 ALU | DX28: VR INOX | DY28: VR ALU
C29: SISTEMA | L29: =J29*K29*M29 -> 0 | N29: =IFERROR(AL29,"") -> 1.0765547 | O29: =IFERROR(N29*M29,"") -> 0 | Q29: =Q30+BF29+($R$350*Q30) -> 0 | R29: =IFERROR(R30+($R$348*R30),"") -> 0 | S29: =+IF(R31="SI",((W33*'BD GN'!$AB$2)+S30)*1,COTIZACIÓN!S30*1)+(P30*S30) -> 0 | T29: =IFERROR(R29*IF(K29<=3,$T$13,15%),"") -> 0 | U29: =BH29+BG29 -> 0 | V29: =IFERROR(BN29,0) | W29: =IFERROR(IF(X31="SI",W32*J29*K29,IF(BE29=3,BE31,IF(BE29=4,BE32,IF(BE29=5,BE33,IF(BE29>5,BE33+(BE34*(BE29-5)),"")))))*0,"") | X29: =IFERROR(IF(X30="NO",(VLOOKUP(D29,'BD M.O'!C:E,3,FALSE))*W33,((VLOOKUP(D29,'BD M.O'!C:E,3,FALSE))+7500)*W33),"") | Y29: =IFERROR($Y$13*AK29,"") -> 0.042084457 | Z29: =IFERROR(($Z$13*AK29)+X29,"") | AA29: =IFERROR(Y29+Z29,"") | AB29: =IFERROR((SUM(Q29:X29)-T29+T31)*$AB$13,"") -> 0 | AC29: =IFERROR(((SUM(Q29:V29,IF(X34>AA29,AVERAGE(X34,AA29),AA29))-T29+T31))*$AB$13,"") -> 0 | AD29: =IFERROR((J29*K29*$BV$14),"") | AE29: =IFERROR($AE$13*AK29,"") -> 0.064010593 | AF29: =IFERROR(($CI$11+$CI$13)*W33,"") | AG29: =IFERROR((SUM(Q29:X29,AB29,AD29,AF29)-T29+T31)*$AG$13,"") -> 0 | AH29: =IFERROR((SUM(Q29:V29,(IF(X34>AA29,AVERAGE(X34,AA29),AA29)),AC29,AE29,AF29)-T29+T31)*$AG$13,"") -> 0.032005296 | AI29: =IFERROR(AL29*$AI$13,"") -> 0.021531093 | AJ29: =IFERROR($AJ$13*AL29,"") -> 0.006007175 | AK29: =IFERROR(SUM(Q29:X29,AB29,AD29,AG29,AF29)/(1-$AI$13)+(1-$AJ$13)-T29+T31,"") -> 0.99442 | AL29: =IFERROR(SUM(Q29:V29,AC29,(IF(AD29>AE29,AVERAGE(AD29,AE29),AE29)),AF29,,AH29,(IF(SUM(X34)>AA29,AVERAGE(AA29,X34),AA29)))/(1-$AJ$13)+(1-$AI$13)-T29+T31,"") -> 1.0765547 | AM29: =$M$15*Q29 -> 0 | AN29: =$M$15*R29 -> 0 | AO29: =$M$15*S29 -> 0 | AP29: =$M$15*T29 -> 0 | AQ29: =$M$15*#REF! -> #REF! | AR29: =$M$15*U29 -> 0 | AS29: =$M$15*V29 -> #VALUE! | AT29: =$M$15*W29 -> #VALUE! | AU29: =$M$15*X29 -> #VALUE! | AV29: =$M$15*AB29 -> 0 | AW29: =$M$15*AE29 -> 0 | AX29: =$M$15*AG29 -> 0 | AY29: =$M$15*AI29 -> 0 | AZ29: =$M$15*AK29 -> 0 | BB29: CORTE 8 | BC29: V8 | BF29: =IF(BH30="NO",((2*J29)+(2*K29))*'BD GN'!$AU$3,((3*J29)+(2*K29))*'BD GN'!$AU$3) -> 0 | BG29: ='BD GN'!$BB$3*J29*K29 -> 0 | BH29: =((J29*2*BE29)+(K29*2*BE29))*'BD GN'!$AN$4 -> 0 | BL29: =J29*K29*2.5*BJ29 -> 0 | BM29: =BK29+BL29 -> 0 | BN29: =IFERROR((VLOOKUP($C$12,'BD GN'!BD:BM,10,FALSE)*BM29)+$BR$338,"") | CV29: =IFERROR(N29*CU29,"") -> 0 | CX29: =IFERROR(P29*CW29,"") -> 0 | CZ29: =IFERROR(R29*CY29,"") -> 0 | DA29: =CU29+CW29+CY29 -> 0 | DB29: =IFERROR(CV29+CX29+CZ29,"") -> 0 | DC29: =M29-(CU29+CW29+CY29) -> 0 | DD29: =IFERROR(O29-(CV29+CX29+CZ29),"") -> 0 | DI29: =IFERROR(IF(DG29>0,(((N29)/(1+10%+19%*5%)+((N29)/(1+10%+19%*5%))*10%)*DH29),0),0) -> 0 | DJ29: =IFERROR(IF(DG29>0,(N29*DH29),0),0) -> 0 | DK29: =IF(DG29>0,((R29+T29)*DH29),0) -> 0 | DL29: =IF(DG29>0,(Q29*DH29),0) -> 0 | DM29: =IF(DG29>0,(S29*DH29),0) -> 0 | DN29: =IF(DG29>0,(BN29*DH29),0) -> 0 | DO29: =IF(DG29>0,(AF29*DH29),0) -> 0 | DP29: =IF(DG29>0,((DI29)*('BD P&G'!$E$16+'BD P&G'!$E$17+'BD P&G'!$E$18+'BD P&G'!$E$19+'BD P&G'!$E$20+'BD P&G'!$E$21+'BD P&G'!$E$22+'BD P&G'!$E$23)*DH29),0) -> 0 | DQ29: =IFERROR(IF(DG29>0,((DI29*'BD P&G'!$E$7)+(DI29*'BD P&G'!$E$9)+AI29),0),0) -> 0 | DR29: =IFERROR(IF(DG29>0,((DI29*1%)),0),0) -> 0 | DS29: =IFERROR(IF(DG29>0,(((DI29*'BD P&G'!$E$32+DI29*'BD P&G'!$E$33+DI29*'BD P&G'!$E$35+DI29*'BD P&G'!$E$36+DI29*'BD P&G'!$E$37))),0),0) -> 0 | DT29: =IF(DG29>0,(Y29*DH29),0) -> 0 | DU29: =IF(DG29>0,(Z29*DH29),0) -> 0 | DV29: =IF(DG29>0,(Y33*DH29),0) -> 0 | DW29: =IF(DG29>0,(Z33*DH29),0) -> 0 | DX29: =IF(DV29>0,DJ29,0) -> 0 | DY29: =IF(DW29>0,DJ29,0) -> 0
C30: CRISTAL | T30: =IFERROR(T29/$R$353,"") -> 0 | W30: ANGEO | X30: NO | BB30: CORTE 9 | BC30: V9 | BE30: ALFAJÍA | BF30: NO | BG30: LUCETA | BH30: NO
C31: ACABADO ALUMINIO | Q31: SANDBLASTING | R31: NO | T31: =IFERROR(($R$353-8000)*T30,"") -> 0 | W31: FACHADA | X31: NO | BB31: CORTE 10 | BC31: V10 | BE31: =IFERROR(VLOOKUP(D29,'BD M.O'!C:H,4,FALSE),"") | BF31: 2HOJAS
C32: PELÍCULA PROTECCIÓN | D32: PERFILES | F32: X | G32: CRISTAL | I32: =+IF($BG$9="SI","","X") -> X | R32: VIDRIO M2 | S32: =IF(S30="","",S30/(J29*K29)) | W32: =IFERROR(IF(X31="SI",VLOOKUP(D29,'BD M.O'!C:F,4,FALSE),""),"") | X32: FACHADA | Y32: M2 INOX | Z32: M2 ALU | BC32: V11 | BE32: =IFERROR(VLOOKUP(COTIZACIÓN!D29,'BD M.O'!C:I,5,FALSE),"") | BF32: 3HOJAS | DI32: =IFERROR(IF(DG32>0,(((N29)/(1+10%+19%*5%)+((N29)/(1+10%+19%*5%))*10%)*DH32),0),0) -> 0 | DJ32: =IFERROR(IF(DG32>0,(N29*DH32),0),0) -> 0 | DK32: =IF(DG32>0,((R29+T29)*DH32),0) -> 0 | DL32: =IF(DG32>0,(Q29*DH32),0) -> 0 | DM32: =IF(DG32>0,(S29*DH32),0) -> 0 | DN32: =IF(DG32>0,(BN29*DH32),0) -> 0 | DO32: =IF(DG32>0,(AF29*DH32),0) -> 0 | DP32: =IF(DG32>0,((DI32)*('BD P&G'!$E$16+'BD P&G'!$E$17+'BD P&G'!$E$18+'BD P&G'!$E$19+'BD P&G'!$E$20+'BD P&G'!$E$21+'BD P&G'!$E$22+'BD P&G'!$E$23)*DH32),0) -> 0 | DQ32: =IFERROR(IF(DG32>0,((DI32*'BD P&G'!$E$7)+(DI32*'BD P&G'!$E$9)+AI29),0),0) -> 0 | DR32: =IFERROR(IF(DG32>0,((DI32*1%)),0),0) -> 0 | DS32: =IFERROR(IF(DG32>0,(((DI32*'BD P&G'!$E$32+DI32*'BD P&G'!$E$33+DI32*'BD P&G'!$E$35+DI32*'BD P&G'!$E$36+DI32*'BD P&G'!$E$37))),0),0) -> 0 | DT32: =IF(DG32>0,(Y29*DH32),0) -> 0 | DU32: =IF(DG32>0,(Z29*DH32),0) -> 0 | DV32: =IF(DG32>0,(Y33*DH32),0) -> 0 | DW32: =IF(DG32>0,(Z33*DH32),0) -> 0 | DX32: =IF(DV32>0,DJ32,0) -> 0 | DY32: =IF(DW32>0,DJ32,0) -> 0
C33: CERRADURA | D33: =IFERROR(VLOOKUP(D29,'BD GN'!C:E,3,),"") | R33: SISTEMA M2 | S33: =IFERROR(IF(N29="","",N29/W33),"") | W33: =+IF(J29*K29>=1,J29*K29,IF(AND(J29*K29>0,J29*K29<1),1,"")) | X33: AREA | Y33: =IFERROR(IF(D29='BD GN'!$C$25,COTIZACIÓN!W33,IF(D29='BD GN'!$C$26,COTIZACIÓN!W33,IF(D29='BD GN'!$C$27,COTIZACIÓN!W33,IF(COTIZACIÓN!D29='BD GN'!$C$28,COTIZACIÓN!W33,IF(COTIZACIÓN!D29='BD GN'!$C$29,COTIZACIÓN!W33,IF(COTIZACIÓN!D29='BD GN'!$C$35,COTIZACIÓN!W33,IF(COTIZACIÓN!D29='BD GN'!$C$36,COTIZACIÓN!W33,IF(COTIZACIÓN!D29='BD GN'!$C$37,COTIZACIÓN!W33,IF(COTIZACIÓN!D29='BD GN'!$C$38,COTIZACIÓN!W33,IF(COTIZACIÓN!D29='BD GN'!$C$39,COTIZACIÓN!W33,IF(COTIZACIÓN!D29='BD GN'!$C$40,COTIZACIÓN!W33,IF(COTIZACIÓN!D29='BD GN'!$C$41,COTIZACIÓN!W33,IF(COTIZACIÓN!D29='BD GN'!$C$42,COTIZACIÓN!W33,IF(COTIZACIÓN!D29='BD GN'!$C$49,COTIZACIÓN!W33,IF(COTIZACIÓN!D29='BD GN'!$C$50,COTIZACIÓN!W33,IF(COTIZACIÓN!D29='BD GN'!$C$51,COTIZACIÓN!W33,IF(COTIZACIÓN!D29='BD GN'!$C$67,COTIZACIÓN!W33,0))))))))))))))))),0) -> 0 | Z33: =IFERROR(W33-Y33,0) -> 0 | BC33: V12 | BE33: =IFERROR(VLOOKUP(D29,'BD M.O'!C:I,6,FALSE),"") | BF33: 4HOJAS
C34: OBSERVACIONES | D34: N.A | R34: VR REF SIS M2 | S34: =IFERROR(IF($C$12='BD GN'!$CC$1,VLOOKUP(COTIZACIÓN!D29,'BD GN'!CB:CG,2,FALSE),IF(COTIZACIÓN!$C$12='BD GN'!$CD$1,VLOOKUP(COTIZACIÓN!D29,'BD GN'!CB:CG,3,FALSE),IF($C$12='BD GN'!$CE$1,VLOOKUP(COTIZACIÓN!D29,'BD GN'!CB:CG,4,FALSE),IF(COTIZACIÓN!$C$12='BD GN'!$CF$1,VLOOKUP(COTIZACIÓN!D29,'BD GN'!CB:CG,5,FALSE),IF(COTIZACIÓN!$C$12='BD GN'!$CG$1,VLOOKUP(COTIZACIÓN!D29,'BD GN'!CB:CG,6,FALSE),""))))),"-") | W34: TOTAL M.O | X34: =IFERROR(SUM(W29:X29),"") -> 0 | Y34: TOTAL M.O PYG | Z34: =IFERROR(Y29+Z29,"") | BC34: V13 | BE34: =IFERROR(VLOOKUP(D29,'BD M.O'!C:I,7,FALSE),"") | BF34: HOJA ADIC
A35: ÍTEM | B35: UBICACIÓN | C35: CONFIGURACIÓN | D35: DESCRIPCIÓN | J35: AN (MT) | K35: AL (MT) | L35: M2 | M35: CNT | N35: VR UNT | O35: VR TOTAL | Q35: ACCE | R35: ALUMINIO | S35: CRISTAL | T35: % DESP ALU | U35: EMPQ | V35: TRANS | W35: ENSAMBLE | X35: INSTA | Y35: ENSAM PYG | Z35: INST PYG | AA35: TOTAL M.O PYG | AB35: IMPREV | AC35: IMPREV PYG | AD35: BACKOFFICE | AE35: PYG | AF35: VIATICOS | AG35: BENEFICIO | AH35: BENEFICIO PYG | AI35: COMISIÓN | AJ35: IMPUESTOS | AK35: VENTA SIN PYG | AL35: VENTA FINAL | AM35: ACCE | AN35: ALUMINIO | AO35: CRISTAL | AP35: % DESP ALU | AQ35: MAQ | AR35: EMPQ | AS35: TRANS | AT35: ENSAMBLE | AU35: INSTA | AV35: IMPREV | AW35: BACKOFFICE | AX35: UTILIDAD | AY35: COMISIÓN | AZ35: VENTA | BC35: V14 | BE35: Nº MÓDULOS | BF35: =$BF$13 -> VR SILICONA | BG35: =$BG$13 -> VR PELÍCULA | BH35: =$BH$13 -> VR EMBALAJE | BJ35: =$BJ$13 -> ESP. CRISTAL | BK35: ESTRUCTURA | BL35: CRISTAL | BM35: =BM28 -> TOTAL | BN35: VR TRANSP | CK35: OR | CL35: MD | CM35: AD | CN35: EL | CO35: MD | CP35: PL | CQ35: PRO | CR35: DESP | CS35: MT | CT35: ENT | CU35: CNT | CV35: VR TOTAL | CW35: CNT | CX35: VR TOTAL | CY35: CNT | CZ35: VR TOTAL | DA35: CNT | DB35: VR TOTAL | DC35: CNT | DD35: VR TOTAL | DG35: RAD | DH35: CANTIDAD | DI35: SUBTOTAL | DJ35: TOTAL | DK35: ALU | DL35: ACC | DM35: VIDRIO | DN35: TRANSPORTE | DO35: VIATICOS | DP35: BACKOFFICE | DQ35: GAST VENTA | DR35: GAST FINANC | DS35: COSTOS IND | DT35: ENSAMBLE | DU35: INSTALACION | DV35: M2 INOX | DW35: M2 ALU | DX35: VR INOX | DY35: VR ALU
C36: SISTEMA | L36: =J36*K36*M36 -> 0 | N36: =IFERROR(AL36,"") -> 1.0765547 | O36: =IFERROR(N36*M36,"") -> 0 | Q36: =Q37+BF36+($R$350*Q37) -> 0 | R36: =IFERROR(R37+($R$348*R37),"") -> 0 | S36: =+IF(R38="SI",((W40*'BD GN'!$AB$2)+S37)*1,COTIZACIÓN!S37*1)+(P37*S37) -> 0 | T36: =IFERROR(R36*IF(K36<=3,$T$13,15%),"") -> 0 | U36: =BH36+BG36 -> 0 | V36: =IFERROR(BN36,0) | W36: =IFERROR(IF(X38="SI",W39*J36*K36,IF(BE36=3,BE38,IF(BE36=4,BE39,IF(BE36=5,BE40,IF(BE36>5,BE40+(BE41*(BE36-5)),"")))))*0,"") | X36: =IFERROR(IF(X37="NO",(VLOOKUP(D36,'BD M.O'!C:E,3,FALSE))*W40,((VLOOKUP(D36,'BD M.O'!C:E,3,FALSE))+7500)*W40),"") | Y36: =IFERROR($Y$13*AK36,"") -> 0.042084457 | Z36: =IFERROR(($Z$13*AK36)+X36,"") | AA36: =IFERROR(Y36+Z36,"") | AB36: =IFERROR((SUM(Q36:X36)-T36+T38)*$AB$13,"") -> 0 | AC36: =IFERROR(((SUM(Q36:V36,IF(X41>AA36,AVERAGE(X41,AA36),AA36))-T36+T38))*$AB$13,"") -> 0 | AD36: =IFERROR((J36*K36*$BV$14),"") | AE36: =IFERROR($AE$13*AK36,"") -> 0.064010593 | AF36: =IFERROR(($CI$11+$CI$13)*W40,"") | AG36: =IFERROR((SUM(Q36:X36,AB36,AD36,AF36)-T36+T38)*$AG$13,"") -> 0 | AH36: =IFERROR((SUM(Q36:V36,(IF(X41>AA36,AVERAGE(X41,AA36),AA36)),AC36,AE36,AF36)-T36+T38)*$AG$13,"") -> 0.032005296 | AI36: =IFERROR(AL36*$AI$13,"") -> 0.021531093 | AJ36: =IFERROR($AJ$13*AL36,"") -> 0.006007175 | AK36: =IFERROR(SUM(Q36:X36,AB36,AD36,AG36,AF36)/(1-$AI$13)+(1-$AJ$13)-T36+T38,"") -> 0.99442 | AL36: =IFERROR(SUM(Q36:V36,AC36,(IF(AD36>AE36,AVERAGE(AD36,AE36),AE36)),AF36,,AH36,(IF(SUM(X41)>AA36,AVERAGE(AA36,X41),AA36)))/(1-$AJ$13)+(1-$AI$13)-T36+T38,"") -> 1.0765547 | AM36: =$M$15*Q36 -> 0 | AN36: =$M$15*R36 -> 0 | AO36: =$M$15*S36 -> 0 | AP36: =$M$15*T36 -> 0 | AQ36: =$M$15*#REF! -> #REF! | AR36: =$M$15*U36 -> 0 | AS36: =$M$15*V36 -> #VALUE! | AT36: =$M$15*W36 -> #VALUE! | AU36: =$M$15*X36 -> #VALUE! | AV36: =$M$15*AB36 -> 0 | AW36: =$M$15*AE36 -> 0 | AX36: =$M$15*AG36 -> 0 | AY36: =$M$15*AI36 -> 0 | AZ36: =$M$15*AK36 -> 0 | BB36: CORTE 8 | BC36: V8 | BF36: =IF(BH37="NO",((2*J36)+(2*K36))*'BD GN'!$AU$3,((3*J36)+(2*K36))*'BD GN'!$AU$3) -> 0 | BG36: ='BD GN'!$BB$3*J36*K36 -> 0 | BH36: =((J36*2*BE36)+(K36*2*BE36))*'BD GN'!$AN$4 -> 0 | BL36: =J36*K36*2.5*BJ36 -> 0 | BM36: =BK36+BL36 -> 0 | BN36: =IFERROR((VLOOKUP($C$12,'BD GN'!BD:BM,10,FALSE)*BM36)+$BR$338,"") | CV36: =IFERROR(N36*CU36,"") -> 0 | CX36: =IFERROR(P36*CW36,"") -> 0 | CZ36: =IFERROR(R36*CY36,"") -> 0 | DA36: =CU36+CW36+CY36 -> 0 | DB36: =IFERROR(CV36+CX36+CZ36,"") -> 0 | DC36: =M36-(CU36+CW36+CY36) -> 0 | DD36: =IFERROR(O36-(CV36+CX36+CZ36),"") -> 0 | DI36: =IFERROR(IF(DG36>0,(((N36)/(1+10%+19%*5%)+((N36)/(1+10%+19%*5%))*10%)*DH36),0),0) -> 0 | DJ36: =IFERROR(IF(DG36>0,(N36*DH36),0),0) -> 0 | DK36: =IF(DG36>0,((R36+T36)*DH36),0) -> 0 | DL36: =IF(DG36>0,(Q36*DH36),0) -> 0 | DM36: =IF(DG36>0,(S36*DH36),0) -> 0 | DN36: =IF(DG36>0,(BN36*DH36),0) -> 0 | DO36: =IF(DG36>0,(AF36*DH36),0) -> 0 | DP36: =IF(DG36>0,((DI36)*('BD P&G'!$E$16+'BD P&G'!$E$17+'BD P&G'!$E$18+'BD P&G'!$E$19+'BD P&G'!$E$20+'BD P&G'!$E$21+'BD P&G'!$E$22+'BD P&G'!$E$23)*DH36),0) -> 0 | DQ36: =IFERROR(IF(DG36>0,((DI36*'BD P&G'!$E$7)+(DI36*'BD P&G'!$E$9)+AI36),0),0) -> 0 | DR36: =IFERROR(IF(DG36>0,((DI36*1%)),0),0) -> 0 | DS36: =IFERROR(IF(DG36>0,(((DI36*'BD P&G'!$E$32+DI36*'BD P&G'!$E$33+DI36*'BD P&G'!$E$35+DI36*'BD P&G'!$E$36+DI36*'BD P&G'!$E$37))),0),0) -> 0 | DT36: =IF(DG36>0,(Y36*DH36),0) -> 0 | DU36: =IF(DG36>0,(Z36*DH36),0) -> 0 | DV36: =IF(DG36>0,(Y40*DH36),0) -> 0 | DW36: =IF(DG36>0,(Z40*DH36),0) -> 0 | DX36: =IF(DV36>0,DJ36,0) -> 0 | DY36: =IF(DW36>0,DJ36,0) -> 0
C37: CRISTAL | T37: =IFERROR(T36/$R$353,"") -> 0 | W37: ANGEO | X37: NO | BB37: CORTE 9 | BC37: V9 | BE37: ALFAJÍA | BF37: NO | BG37: LUCETA | BH37: NO
C38: ACABADO ALUMINIO | Q38: SANDBLASTING | R38: NO | T38: =IFERROR(($R$353-8000)*T37,"") -> 0 | W38: FACHADA | X38: NO | BB38: CORTE 10 | BC38: V10 | BE38: =IFERROR(VLOOKUP(D36,'BD M.O'!C:H,4,FALSE),"") | BF38: 2HOJAS
C39: PELÍCULA PROTECCIÓN | D39: PERFILES | F39: X | G39: CRISTAL | I39: =+IF($BG$9="SI","","X") -> X | R39: VIDRIO M2 | S39: =IF(S37="","",S37/(J36*K36)) | W39: =IFERROR(IF(X38="SI",VLOOKUP(D36,'BD M.O'!C:F,4,FALSE),""),"") | X39: FACHADA | Y39: M2 INOX | Z39: M2 ALU | BC39: V11 | BE39: =IFERROR(VLOOKUP(COTIZACIÓN!D36,'BD M.O'!C:I,5,FALSE),"") | BF39: 3HOJAS | DI39: =IFERROR(IF(DG39>0,(((N36)/(1+10%+19%*5%)+((N36)/(1+10%+19%*5%))*10%)*DH39),0),0) -> 0 | DJ39: =IFERROR(IF(DG39>0,(N36*DH39),0),0) -> 0 | DK39: =IF(DG39>0,((R36+T36)*DH39),0) -> 0 | DL39: =IF(DG39>0,(Q36*DH39),0) -> 0 | DM39: =IF(DG39>0,(S36*DH39),0) -> 0 | DN39: =IF(DG39>0,(BN36*DH39),0) -> 0 | DO39: =IF(DG39>0,(AF36*DH39),0) -> 0 | DP39: =IF(DG39>0,((DI39)*('BD P&G'!$E$16+'BD P&G'!$E$17+'BD P&G'!$E$18+'BD P&G'!$E$19+'BD P&G'!$E$20+'BD P&G'!$E$21+'BD P&G'!$E$22+'BD P&G'!$E$23)*DH39),0) -> 0 | DQ39: =IFERROR(IF(DG39>0,((DI39*'BD P&G'!$E$7)+(DI39*'BD P&G'!$E$9)+AI36),0),0) -> 0 | DR39: =IFERROR(IF(DG39>0,((DI39*1%)),0),0) -> 0 | DS39: =IFERROR(IF(DG39>0,(((DI39*'BD P&G'!$E$32+DI39*'BD P&G'!$E$33+DI39*'BD P&G'!$E$35+DI39*'BD P&G'!$E$36+DI39*'BD P&G'!$E$37))),0),0) -> 0 | DT39: =IF(DG39>0,(Y36*DH39),0) -> 0 | DU39: =IF(DG39>0,(Z36*DH39),0) -> 0 | DV39: =IF(DG39>0,(Y40*DH39),0) -> 0 | DW39: =IF(DG39>0,(Z40*DH39),0) -> 0 | DX39: =IF(DV39>0,DJ39,0) -> 0 | DY39: =IF(DW39>0,DJ39,0) -> 0
C40: CERRADURA | D40: =IFERROR(VLOOKUP(D36,'BD GN'!C:E,3,),"") | R40: SISTEMA M2 | S40: =IFERROR(IF(N36="","",N36/W40),"") | W40: =+IF(J36*K36>=1,J36*K36,IF(AND(J36*K36>0,J36*K36<1),1,"")) | X40: AREA | Y40: =IFERROR(IF(D36='BD GN'!$C$25,COTIZACIÓN!W40,IF(D36='BD GN'!$C$26,COTIZACIÓN!W40,IF(D36='BD GN'!$C$27,COTIZACIÓN!W40,IF(COTIZACIÓN!D36='BD GN'!$C$28,COTIZACIÓN!W40,IF(COTIZACIÓN!D36='BD GN'!$C$29,COTIZACIÓN!W40,IF(COTIZACIÓN!D36='BD GN'!$C$35,COTIZACIÓN!W40,IF(COTIZACIÓN!D36='BD GN'!$C$36,COTIZACIÓN!W40,IF(COTIZACIÓN!D36='BD GN'!$C$37,COTIZACIÓN!W40,IF(COTIZACIÓN!D36='BD GN'!$C$38,COTIZACIÓN!W40,IF(COTIZACIÓN!D36='BD GN'!$C$39,COTIZACIÓN!W40,IF(COTIZACIÓN!D36='BD GN'!$C$40,COTIZACIÓN!W40,IF(COTIZACIÓN!D36='BD GN'!$C$41,COTIZACIÓN!W40,IF(COTIZACIÓN!D36='BD GN'!$C$42,COTIZACIÓN!W40,IF(COTIZACIÓN!D36='BD GN'!$C$49,COTIZACIÓN!W40,IF(COTIZACIÓN!D36='BD GN'!$C$50,COTIZACIÓN!W40,IF(COTIZACIÓN!D36='BD GN'!$C$51,COTIZACIÓN!W40,IF(COTIZACIÓN!D36='BD GN'!$C$67,COTIZACIÓN!W40,0))))))))))))))))),0) -> 0 | Z40: =IFERROR(W40-Y40,0) -> 0 | BC40: V12 | BE40: =IFERROR(VLOOKUP(D36,'BD M.O'!C:I,6,FALSE),"") | BF40: 4HOJAS
C41: OBSERVACIONES | D41: N.A | R41: VR REF SIS M2 | S41: =IFERROR(IF($C$12='BD GN'!$CC$1,VLOOKUP(COTIZACIÓN!D36,'BD GN'!CB:CG,2,FALSE),IF(COTIZACIÓN!$C$12='BD GN'!$CD$1,VLOOKUP(COTIZACIÓN!D36,'BD GN'!CB:CG,3,FALSE),IF($C$12='BD GN'!$CE$1,VLOOKUP(COTIZACIÓN!D36,'BD GN'!CB:CG,4,FALSE),IF(COTIZACIÓN!$C$12='BD GN'!$CF$1,VLOOKUP(COTIZACIÓN!D36,'BD GN'!CB:CG,5,FALSE),IF(COTIZACIÓN!$C$12='BD GN'!$CG$1,VLOOKUP(COTIZACIÓN!D36,'BD GN'!CB:CG,6,FALSE),""))))),"-") | W41: TOTAL M.O | X41: =IFERROR(SUM(W36:X36),"") -> 0 | Y41: TOTAL M.O PYG | Z41: =IFERROR(Y36+Z36,"") | BC41: V13 | BE41: =IFERROR(VLOOKUP(D36,'BD M.O'!C:I,7,FALSE),"") | BF41: HOJA ADIC
A42: ÍTEM | B42: UBICACIÓN | C42: CONFIGURACIÓN | D42: DESCRIPCIÓN | J42: AN (MT) | K42: AL (MT) | L42: M2 | M42: CNT | N42: VR UNT | O42: VR TOTAL | Q42: ACCE | R42: ALUMINIO | S42: CRISTAL | T42: % DESP ALU | U42: EMPQ | V42: TRANS | W42: ENSAMBLE | X42: INSTA | Y42: ENSAM PYG | Z42: INST PYG | AA42: TOTAL M.O PYG | AB42: IMPREV | AC42: IMPREV PYG | AD42: BACKOFFICE | AE42: PYG | AF42: VIATICOS | AG42: BENEFICIO | AH42: BENEFICIO PYG | AI42: COMISIÓN | AJ42: IMPUESTOS | AK42: VENTA SIN PYG | AL42: VENTA FINAL | AM42: ACCE | AN42: ALUMINIO | AO42: CRISTAL | AP42: % DESP ALU | AQ42: MAQ | AR42: EMPQ | AS42: TRANS | AT42: ENSAMBLE | AU42: INSTA | AV42: IMPREV | AW42: BACKOFFICE | AX42: UTILIDAD | AY42: COMISIÓN | AZ42: VENTA | BC42: V14 | BE42: Nº MÓDULOS | BF42: =$BF$13 -> VR SILICONA | BG42: =$BG$13 -> VR PELÍCULA | BH42: =$BH$13 -> VR EMBALAJE | BJ42: =$BJ$13 -> ESP. CRISTAL | BK42: ESTRUCTURA | BL42: CRISTAL | BM42: =BM35 -> TOTAL | BN42: VR TRANSP | CK42: OR | CL42: MD | CM42: AD | CN42: EL | CO42: MD | CP42: PL | CQ42: PRO | CR42: DESP | CS42: MT | CT42: ENT | CU42: CNT | CV42: VR TOTAL | CW42: CNT | CX42: VR TOTAL | CY42: CNT | CZ42: VR TOTAL | DA42: CNT | DB42: VR TOTAL | DC42: CNT | DD42: VR TOTAL | DG42: RAD | DH42: CANTIDAD | DI42: SUBTOTAL | DJ42: TOTAL | DK42: ALU | DL42: ACC | DM42: VIDRIO | DN42: TRANSPORTE | DO42: VIATICOS | DP42: BACKOFFICE | DQ42: GAST VENTA | DR42: GAST FINANC | DS42: COSTOS IND | DT42: ENSAMBLE | DU42: INSTALACION | DV42: M2 INOX | DW42: M2 ALU | DX42: VR INOX | DY42: VR ALU
C43: SISTEMA | L43: =J43*K43*M43 -> 0 | N43: =IFERROR(AL43,"") -> 1.0765547 | O43: =IFERROR(N43*M43,"") -> 0 | Q43: =Q44+BF43+($R$350*Q44) -> 0 | R43: =IFERROR(R44+($R$348*R44),"") -> 0 | S43: =+IF(R45="SI",((W47*'BD GN'!$AB$2)+S44)*1,COTIZACIÓN!S44*1)+(P44*S44) -> 0 | T43: =IFERROR(R43*IF(K43<=3,$T$13,15%),"") -> 0 | U43: =BH43+BG43 -> 0 | V43: =IFERROR(BN43,0) | W43: =IFERROR(IF(X45="SI",W46*J43*K43,IF(BE43=3,BE45,IF(BE43=4,BE46,IF(BE43=5,BE47,IF(BE43>5,BE47+(BE48*(BE43-5)),"")))))*0,"") | X43: =IFERROR(IF(X44="NO",(VLOOKUP(D43,'BD M.O'!C:E,3,FALSE))*W47,((VLOOKUP(D43,'BD M.O'!C:E,3,FALSE))+7500)*W47),"") | Y43: =IFERROR($Y$13*AK43,"") -> 0.042084457 | Z43: =IFERROR(($Z$13*AK43)+X43,"") | AA43: =IFERROR(Y43+Z43,"") | AB43: =IFERROR((SUM(Q43:X43)-T43+T45)*$AB$13,"") -> 0 | AC43: =IFERROR(((SUM(Q43:V43,IF(X48>AA43,AVERAGE(X48,AA43),AA43))-T43+T45))*$AB$13,"") -> 0 | AD43: =IFERROR((J43*K43*$BV$14),"") | AE43: =IFERROR($AE$13*AK43,"") -> 0.064010593 | AF43: =IFERROR(($CI$11+$CI$13)*W47,"") | AG43: =IFERROR((SUM(Q43:X43,AB43,AD43,AF43)-T43+T45)*$AG$13,"") -> 0 | AH43: =IFERROR((SUM(Q43:V43,(IF(X48>AA43,AVERAGE(X48,AA43),AA43)),AC43,AE43,AF43)-T43+T45)*$AG$13,"") -> 0.032005296 | AI43: =IFERROR(AL43*$AI$13,"") -> 0.021531093 | AJ43: =IFERROR($AJ$13*AL43,"") -> 0.006007175 | AK43: =IFERROR(SUM(Q43:X43,AB43,AD43,AG43,AF43)/(1-$AI$13)+(1-$AJ$13)-T43+T45,"") -> 0.99442 | AL43: =IFERROR(SUM(Q43:V43,AC43,(IF(AD43>AE43,AVERAGE(AD43,AE43),AE43)),AF43,,AH43,(IF(SUM(X48)>AA43,AVERAGE(AA43,X48),AA43)))/(1-$AJ$13)+(1-$AI$13)-T43+T45,"") -> 1.0765547 | AM43: =$M$15*Q43 -> 0 | AN43: =$M$15*R43 -> 0 | AO43: =$M$15*S43 -> 0 | AP43: =$M$15*T43 -> 0 | AQ43: =$M$15*#REF! -> #REF! | AR43: =$M$15*U43 -> 0 | AS43: =$M$15*V43 -> #VALUE! | AT43: =$M$15*W43 -> #VALUE! | AU43: =$M$15*X43 -> #VALUE! | AV43: =$M$15*AB43 -> 0 | AW43: =$M$15*AE43 -> 0 | AX43: =$M$15*AG43 -> 0 | AY43: =$M$15*AI43 -> 0 | AZ43: =$M$15*AK43 -> 0 | BB43: CORTE 8 | BC43: V8 | BF43: =IF(BH44="NO",((2*J43)+(2*K43))*'BD GN'!$AU$3,((3*J43)+(2*K43))*'BD GN'!$AU$3) -> 0 | BG43: ='BD GN'!$BB$3*J43*K43 -> 0 | BH43: =((J43*2*BE43)+(K43*2*BE43))*'BD GN'!$AN$4 -> 0 | BL43: =J43*K43*2.5*BJ43 -> 0 | BM43: =BK43+BL43 -> 0 | BN43: =IFERROR((VLOOKUP($C$12,'BD GN'!BD:BM,10,FALSE)*BM43)+$BR$338,"") | CV43: =IFERROR(N43*CU43,"") -> 0 | CX43: =IFERROR(P43*CW43,"") -> 0 | CZ43: =IFERROR(R43*CY43,"") -> 0 | DA43: =CU43+CW43+CY43 -> 0 | DB43: =IFERROR(CV43+CX43+CZ43,"") -> 0 | DC43: =M43-(CU43+CW43+CY43) -> 0 | DD43: =IFERROR(O43-(CV43+CX43+CZ43),"") -> 0 | DI43: =IFERROR(IF(DG43>0,(((N43)/(1+10%+19%*5%)+((N43)/(1+10%+19%*5%))*10%)*DH43),0),0) -> 0 | DJ43: =IFERROR(IF(DG43>0,(N43*DH43),0),0) -> 0 | DK43: =IF(DG43>0,((R43+T43)*DH43),0) -> 0 | DL43: =IF(DG43>0,(Q43*DH43),0) -> 0 | DM43: =IF(DG43>0,(S43*DH43),0) -> 0 | DN43: =IF(DG43>0,(BN43*DH43),0) -> 0 | DO43: =IF(DG43>0,(AF43*DH43),0) -> 0 | DP43: =IF(DG43>0,((DI43)*('BD P&G'!$E$16+'BD P&G'!$E$17+'BD P&G'!$E$18+'BD P&G'!$E$19+'BD P&G'!$E$20+'BD P&G'!$E$21+'BD P&G'!$E$22+'BD P&G'!$E$23)*DH43),0) -> 0 | DQ43: =IFERROR(IF(DG43>0,((DI43*'BD P&G'!$E$7)+(DI43*'BD P&G'!$E$9)+AI43),0),0) -> 0 | DR43: =IFERROR(IF(DG43>0,((DI43*1%)),0),0) -> 0 | DS43: =IFERROR(IF(DG43>0,(((DI43*'BD P&G'!$E$32+DI43*'BD P&G'!$E$33+DI43*'BD P&G'!$E$35+DI43*'BD P&G'!$E$36+DI43*'BD P&G'!$E$37))),0),0) -> 0 | DT43: =IF(DG43>0,(Y43*DH43),0) -> 0 | DU43: =IF(DG43>0,(Z43*DH43),0) -> 0 | DV43: =IF(DG43>0,(Y47*DH43),0) -> 0 | DW43: =IF(DG43>0,(Z47*DH43),0) -> 0 | DX43: =IF(DV43>0,DJ43,0) -> 0 | DY43: =IF(DW43>0,DJ43,0) -> 0
C44: CRISTAL | T44: =IFERROR(T43/$R$353,"") -> 0 | W44: ANGEO | X44: NO | BB44: CORTE 9 | BC44: V9 | BE44: ALFAJÍA | BF44: NO | BG44: LUCETA | BH44: NO
C45: ACABADO ALUMINIO | Q45: SANDBLASTING | R45: NO | T45: =IFERROR(($R$353-8000)*T44,"") -> 0 | W45: FACHADA | X45: NO | BB45: CORTE 10 | BC45: V10 | BE45: =IFERROR(VLOOKUP(D43,'BD M.O'!C:H,4,FALSE),"") | BF45: 2HOJAS
C46: PELÍCULA PROTECCIÓN | D46: PERFILES | F46: X | G46: CRISTAL | I46: =+IF($BG$9="SI","","X") -> X | R46: VIDRIO M2 | S46: =IF(S44="","",S44/(J43*K43)) | W46: =IFERROR(IF(X45="SI",VLOOKUP(D43,'BD M.O'!C:F,4,FALSE),""),"") | X46: FACHADA | Y46: M2 INOX | Z46: M2 ALU | BC46: V11 | BE46: =IFERROR(VLOOKUP(COTIZACIÓN!D43,'BD M.O'!C:I,5,FALSE),"") | BF46: 3HOJAS | DI46: =IFERROR(IF(DG46>0,(((N43)/(1+10%+19%*5%)+((N43)/(1+10%+19%*5%))*10%)*DH46),0),0) -> 0 | DJ46: =IFERROR(IF(DG46>0,(N43*DH46),0),0) -> 0 | DK46: =IF(DG46>0,((R43+T43)*DH46),0) -> 0 | DL46: =IF(DG46>0,(Q43*DH46),0) -> 0 | DM46: =IF(DG46>0,(S43*DH46),0) -> 0 | DN46: =IF(DG46>0,(BN43*DH46),0) -> 0 | DO46: =IF(DG46>0,(AF43*DH46),0) -> 0 | DP46: =IF(DG46>0,((DI46)*('BD P&G'!$E$16+'BD P&G'!$E$17+'BD P&G'!$E$18+'BD P&G'!$E$19+'BD P&G'!$E$20+'BD P&G'!$E$21+'BD P&G'!$E$22+'BD P&G'!$E$23)*DH46),0) -> 0 | DQ46: =IFERROR(IF(DG46>0,((DI46*'BD P&G'!$E$7)+(DI46*'BD P&G'!$E$9)+AI43),0),0) -> 0 | DR46: =IFERROR(IF(DG46>0,((DI46*1%)),0),0) -> 0 | DS46: =IFERROR(IF(DG46>0,(((DI46*'BD P&G'!$E$32+DI46*'BD P&G'!$E$33+DI46*'BD P&G'!$E$35+DI46*'BD P&G'!$E$36+DI46*'BD P&G'!$E$37))),0),0) -> 0 | DT46: =IF(DG46>0,(Y43*DH46),0) -> 0 | DU46: =IF(DG46>0,(Z43*DH46),0) -> 0 | DV46: =IF(DG46>0,(Y47*DH46),0) -> 0 | DW46: =IF(DG46>0,(Z47*DH46),0) -> 0 | DX46: =IF(DV46>0,DJ46,0) -> 0 | DY46: =IF(DW46>0,DJ46,0) -> 0
C47: CERRADURA | D47: =IFERROR(VLOOKUP(D43,'BD GN'!C:E,3,),"") | R47: SISTEMA M2 | S47: =IFERROR(IF(N43="","",N43/W47),"") | W47: =+IF(J43*K43>=1,J43*K43,IF(AND(J43*K43>0,J43*K43<1),1,"")) | X47: AREA | Y47: =IFERROR(IF(D43='BD GN'!$C$25,COTIZACIÓN!W47,IF(D43='BD GN'!$C$26,COTIZACIÓN!W47,IF(D43='BD GN'!$C$27,COTIZACIÓN!W47,IF(COTIZACIÓN!D43='BD GN'!$C$28,COTIZACIÓN!W47,IF(COTIZACIÓN!D43='BD GN'!$C$29,COTIZACIÓN!W47,IF(COTIZACIÓN!D43='BD GN'!$C$35,COTIZACIÓN!W47,IF(COTIZACIÓN!D43='BD GN'!$C$36,COTIZACIÓN!W47,IF(COTIZACIÓN!D43='BD GN'!$C$37,COTIZACIÓN!W47,IF(COTIZACIÓN!D43='BD GN'!$C$38,COTIZACIÓN!W47,IF(COTIZACIÓN!D43='BD GN'!$C$39,COTIZACIÓN!W47,IF(COTIZACIÓN!D43='BD GN'!$C$40,COTIZACIÓN!W47,IF(COTIZACIÓN!D43='BD GN'!$C$41,COTIZACIÓN!W47,IF(COTIZACIÓN!D43='BD GN'!$C$42,COTIZACIÓN!W47,IF(COTIZACIÓN!D43='BD GN'!$C$49,COTIZACIÓN!W47,IF(COTIZACIÓN!D43='BD GN'!$C$50,COTIZACIÓN!W47,IF(COTIZACIÓN!D43='BD GN'!$C$51,COTIZACIÓN!W47,IF(COTIZACIÓN!D43='BD GN'!$C$67,COTIZACIÓN!W47,0))))))))))))))))),0) -> 0 | Z47: =IFERROR(W47-Y47,0) -> 0 | BC47: V12 | BE47: =IFERROR(VLOOKUP(D43,'BD M.O'!C:I,6,FALSE),"") | BF47: 4HOJAS
C48: OBSERVACIONES | D48: N.A | R48: VR REF SIS M2 | S48: =IFERROR(IF($C$12='BD GN'!$CC$1,VLOOKUP(COTIZACIÓN!D43,'BD GN'!CB:CG,2,FALSE),IF(COTIZACIÓN!$C$12='BD GN'!$CD$1,VLOOKUP(COTIZACIÓN!D43,'BD GN'!CB:CG,3,FALSE),IF($C$12='BD GN'!$CE$1,VLOOKUP(COTIZACIÓN!D43,'BD GN'!CB:CG,4,FALSE),IF(COTIZACIÓN!$C$12='BD GN'!$CF$1,VLOOKUP(COTIZACIÓN!D43,'BD GN'!CB:CG,5,FALSE),IF(COTIZACIÓN!$C$12='BD GN'!$CG$1,VLOOKUP(COTIZACIÓN!D43,'BD GN'!CB:CG,6,FALSE),""))))),"-") | W48: TOTAL M.O | X48: =IFERROR(SUM(W43:X43),"") -> 0 | Y48: TOTAL M.O PYG | Z48: =IFERROR(Y43+Z43,"") | BC48: V13 | BE48: =IFERROR(VLOOKUP(D43,'BD M.O'!C:I,7,FALSE),"") | BF48: HOJA ADIC
A49: ÍTEM | B49: UBICACIÓN | C49: CONFIGURACIÓN | D49: DESCRIPCIÓN | J49: AN (MT) | K49: AL (MT) | L49: M2 | M49: CNT | N49: VR UNT | O49: VR TOTAL | Q49: ACCE | R49: ALUMINIO | S49: CRISTAL | T49: % DESP ALU | U49: EMPQ | V49: TRANS | W49: ENSAMBLE | X49: INSTA | Y49: ENSAM PYG | Z49: INST PYG | AA49: TOTAL M.O PYG | AB49: IMPREV | AC49: IMPREV PYG | AD49: BACKOFFICE | AE49: PYG | AF49: VIATICOS | AG49: BENEFICIO | AH49: BENEFICIO PYG | AI49: COMISIÓN | AJ49: IMPUESTOS | AK49: VENTA SIN PYG | AL49: VENTA FINAL | AM49: ACCE | AN49: ALUMINIO | AO49: CRISTAL | AP49: % DESP ALU | AQ49: MAQ | AR49: EMPQ | AS49: TRANS | AT49: ENSAMBLE | AU49: INSTA | AV49: IMPREV | AW49: BACKOFFICE | AX49: UTILIDAD | AY49: COMISIÓN | AZ49: VENTA | BC49: V14 | BE49: Nº MÓDULOS | BF49: =$BF$13 -> VR SILICONA | BG49: =$BG$13 -> VR PELÍCULA | BH49: =$BH$13 -> VR EMBALAJE | BJ49: =$BJ$13 -> ESP. CRISTAL | BK49: ESTRUCTURA | BL49: CRISTAL | BM49: =BM42 -> TOTAL | BN49: VR TRANSP | CK49: OR | CL49: MD | CM49: AD | CN49: EL | CO49: MD | CP49: PL | CQ49: PRO | CR49: DESP | CS49: MT | CT49: ENT | CU49: CNT | CV49: VR TOTAL | CW49: CNT | CX49: VR TOTAL | CY49: CNT | CZ49: VR TOTAL | DA49: CNT | DB49: VR TOTAL | DC49: CNT | DD49: VR TOTAL | DG49: RAD | DH49: CANTIDAD | DI49: SUBTOTAL | DJ49: TOTAL | DK49: ALU | DL49: ACC | DM49: VIDRIO | DN49: TRANSPORTE | DO49: VIATICOS | DP49: BACKOFFICE | DQ49: GAST VENTA | DR49: GAST FINANC | DS49: COSTOS IND | DT49: ENSAMBLE | DU49: INSTALACION | DV49: M2 INOX | DW49: M2 ALU | DX49: VR INOX | DY49: VR ALU
C50: SISTEMA | L50: =J50*K50*M50 -> 0 | N50: =IFERROR(AL50,"") -> 1.0765547 | O50: =IFERROR(N50*M50,"") -> 0 | Q50: =Q51+BF50+($R$350*Q51) -> 0 | R50: =IFERROR(R51+($R$348*R51),"") -> 0 | S50: =+IF(R52="SI",((W54*'BD GN'!$AB$2)+S51)*1,COTIZACIÓN!S51*1)+(P51*S51) -> 0 | T50: =IFERROR(R50*IF(K50<=3,$T$13,15%),"") -> 0 | U50: =BH50+BG50 -> 0 | V50: =IFERROR(BN50,0) | W50: =IFERROR(IF(X52="SI",W53*J50*K50,IF(BE50=3,BE52,IF(BE50=4,BE53,IF(BE50=5,BE54,IF(BE50>5,BE54+(BE55*(BE50-5)),"")))))*0,"") | X50: =IFERROR(IF(X51="NO",(VLOOKUP(D50,'BD M.O'!C:E,3,FALSE))*W54,((VLOOKUP(D50,'BD M.O'!C:E,3,FALSE))+7500)*W54),"") | Y50: =IFERROR($Y$13*AK50,"") -> 0.042084457 | Z50: =IFERROR(($Z$13*AK50)+X50,"") | AA50: =IFERROR(Y50+Z50,"") | AB50: =IFERROR((SUM(Q50:X50)-T50+T52)*$AB$13,"") -> 0 | AC50: =IFERROR(((SUM(Q50:V50,IF(X55>AA50,AVERAGE(X55,AA50),AA50))-T50+T52))*$AB$13,"") -> 0 | AD50: =IFERROR((J50*K50*$BV$14),"") | AE50: =IFERROR($AE$13*AK50,"") -> 0.064010593 | AF50: =IFERROR(($CI$11+$CI$13)*W54,"") | AG50: =IFERROR((SUM(Q50:X50,AB50,AD50,AF50)-T50+T52)*$AG$13,"") -> 0 | AH50: =IFERROR((SUM(Q50:V50,(IF(X55>AA50,AVERAGE(X55,AA50),AA50)),AC50,AE50,AF50)-T50+T52)*$AG$13,"") -> 0.032005296 | AI50: =IFERROR(AL50*$AI$13,"") -> 0.021531093 | AJ50: =IFERROR($AJ$13*AL50,"") -> 0.006007175 | AK50: =IFERROR(SUM(Q50:X50,AB50,AD50,AG50,AF50)/(1-$AI$13)+(1-$AJ$13)-T50+T52,"") -> 0.99442 | AL50: =IFERROR(SUM(Q50:V50,AC50,(IF(AD50>AE50,AVERAGE(AD50,AE50),AE50)),AF50,,AH50,(IF(SUM(X55)>AA50,AVERAGE(AA50,X55),AA50)))/(1-$AJ$13)+(1-$AI$13)-T50+T52,"") -> 1.0765547 | AM50: =$M$15*Q50 -> 0 | AN50: =$M$15*R50 -> 0 | AO50: =$M$15*S50 -> 0 | AP50: =$M$15*T50 -> 0 | AQ50: =$M$15*#REF! -> #REF! | AR50: =$M$15*U50 -> 0 | AS50: =$M$15*V50 -> #VALUE! | AT50: =$M$15*W50 -> #VALUE! | AU50: =$M$15*X50 -> #VALUE! | AV50: =$M$15*AB50 -> 0 | AW50: =$M$15*AE50 -> 0 | AX50: =$M$15*AG50 -> 0 | AY50: =$M$15*AI50 -> 0 | AZ50: =$M$15*AK50 -> 0 | BB50: CORTE 8 | BC50: V8 | BF50: =IF(BH51="NO",((2*J50)+(2*K50))*'BD GN'!$AU$3,((3*J50)+(2*K50))*'BD GN'!$AU$3) -> 0 | BG50: ='BD GN'!$BB$3*J50*K50 -> 0 | BH50: =((J50*2*BE50)+(K50*2*BE50))*'BD GN'!$AN$4 -> 0 | BL50: =J50*K50*2.5*BJ50 -> 0 | BM50: =BK50+BL50 -> 0 | BN50: =IFERROR((VLOOKUP($C$12,'BD GN'!BD:BM,10,FALSE)*BM50)+$BR$338,"") | CV50: =IFERROR(N50*CU50,"") -> 0 | CX50: =IFERROR(P50*CW50,"") -> 0 | CZ50: =IFERROR(R50*CY50,"") -> 0 | DA50: =CU50+CW50+CY50 -> 0 | DB50: =IFERROR(CV50+CX50+CZ50,"") -> 0 | DC50: =M50-(CU50+CW50+CY50) -> 0 | DD50: =IFERROR(O50-(CV50+CX50+CZ50),"") -> 0 | DI50: =IFERROR(IF(DG50>0,(((N50)/(1+10%+19%*5%)+((N50)/(1+10%+19%*5%))*10%)*DH50),0),0) -> 0 | DJ50: =IFERROR(IF(DG50>0,(N50*DH50),0),0) -> 0 | DK50: =IF(DG50>0,((R50+T50)*DH50),0) -> 0 | DL50: =IF(DG50>0,(Q50*DH50),0) -> 0 | DM50: =IF(DG50>0,(S50*DH50),0) -> 0 | DN50: =IF(DG50>0,(BN50*DH50),0) -> 0 | DO50: =IF(DG50>0,(AF50*DH50),0) -> 0 | DP50: =IF(DG50>0,((DI50)*('BD P&G'!$E$16+'BD P&G'!$E$17+'BD P&G'!$E$18+'BD P&G'!$E$19+'BD P&G'!$E$20+'BD P&G'!$E$21+'BD P&G'!$E$22+'BD P&G'!$E$23)*DH50),0) -> 0 | DQ50: =IFERROR(IF(DG50>0,((DI50*'BD P&G'!$E$7)+(DI50*'BD P&G'!$E$9)+AI50),0),0) -> 0 | DR50: =IFERROR(IF(DG50>0,((DI50*1%)),0),0) -> 0 | DS50: =IFERROR(IF(DG50>0,(((DI50*'BD P&G'!$E$32+DI50*'BD P&G'!$E$33+DI50*'BD P&G'!$E$35+DI50*'BD P&G'!$E$36+DI50*'BD P&G'!$E$37))),0),0) -> 0 | DT50: =IF(DG50>0,(Y50*DH50),0) -> 0 | DU50: =IF(DG50>0,(Z50*DH50),0) -> 0 | DV50: =IF(DG50>0,(Y54*DH50),0) -> 0 | DW50: =IF(DG50>0,(Z54*DH50),0) -> 0 | DX50: =IF(DV50>0,DJ50,0) -> 0 | DY50: =IF(DW50>0,DJ50,0) -> 0
C51: CRISTAL | T51: =IFERROR(T50/$R$353,"") -> 0 | W51: ANGEO | X51: NO | BB51: CORTE 9 | BC51: V9 | BE51: ALFAJÍA | BF51: NO | BG51: LUCETA | BH51: NO
C52: ACABADO ALUMINIO | Q52: SANDBLASTING | R52: NO | T52: =IFERROR(($R$353-8000)*T51,"") -> 0 | W52: FACHADA | X52: NO | BB52: CORTE 10 | BC52: V10 | BE52: =IFERROR(VLOOKUP(D50,'BD M.O'!C:H,4,FALSE),"") | BF52: 2HOJAS
C53: PELÍCULA PROTECCIÓN | D53: PERFILES | F53: X | G53: CRISTAL | I53: =+IF($BG$9="SI","","X") -> X | R53: VIDRIO M2 | S53: =IF(S51="","",S51/(J50*K50)) | W53: =IFERROR(IF(X52="SI",VLOOKUP(D50,'BD M.O'!C:F,4,FALSE),""),"") | X53: FACHADA | Y53: M2 INOX | Z53: M2 ALU | BC53: V11 | BE53: =IFERROR(VLOOKUP(COTIZACIÓN!D50,'BD M.O'!C:I,5,FALSE),"") | BF53: 3HOJAS | DI53: =IFERROR(IF(DG53>0,(((N50)/(1+10%+19%*5%)+((N50)/(1+10%+19%*5%))*10%)*DH53),0),0) -> 0 | DJ53: =IFERROR(IF(DG53>0,(N50*DH53),0),0) -> 0 | DK53: =IF(DG53>0,((R50+T50)*DH53),0) -> 0 | DL53: =IF(DG53>0,(Q50*DH53),0) -> 0 | DM53: =IF(DG53>0,(S50*DH53),0) -> 0 | DN53: =IF(DG53>0,(BN50*DH53),0) -> 0 | DO53: =IF(DG53>0,(AF50*DH53),0) -> 0 | DP53: =IF(DG53>0,((DI53)*('BD P&G'!$E$16+'BD P&G'!$E$17+'BD P&G'!$E$18+'BD P&G'!$E$19+'BD P&G'!$E$20+'BD P&G'!$E$21+'BD P&G'!$E$22+'BD P&G'!$E$23)*DH53),0) -> 0 | DQ53: =IFERROR(IF(DG53>0,((DI53*'BD P&G'!$E$7)+(DI53*'BD P&G'!$E$9)+AI50),0),0) -> 0 | DR53: =IFERROR(IF(DG53>0,((DI53*1%)),0),0) -> 0 | DS53: =IFERROR(IF(DG53>0,(((DI53*'BD P&G'!$E$32+DI53*'BD P&G'!$E$33+DI53*'BD P&G'!$E$35+DI53*'BD P&G'!$E$36+DI53*'BD P&G'!$E$37))),0),0) -> 0 | DT53: =IF(DG53>0,(Y50*DH53),0) -> 0 | DU53: =IF(DG53>0,(Z50*DH53),0) -> 0 | DV53: =IF(DG53>0,(Y54*DH53),0) -> 0 | DW53: =IF(DG53>0,(Z54*DH53),0) -> 0 | DX53: =IF(DV53>0,DJ53,0) -> 0 | DY53: =IF(DW53>0,DJ53,0) -> 0
C54: CERRADURA | D54: =IFERROR(VLOOKUP(D50,'BD GN'!C:E,3,),"") | R54: SISTEMA M2 | S54: =IFERROR(IF(N50="","",N50/W54),"") | W54: =+IF(J50*K50>=1,J50*K50,IF(AND(J50*K50>0,J50*K50<1),1,"")) | X54: AREA | Y54: =IFERROR(IF(D50='BD GN'!$C$25,COTIZACIÓN!W54,IF(D50='BD GN'!$C$26,COTIZACIÓN!W54,IF(D50='BD GN'!$C$27,COTIZACIÓN!W54,IF(COTIZACIÓN!D50='BD GN'!$C$28,COTIZACIÓN!W54,IF(COTIZACIÓN!D50='BD GN'!$C$29,COTIZACIÓN!W54,IF(COTIZACIÓN!D50='BD GN'!$C$35,COTIZACIÓN!W54,IF(COTIZACIÓN!D50='BD GN'!$C$36,COTIZACIÓN!W54,IF(COTIZACIÓN!D50='BD GN'!$C$37,COTIZACIÓN!W54,IF(COTIZACIÓN!D50='BD GN'!$C$38,COTIZACIÓN!W54,IF(COTIZACIÓN!D50='BD GN'!$C$39,COTIZACIÓN!W54,IF(COTIZACIÓN!D50='BD GN'!$C$40,COTIZACIÓN!W54,IF(COTIZACIÓN!D50='BD GN'!$C$41,COTIZACIÓN!W54,IF(COTIZACIÓN!D50='BD GN'!$C$42,COTIZACIÓN!W54,IF(COTIZACIÓN!D50='BD GN'!$C$49,COTIZACIÓN!W54,IF(COTIZACIÓN!D50='BD GN'!$C$50,COTIZACIÓN!W54,IF(COTIZACIÓN!D50='BD GN'!$C$51,COTIZACIÓN!W54,IF(COTIZACIÓN!D50='BD GN'!$C$67,COTIZACIÓN!W54,0))))))))))))))))),0) -> 0 | Z54: =IFERROR(W54-Y54,0) -> 0 | BC54: V12 | BE54: =IFERROR(VLOOKUP(D50,'BD M.O'!C:I,6,FALSE),"") | BF54: 4HOJAS
C55: OBSERVACIONES | D55: N.A | R55: VR REF SIS M2 | S55: =IFERROR(IF($C$12='BD GN'!$CC$1,VLOOKUP(COTIZACIÓN!D50,'BD GN'!CB:CG,2,FALSE),IF(COTIZACIÓN!$C$12='BD GN'!$CD$1,VLOOKUP(COTIZACIÓN!D50,'BD GN'!CB:CG,3,FALSE),IF($C$12='BD GN'!$CE$1,VLOOKUP(COTIZACIÓN!D50,'BD GN'!CB:CG,4,FALSE),IF(COTIZACIÓN!$C$12='BD GN'!$CF$1,VLOOKUP(COTIZACIÓN!D50,'BD GN'!CB:CG,5,FALSE),IF(COTIZACIÓN!$C$12='BD GN'!$CG$1,VLOOKUP(COTIZACIÓN!D50,'BD GN'!CB:CG,6,FALSE),""))))),"-") | W55: TOTAL M.O | X55: =IFERROR(SUM(W50:X50),"") -> 0 | Y55: TOTAL M.O PYG | Z55: =IFERROR(Y50+Z50,"") | BC55: V13 | BE55: =IFERROR(VLOOKUP(D50,'BD M.O'!C:I,7,FALSE),"") | BF55: HOJA ADIC
A56: ÍTEM | B56: UBICACIÓN | C56: CONFIGURACIÓN | D56: DESCRIPCIÓN | J56: AN (MT) | K56: AL (MT) | L56: M2 | M56: CNT | N56: VR UNT | O56: VR TOTAL | Q56: ACCE | R56: ALUMINIO | S56: CRISTAL | T56: % DESP ALU | U56: EMPQ | V56: TRANS | W56: ENSAMBLE | X56: INSTA | Y56: ENSAM PYG | Z56: INST PYG | AA56: TOTAL M.O PYG | AB56: IMPREV | AC56: IMPREV PYG | AD56: BACKOFFICE | AE56: PYG | AF56: VIATICOS | AG56: BENEFICIO | AH56: BENEFICIO PYG | AI56: COMISIÓN | AJ56: IMPUESTOS | AK56: VENTA SIN PYG | AL56: VENTA FINAL | AM56: ACCE | AN56: ALUMINIO | AO56: CRISTAL | AP56: % DESP ALU | AQ56: MAQ | AR56: EMPQ | AS56: TRANS | AT56: ENSAMBLE | AU56: INSTA | AV56: IMPREV | AW56: BACKOFFICE | AX56: UTILIDAD | AY56: COMISIÓN | AZ56: VENTA | BC56: V14 | BE56: Nº MÓDULOS | BF56: =$BF$13 -> VR SILICONA | BG56: =$BG$13 -> VR PELÍCULA | BH56: =$BH$13 -> VR EMBALAJE | BJ56: =$BJ$13 -> ESP. CRISTAL | BK56: ESTRUCTURA | BL56: CRISTAL | BM56: =BM49 -> TOTAL | BN56: VR TRANSP | CK56: OR | CL56: MD | CM56: AD | CN56: EL | CO56: MD | CP56: PL | CQ56: PRO | CR56: DESP | CS56: MT | CT56: ENT | CU56: CNT | CV56: VR TOTAL | CW56: CNT | CX56: VR TOTAL | CY56: CNT | CZ56: VR TOTAL | DA56: CNT | DB56: VR TOTAL | DC56: CNT | DD56: VR TOTAL | DG56: RAD | DH56: CANTIDAD | DI56: SUBTOTAL | DJ56: TOTAL | DK56: ALU | DL56: ACC | DM56: VIDRIO | DN56: TRANSPORTE | DO56: VIATICOS | DP56: BACKOFFICE | DQ56: GAST VENTA | DR56: GAST FINANC | DS56: COSTOS IND | DT56: ENSAMBLE | DU56: INSTALACION | DV56: M2 INOX | DW56: M2 ALU | DX56: VR INOX | DY56: VR ALU
C57: SISTEMA | L57: =J57*K57*M57 -> 0 | N57: =IFERROR(AL57,"") -> 1.0765547 | O57: =IFERROR(N57*M57,"") -> 0 | Q57: =Q58+BF57+($R$350*Q58) -> 0 | R57: =IFERROR(R58+($R$348*R58),"") -> 0 | S57: =+IF(R59="SI",((W61*'BD GN'!$AB$2)+S58)*1,COTIZACIÓN!S58*1)+(P58*S58) -> 0 | T57: =IFERROR(R57*IF(K57<=3,$T$13,15%),"") -> 0 | U57: =BH57+BG57 -> 0 | V57: =IFERROR(BN57,0) | W57: =IFERROR(IF(X59="SI",W60*J57*K57,IF(BE57=3,BE59,IF(BE57=4,BE60,IF(BE57=5,BE61,IF(BE57>5,BE61+(BE62*(BE57-5)),"")))))*0,"") | X57: =IFERROR(IF(X58="NO",(VLOOKUP(D57,'BD M.O'!C:E,3,FALSE))*W61,((VLOOKUP(D57,'BD M.O'!C:E,3,FALSE))+7500)*W61),"") | Y57: =IFERROR($Y$13*AK57,"") -> 0.042084457 | Z57: =IFERROR(($Z$13*AK57)+X57,"") | AA57: =IFERROR(Y57+Z57,"") | AB57: =IFERROR((SUM(Q57:X57)-T57+T59)*$AB$13,"") -> 0 | AC57: =IFERROR(((SUM(Q57:V57,IF(X62>AA57,AVERAGE(X62,AA57),AA57))-T57+T59))*$AB$13,"") -> 0 | AD57: =IFERROR((J57*K57*$BV$14),"") | AE57: =IFERROR($AE$13*AK57,"") -> 0.064010593 | AF57: =IFERROR(($CI$11+$CI$13)*W61,"") | AG57: =IFERROR((SUM(Q57:X57,AB57,AD57,AF57)-T57+T59)*$AG$13,"") -> 0 | AH57: =IFERROR((SUM(Q57:V57,(IF(X62>AA57,AVERAGE(X62,AA57),AA57)),AC57,AE57,AF57)-T57+T59)*$AG$13,"") -> 0.032005296 | AI57: =IFERROR(AL57*$AI$13,"") -> 0.021531093 | AJ57: =IFERROR($AJ$13*AL57,"") -> 0.006007175 | AK57: =IFERROR(SUM(Q57:X57,AB57,AD57,AG57,AF57)/(1-$AI$13)+(1-$AJ$13)-T57+T59,"") -> 0.99442 | AL57: =IFERROR(SUM(Q57:V57,AC57,(IF(AD57>AE57,AVERAGE(AD57,AE57),AE57)),AF57,,AH57,(IF(SUM(X62)>AA57,AVERAGE(AA57,X62),AA57)))/(1-$AJ$13)+(1-$AI$13)-T57+T59,"") -> 1.0765547 | AM57: =$M$15*Q57 -> 0 | AN57: =$M$15*R57 -> 0 | AO57: =$M$15*S57 -> 0 | AP57: =$M$15*T57 -> 0 | AQ57: =$M$15*#REF! -> #REF! | AR57: =$M$15*U57 -> 0 | AS57: =$M$15*V57 -> #VALUE! | AT57: =$M$15*W57 -> #VALUE! | AU57: =$M$15*X57 -> #VALUE! | AV57: =$M$15*AB57 -> 0 | AW57: =$M$15*AE57 -> 0 | AX57: =$M$15*AG57 -> 0 | AY57: =$M$15*AI57 -> 0 | AZ57: =$M$15*AK57 -> 0 | BB57: CORTE 8 | BC57: V8 | BF57: =IF(BH58="NO",((2*J57)+(2*K57))*'BD GN'!$AU$3,((3*J57)+(2*K57))*'BD GN'!$AU$3) -> 0 | BG57: ='BD GN'!$BB$3*J57*K57 -> 0 | BH57: =((J57*2*BE57)+(K57*2*BE57))*'BD GN'!$AN$4 -> 0 | BL57: =J57*K57*2.5*BJ57 -> 0 | BM57: =BK57+BL57 -> 0 | BN57: =IFERROR((VLOOKUP($C$12,'BD GN'!BD:BM,10,FALSE)*BM57)+$BR$338,"") | CV57: =IFERROR(N57*CU57,"") -> 0 | CX57: =IFERROR(P57*CW57,"") -> 0 | CZ57: =IFERROR(R57*CY57,"") -> 0 | DA57: =CU57+CW57+CY57 -> 0 | DB57: =IFERROR(CV57+CX57+CZ57,"") -> 0 | DC57: =M57-(CU57+CW57+CY57) -> 0 | DD57: =IFERROR(O57-(CV57+CX57+CZ57),"") -> 0 | DI57: =IFERROR(IF(DG57>0,(((N57)/(1+10%+19%*5%)+((N57)/(1+10%+19%*5%))*10%)*DH57),0),0) -> 0 | DJ57: =IFERROR(IF(DG57>0,(N57*DH57),0),0) -> 0 | DK57: =IF(DG57>0,((R57+T57)*DH57),0) -> 0 | DL57: =IF(DG57>0,(Q57*DH57),0) -> 0 | DM57: =IF(DG57>0,(S57*DH57),0) -> 0 | DN57: =IF(DG57>0,(BN57*DH57),0) -> 0 | DO57: =IF(DG57>0,(AF57*DH57),0) -> 0 | DP57: =IF(DG57>0,((DI57)*('BD P&G'!$E$16+'BD P&G'!$E$17+'BD P&G'!$E$18+'BD P&G'!$E$19+'BD P&G'!$E$20+'BD P&G'!$E$21+'BD P&G'!$E$22+'BD P&G'!$E$23)*DH57),0) -> 0 | DQ57: =IFERROR(IF(DG57>0,((DI57*'BD P&G'!$E$7)+(DI57*'BD P&G'!$E$9)+AI57),0),0) -> 0 | DR57: =IFERROR(IF(DG57>0,((DI57*1%)),0),0) -> 0 | DS57: =IFERROR(IF(DG57>0,(((DI57*'BD P&G'!$E$32+DI57*'BD P&G'!$E$33+DI57*'BD P&G'!$E$35+DI57*'BD P&G'!$E$36+DI57*'BD P&G'!$E$37))),0),0) -> 0 | DT57: =IF(DG57>0,(Y57*DH57),0) -> 0 | DU57: =IF(DG57>0,(Z57*DH57),0) -> 0 | DV57: =IF(DG57>0,(Y61*DH57),0) -> 0 | DW57: =IF(DG57>0,(Z61*DH57),0) -> 0 | DX57: =IF(DV57>0,DJ57,0) -> 0 | DY57: =IF(DW57>0,DJ57,0) -> 0
C58: CRISTAL | T58: =IFERROR(T57/$R$353,"") -> 0 | W58: ANGEO | X58: NO | BB58: CORTE 9 | BC58: V9 | BE58: ALFAJÍA | BF58: NO | BG58: LUCETA | BH58: NO
C59: ACABADO ALUMINIO | Q59: SANDBLASTING | R59: NO | T59: =IFERROR(($R$353-8000)*T58,"") -> 0 | W59: FACHADA | X59: NO | BB59: CORTE 10 | BC59: V10 | BE59: =IFERROR(VLOOKUP(D57,'BD M.O'!C:H,4,FALSE),"") | BF59: 2HOJAS
C60: PELÍCULA PROTECCIÓN | D60: PERFILES | F60: X | G60: CRISTAL | I60: =+IF($BG$9="SI","","X") -> X | R60: VIDRIO M2 | S60: =IF(S58="","",S58/(J57*K57)) | W60: =IFERROR(IF(X59="SI",VLOOKUP(D57,'BD M.O'!C:F,4,FALSE),""),"") | X60: FACHADA | Y60: M2 INOX | Z60: M2 ALU | BC60: V11 | BE60: =IFERROR(VLOOKUP(COTIZACIÓN!D57,'BD M.O'!C:I,5,FALSE),"") | BF60: 3HOJAS | DI60: =IFERROR(IF(DG60>0,(((N57)/(1+10%+19%*5%)+((N57)/(1+10%+19%*5%))*10%)*DH60),0),0) -> 0 | DJ60: =IFERROR(IF(DG60>0,(N57*DH60),0),0) -> 0 | DK60: =IF(DG60>0,((R57+T57)*DH60),0) -> 0 | DL60: =IF(DG60>0,(Q57*DH60),0) -> 0 | DM60: =IF(DG60>0,(S57*DH60),0) -> 0 | DN60: =IF(DG60>0,(BN57*DH60),0) -> 0 | DO60: =IF(DG60>0,(AF57*DH60),0) -> 0 | DP60: =IF(DG60>0,((DI60)*('BD P&G'!$E$16+'BD P&G'!$E$17+'BD P&G'!$E$18+'BD P&G'!$E$19+'BD P&G'!$E$20+'BD P&G'!$E$21+'BD P&G'!$E$22+'BD P&G'!$E$23)*DH60),0) -> 0 | DQ60: =IFERROR(IF(DG60>0,((DI60*'BD P&G'!$E$7)+(DI60*'BD P&G'!$E$9)+AI57),0),0) -> 0 | DR60: =IFERROR(IF(DG60>0,((DI60*1%)),0),0) -> 0 | DS60: =IFERROR(IF(DG60>0,(((DI60*'BD P&G'!$E$32+DI60*'BD P&G'!$E$33+DI60*'BD P&G'!$E$35+DI60*'BD P&G'!$E$36+DI60*'BD P&G'!$E$37))),0),0) -> 0 | DT60: =IF(DG60>0,(Y57*DH60),0) -> 0 | DU60: =IF(DG60>0,(Z57*DH60),0) -> 0 | DV60: =IF(DG60>0,(Y61*DH60),0) -> 0 | DW60: =IF(DG60>0,(Z61*DH60),0) -> 0 | DX60: =IF(DV60>0,DJ60,0) -> 0 | DY60: =IF(DW60>0,DJ60,0) -> 0
C61: CERRADURA | D61: =IFERROR(VLOOKUP(D57,'BD GN'!C:E,3,),"") | R61: SISTEMA M2 | S61: =IFERROR(IF(N57="","",N57/W61),"") | W61: =+IF(J57*K57>=1,J57*K57,IF(AND(J57*K57>0,J57*K57<1),1,"")) | X61: AREA | Y61: =IFERROR(IF(D57='BD GN'!$C$25,COTIZACIÓN!W61,IF(D57='BD GN'!$C$26,COTIZACIÓN!W61,IF(D57='BD GN'!$C$27,COTIZACIÓN!W61,IF(COTIZACIÓN!D57='BD GN'!$C$28,COTIZACIÓN!W61,IF(COTIZACIÓN!D57='BD GN'!$C$29,COTIZACIÓN!W61,IF(COTIZACIÓN!D57='BD GN'!$C$35,COTIZACIÓN!W61,IF(COTIZACIÓN!D57='BD GN'!$C$36,COTIZACIÓN!W61,IF(COTIZACIÓN!D57='BD GN'!$C$37,COTIZACIÓN!W61,IF(COTIZACIÓN!D57='BD GN'!$C$38,COTIZACIÓN!W61,IF(COTIZACIÓN!D57='BD GN'!$C$39,COTIZACIÓN!W61,IF(COTIZACIÓN!D57='BD GN'!$C$40,COTIZACIÓN!W61,IF(COTIZACIÓN!D57='BD GN'!$C$41,COTIZACIÓN!W61,IF(COTIZACIÓN!D57='BD GN'!$C$42,COTIZACIÓN!W61,IF(COTIZACIÓN!D57='BD GN'!$C$49,COTIZACIÓN!W61,IF(COTIZACIÓN!D57='BD GN'!$C$50,COTIZACIÓN!W61,IF(COTIZACIÓN!D57='BD GN'!$C$51,COTIZACIÓN!W61,IF(COTIZACIÓN!D57='BD GN'!$C$67,COTIZACIÓN!W61,0))))))))))))))))),0) -> 0 | Z61: =IFERROR(W61-Y61,0) -> 0 | BC61: V12 | BE61: =IFERROR(VLOOKUP(D57,'BD M.O'!C:I,6,FALSE),"") | BF61: 4HOJAS
C62: OBSERVACIONES | D62: N.A | R62: VR REF SIS M2 | S62: =IFERROR(IF($C$12='BD GN'!$CC$1,VLOOKUP(COTIZACIÓN!D57,'BD GN'!CB:CG,2,FALSE),IF(COTIZACIÓN!$C$12='BD GN'!$CD$1,VLOOKUP(COTIZACIÓN!D57,'BD GN'!CB:CG,3,FALSE),IF($C$12='BD GN'!$CE$1,VLOOKUP(COTIZACIÓN!D57,'BD GN'!CB:CG,4,FALSE),IF(COTIZACIÓN!$C$12='BD GN'!$CF$1,VLOOKUP(COTIZACIÓN!D57,'BD GN'!CB:CG,5,FALSE),IF(COTIZACIÓN!$C$12='BD GN'!$CG$1,VLOOKUP(COTIZACIÓN!D57,'BD GN'!CB:CG,6,FALSE),""))))),"-") | W62: TOTAL M.O | X62: =IFERROR(SUM(W57:X57),"") -> 0 | Y62: TOTAL M.O PYG | Z62: =IFERROR(Y57+Z57,"") | BC62: V13 | BE62: =IFERROR(VLOOKUP(D57,'BD M.O'!C:I,7,FALSE),"") | BF62: HOJA ADIC
A63: ÍTEM | B63: UBICACIÓN | C63: CONFIGURACIÓN | D63: DESCRIPCIÓN | J63: AN (MT) | K63: AL (MT) | L63: M2 | M63: CNT | N63: VR UNT | O63: VR TOTAL | Q63: ACCE | R63: ALUMINIO | S63: CRISTAL | T63: % DESP ALU | U63: EMPQ | V63: TRANS | W63: ENSAMBLE | X63: INSTA | Y63: ENSAM PYG | Z63: INST PYG | AA63: TOTAL M.O PYG | AB63: IMPREV | AC63: IMPREV PYG | AD63: BACKOFFICE | AE63: PYG | AF63: VIATICOS | AG63: BENEFICIO | AH63: BENEFICIO PYG | AI63: COMISIÓN | AJ63: IMPUESTOS | AK63: VENTA SIN PYG | AL63: VENTA FINAL | AM63: ACCE | AN63: ALUMINIO | AO63: CRISTAL | AP63: % DESP ALU | AQ63: MAQ | AR63: EMPQ | AS63: TRANS | AT63: ENSAMBLE | AU63: INSTA | AV63: IMPREV | AW63: BACKOFFICE | AX63: UTILIDAD | AY63: COMISIÓN | AZ63: VENTA | BC63: V14 | BE63: Nº MÓDULOS | BF63: =$BF$13 -> VR SILICONA | BG63: =$BG$13 -> VR PELÍCULA | BH63: =$BH$13 -> VR EMBALAJE | BJ63: =$BJ$13 -> ESP. CRISTAL | BK63: ESTRUCTURA | BL63: CRISTAL | BM63: =BM56 -> TOTAL | BN63: VR TRANSP | CK63: OR | CL63: MD | CM63: AD | CN63: EL | CO63: MD | CP63: PL | CQ63: PRO | CR63: DESP | CS63: MT | CT63: ENT | CU63: CNT | CV63: VR TOTAL | CW63: CNT | CX63: VR TOTAL | CY63: CNT | CZ63: VR TOTAL | DA63: CNT | DB63: VR TOTAL | DC63: CNT | DD63: VR TOTAL | DG63: RAD | DH63: CANTIDAD | DI63: SUBTOTAL | DJ63: TOTAL | DK63: ALU | DL63: ACC | DM63: VIDRIO | DN63: TRANSPORTE | DO63: VIATICOS | DP63: BACKOFFICE | DQ63: GAST VENTA | DR63: GAST FINANC | DS63: COSTOS IND | DT63: ENSAMBLE | DU63: INSTALACION | DV63: M2 INOX | DW63: M2 ALU | DX63: VR INOX | DY63: VR ALU
C64: SISTEMA | L64: =J64*K64*M64 -> 0 | N64: =IFERROR(AL64,"") -> 1.0765547 | O64: =IFERROR(N64*M64,"") -> 0 | Q64: =Q65+BF64+($R$350*Q65) -> 0 | R64: =IFERROR(R65+($R$348*R65),"") -> 0 | S64: =+IF(R66="SI",((W68*'BD GN'!$AB$2)+S65)*1,COTIZACIÓN!S65*1)+(P65*S65) -> 0 | T64: =IFERROR(R64*IF(K64<=3,$T$13,15%),"") -> 0 | U64: =BH64+BG64 -> 0 | V64: =IFERROR(BN64,0) | W64: =IFERROR(IF(X66="SI",W67*J64*K64,IF(BE64=3,BE66,IF(BE64=4,BE67,IF(BE64=5,BE68,IF(BE64>5,BE68+(BE69*(BE64-5)),"")))))*0,"") | X64: =IFERROR(IF(X65="NO",(VLOOKUP(D64,'BD M.O'!C:E,3,FALSE))*W68,((VLOOKUP(D64,'BD M.O'!C:E,3,FALSE))+7500)*W68),"") | Y64: =IFERROR($Y$13*AK64,"") -> 0.042084457 | Z64: =IFERROR(($Z$13*AK64)+X64,"") | AA64: =IFERROR(Y64+Z64,"") | AB64: =IFERROR((SUM(Q64:X64)-T64+T66)*$AB$13,"") -> 0 | AC64: =IFERROR(((SUM(Q64:V64,IF(X69>AA64,AVERAGE(X69,AA64),AA64))-T64+T66))*$AB$13,"") -> 0 | AD64: =IFERROR((J64*K64*$BV$14),"") | AE64: =IFERROR($AE$13*AK64,"") -> 0.064010593 | AF64: =IFERROR(($CI$11+$CI$13)*W68,"") | AG64: =IFERROR((SUM(Q64:X64,AB64,AD64,AF64)-T64+T66)*$AG$13,"") -> 0 | AH64: =IFERROR((SUM(Q64:V64,(IF(X69>AA64,AVERAGE(X69,AA64),AA64)),AC64,AE64,AF64)-T64+T66)*$AG$13,"") -> 0.032005296 | AI64: =IFERROR(AL64*$AI$13,"") -> 0.021531093 | AJ64: =IFERROR($AJ$13*AL64,"") -> 0.006007175 | AK64: =IFERROR(SUM(Q64:X64,AB64,AD64,AG64,AF64)/(1-$AI$13)+(1-$AJ$13)-T64+T66,"") -> 0.99442 | AL64: =IFERROR(SUM(Q64:V64,AC64,(IF(AD64>AE64,AVERAGE(AD64,AE64),AE64)),AF64,,AH64,(IF(SUM(X69)>AA64,AVERAGE(AA64,X69),AA64)))/(1-$AJ$13)+(1-$AI$13)-T64+T66,"") -> 1.0765547 | AM64: =$M$15*Q64 -> 0 | AN64: =$M$15*R64 -> 0 | AO64: =$M$15*S64 -> 0 | AP64: =$M$15*T64 -> 0 | AQ64: =$M$15*#REF! -> #REF! | AR64: =$M$15*U64 -> 0 | AS64: =$M$15*V64 -> #VALUE! | AT64: =$M$15*W64 -> #VALUE! | AU64: =$M$15*X64 -> #VALUE! | AV64: =$M$15*AB64 -> 0 | AW64: =$M$15*AE64 -> 0 | AX64: =$M$15*AG64 -> 0 | AY64: =$M$15*AI64 -> 0 | AZ64: =$M$15*AK64 -> 0 | BB64: CORTE 8 | BC64: V8 | BF64: =IF(BH65="NO",((2*J64)+(2*K64))*'BD GN'!$AU$3,((3*J64)+(2*K64))*'BD GN'!$AU$3) -> 0 | BG64: ='BD GN'!$BB$3*J64*K64 -> 0 | BH64: =((J64*2*BE64)+(K64*2*BE64))*'BD GN'!$AN$4 -> 0 | BL64: =J64*K64*2.5*BJ64 -> 0 | BM64: =BK64+BL64 -> 0 | BN64: =IFERROR((VLOOKUP($C$12,'BD GN'!BD:BM,10,FALSE)*BM64)+$BR$338,"") | CV64: =IFERROR(N64*CU64,"") -> 0 | CX64: =IFERROR(P64*CW64,"") -> 0 | CZ64: =IFERROR(R64*CY64,"") -> 0 | DA64: =CU64+CW64+CY64 -> 0 | DB64: =IFERROR(CV64+CX64+CZ64,"") -> 0 | DC64: =M64-(CU64+CW64+CY64) -> 0 | DD64: =IFERROR(O64-(CV64+CX64+CZ64),"") -> 0 | DI64: =IFERROR(IF(DG64>0,(((N64)/(1+10%+19%*5%)+((N64)/(1+10%+19%*5%))*10%)*DH64),0),0) -> 0 | DJ64: =IFERROR(IF(DG64>0,(N64*DH64),0),0) -> 0 | DK64: =IF(DG64>0,((R64+T64)*DH64),0) -> 0 | DL64: =IF(DG64>0,(Q64*DH64),0) -> 0 | DM64: =IF(DG64>0,(S64*DH64),0) -> 0 | DN64: =IF(DG64>0,(BN64*DH64),0) -> 0 | DO64: =IF(DG64>0,(AF64*DH64),0) -> 0 | DP64: =IF(DG64>0,((DI64)*('BD P&G'!$E$16+'BD P&G'!$E$17+'BD P&G'!$E$18+'BD P&G'!$E$19+'BD P&G'!$E$20+'BD P&G'!$E$21+'BD P&G'!$E$22+'BD P&G'!$E$23)*DH64),0) -> 0 | DQ64: =IFERROR(IF(DG64>0,((DI64*'BD P&G'!$E$7)+(DI64*'BD P&G'!$E$9)+AI64),0),0) -> 0 | DR64: =IFERROR(IF(DG64>0,((DI64*1%)),0),0) -> 0 | DS64: =IFERROR(IF(DG64>0,(((DI64*'BD P&G'!$E$32+DI64*'BD P&G'!$E$33+DI64*'BD P&G'!$E$35+DI64*'BD P&G'!$E$36+DI64*'BD P&G'!$E$37))),0),0) -> 0 | DT64: =IF(DG64>0,(Y64*DH64),0) -> 0 | DU64: =IF(DG64>0,(Z64*DH64),0) -> 0 | DV64: =IF(DG64>0,(Y68*DH64),0) -> 0 | DW64: =IF(DG64>0,(Z68*DH64),0) -> 0 | DX64: =IF(DV64>0,DJ64,0) -> 0 | DY64: =IF(DW64>0,DJ64,0) -> 0
C65: CRISTAL | T65: =IFERROR(T64/$R$353,"") -> 0 | W65: ANGEO | X65: NO | BB65: CORTE 9 | BC65: V9 | BE65: ALFAJÍA | BF65: NO | BG65: LUCETA | BH65: NO
C66: ACABADO ALUMINIO | Q66: SANDBLASTING | R66: NO | T66: =IFERROR(($R$353-8000)*T65,"") -> 0 | W66: FACHADA | X66: NO | BB66: CORTE 10 | BC66: V10 | BE66: =IFERROR(VLOOKUP(D64,'BD M.O'!C:H,4,FALSE),"") | BF66: 2HOJAS
C67: PELÍCULA PROTECCIÓN | D67: PERFILES | F67: X | G67: CRISTAL | I67: =+IF($BG$9="SI","","X") -> X | R67: VIDRIO M2 | S67: =IF(S65="","",S65/(J64*K64)) | W67: =IFERROR(IF(X66="SI",VLOOKUP(D64,'BD M.O'!C:F,4,FALSE),""),"") | X67: FACHADA | Y67: M2 INOX | Z67: M2 ALU | BC67: V11 | BE67: =IFERROR(VLOOKUP(COTIZACIÓN!D64,'BD M.O'!C:I,5,FALSE),"") | BF67: 3HOJAS | DI67: =IFERROR(IF(DG67>0,(((N64)/(1+10%+19%*5%)+((N64)/(1+10%+19%*5%))*10%)*DH67),0),0) -> 0 | DJ67: =IFERROR(IF(DG67>0,(N64*DH67),0),0) -> 0 | DK67: =IF(DG67>0,((R64+T64)*DH67),0) -> 0 | DL67: =IF(DG67>0,(Q64*DH67),0) -> 0 | DM67: =IF(DG67>0,(S64*DH67),0) -> 0 | DN67: =IF(DG67>0,(BN64*DH67),0) -> 0 | DO67: =IF(DG67>0,(AF64*DH67),0) -> 0 | DP67: =IF(DG67>0,((DI67)*('BD P&G'!$E$16+'BD P&G'!$E$17+'BD P&G'!$E$18+'BD P&G'!$E$19+'BD P&G'!$E$20+'BD P&G'!$E$21+'BD P&G'!$E$22+'BD P&G'!$E$23)*DH67),0) -> 0 | DQ67: =IFERROR(IF(DG67>0,((DI67*'BD P&G'!$E$7)+(DI67*'BD P&G'!$E$9)+AI64),0),0) -> 0 | DR67: =IFERROR(IF(DG67>0,((DI67*1%)),0),0) -> 0 | DS67: =IFERROR(IF(DG67>0,(((DI67*'BD P&G'!$E$32+DI67*'BD P&G'!$E$33+DI67*'BD P&G'!$E$35+DI67*'BD P&G'!$E$36+DI67*'BD P&G'!$E$37))),0),0) -> 0 | DT67: =IF(DG67>0,(Y64*DH67),0) -> 0 | DU67: =IF(DG67>0,(Z64*DH67),0) -> 0 | DV67: =IF(DG67>0,(Y68*DH67),0) -> 0 | DW67: =IF(DG67>0,(Z68*DH67),0) -> 0 | DX67: =IF(DV67>0,DJ67,0) -> 0 | DY67: =IF(DW67>0,DJ67,0) -> 0
C68: CERRADURA | D68: =IFERROR(VLOOKUP(D64,'BD GN'!C:E,3,),"") | R68: SISTEMA M2 | S68: =IFERROR(IF(N64="","",N64/W68),"") | W68: =+IF(J64*K64>=1,J64*K64,IF(AND(J64*K64>0,J64*K64<1),1,"")) | X68: AREA | Y68: =IFERROR(IF(D64='BD GN'!$C$25,COTIZACIÓN!W68,IF(D64='BD GN'!$C$26,COTIZACIÓN!W68,IF(D64='BD GN'!$C$27,COTIZACIÓN!W68,IF(COTIZACIÓN!D64='BD GN'!$C$28,COTIZACIÓN!W68,IF(COTIZACIÓN!D64='BD GN'!$C$29,COTIZACIÓN!W68,IF(COTIZACIÓN!D64='BD GN'!$C$35,COTIZACIÓN!W68,IF(COTIZACIÓN!D64='BD GN'!$C$36,COTIZACIÓN!W68,IF(COTIZACIÓN!D64='BD GN'!$C$37,COTIZACIÓN!W68,IF(COTIZACIÓN!D64='BD GN'!$C$38,COTIZACIÓN!W68,IF(COTIZACIÓN!D64='BD GN'!$C$39,COTIZACIÓN!W68,IF(COTIZACIÓN!D64='BD GN'!$C$40,COTIZACIÓN!W68,IF(COTIZACIÓN!D64='BD GN'!$C$41,COTIZACIÓN!W68,IF(COTIZACIÓN!D64='BD GN'!$C$42,COTIZACIÓN!W68,IF(COTIZACIÓN!D64='BD GN'!$C$49,COTIZACIÓN!W68,IF(COTIZACIÓN!D64='BD GN'!$C$50,COTIZACIÓN!W68,IF(COTIZACIÓN!D64='BD GN'!$C$51,COTIZACIÓN!W68,IF(COTIZACIÓN!D64='BD GN'!$C$67,COTIZACIÓN!W68,0))))))))))))))))),0) -> 0 | Z68: =IFERROR(W68-Y68,0) -> 0 | BC68: V12 | BE68: =IFERROR(VLOOKUP(D64,'BD M.O'!C:I,6,FALSE),"") | BF68: 4HOJAS
C69: OBSERVACIONES | D69: N.A | R69: VR REF SIS M2 | S69: =IFERROR(IF($C$12='BD GN'!$CC$1,VLOOKUP(COTIZACIÓN!D64,'BD GN'!CB:CG,2,FALSE),IF(COTIZACIÓN!$C$12='BD GN'!$CD$1,VLOOKUP(COTIZACIÓN!D64,'BD GN'!CB:CG,3,FALSE),IF($C$12='BD GN'!$CE$1,VLOOKUP(COTIZACIÓN!D64,'BD GN'!CB:CG,4,FALSE),IF(COTIZACIÓN!$C$12='BD GN'!$CF$1,VLOOKUP(COTIZACIÓN!D64,'BD GN'!CB:CG,5,FALSE),IF(COTIZACIÓN!$C$12='BD GN'!$CG$1,VLOOKUP(COTIZACIÓN!D64,'BD GN'!CB:CG,6,FALSE),""))))),"-") | W69: TOTAL M.O | X69: =IFERROR(SUM(W64:X64),"") -> 0 | Y69: TOTAL M.O PYG | Z69: =IFERROR(Y64+Z64,"") | BC69: V13 | BE69: =IFERROR(VLOOKUP(D64,'BD M.O'!C:I,7,FALSE),"") | BF69: HOJA ADIC
A70: ÍTEM | B70: UBICACIÓN | C70: CONFIGURACIÓN | D70: DESCRIPCIÓN | J70: AN (MT) | K70: AL (MT) | L70: M2 | M70: CNT | N70: VR UNT | O70: VR TOTAL | Q70: ACCE | R70: ALUMINIO | S70: CRISTAL | T70: % DESP ALU | U70: EMPQ | V70: TRANS | W70: ENSAMBLE | X70: INSTA | Y70: ENSAM PYG | Z70: INST PYG | AA70: TOTAL M.O PYG | AB70: IMPREV | AC70: IMPREV PYG | AD70: BACKOFFICE | AE70: PYG | AF70: VIATICOS | AG70: BENEFICIO | AH70: BENEFICIO PYG | AI70: COMISIÓN | AJ70: IMPUESTOS | AK70: VENTA SIN PYG | AL70: VENTA FINAL | AM70: ACCE | AN70: ALUMINIO | AO70: CRISTAL | AP70: % DESP ALU | AQ70: MAQ | AR70: EMPQ | AS70: TRANS | AT70: ENSAMBLE | AU70: INSTA | AV70: IMPREV | AW70: BACKOFFICE | AX70: UTILIDAD | AY70: COMISIÓN | AZ70: VENTA | BC70: V14 | BE70: Nº MÓDULOS | BF70: =$BF$13 -> VR SILICONA | BG70: =$BG$13 -> VR PELÍCULA | BH70: =$BH$13 -> VR EMBALAJE | BJ70: =$BJ$13 -> ESP. CRISTAL | BK70: ESTRUCTURA | BL70: CRISTAL | BM70: =BM63 -> TOTAL | BN70: VR TRANSP | CK70: OR | CL70: MD | CM70: AD | CN70: EL | CO70: MD | CP70: PL | CQ70: PRO | CR70: DESP | CS70: MT | CT70: ENT | CU70: CNT | CV70: VR TOTAL | CW70: CNT | CX70: VR TOTAL | CY70: CNT | CZ70: VR TOTAL | DA70: CNT | DB70: VR TOTAL | DC70: CNT | DD70: VR TOTAL | DG70: RAD | DH70: CANTIDAD | DI70: SUBTOTAL | DJ70: TOTAL | DK70: ALU | DL70: ACC | DM70: VIDRIO | DN70: TRANSPORTE | DO70: VIATICOS | DP70: BACKOFFICE | DQ70: GAST VENTA | DR70: GAST FINANC | DS70: COSTOS IND | DT70: ENSAMBLE | DU70: INSTALACION | DV70: M2 INOX | DW70: M2 ALU | DX70: VR INOX | DY70: VR ALU
C71: SISTEMA | L71: =J71*K71*M71 -> 0 | N71: =IFERROR(AL71,"") -> 1.0765547 | O71: =IFERROR(N71*M71,"") -> 0 | Q71: =Q72+BF71+($R$350*Q72) -> 0 | R71: =IFERROR(R72+($R$348*R72),"") -> 0 | S71: =+IF(R73="SI",((W75*'BD GN'!$AB$2)+S72)*1,COTIZACIÓN!S72*1)+(P72*S72) -> 0 | T71: =IFERROR(R71*IF(K71<=3,$T$13,15%),"") -> 0 | U71: =BH71+BG71 -> 0 | V71: =IFERROR(BN71,0) | W71: =IFERROR(IF(X73="SI",W74*J71*K71,IF(BE71=3,BE73,IF(BE71=4,BE74,IF(BE71=5,BE75,IF(BE71>5,BE75+(BE76*(BE71-5)),"")))))*0,"") | X71: =IFERROR(IF(X72="NO",(VLOOKUP(D71,'BD M.O'!C:E,3,FALSE))*W75,((VLOOKUP(D71,'BD M.O'!C:E,3,FALSE))+7500)*W75),"") | Y71: =IFERROR($Y$13*AK71,"") -> 0.042084457 | Z71: =IFERROR(($Z$13*AK71)+X71,"") | AA71: =IFERROR(Y71+Z71,"") | AB71: =IFERROR((SUM(Q71:X71)-T71+T73)*$AB$13,"") -> 0 | AC71: =IFERROR(((SUM(Q71:V71,IF(X76>AA71,AVERAGE(X76,AA71),AA71))-T71+T73))*$AB$13,"") -> 0 | AD71: =IFERROR((J71*K71*$BV$14),"") | AE71: =IFERROR($AE$13*AK71,"") -> 0.064010593 | AF71: =IFERROR(($CI$11+$CI$13)*W75,"") | AG71: =IFERROR((SUM(Q71:X71,AB71,AD71,AF71)-T71+T73)*$AG$13,"") -> 0 | AH71: =IFERROR((SUM(Q71:V71,(IF(X76>AA71,AVERAGE(X76,AA71),AA71)),AC71,AE71,AF71)-T71+T73)*$AG$13,"") -> 0.032005296 | AI71: =IFERROR(AL71*$AI$13,"") -> 0.021531093 | AJ71: =IFERROR($AJ$13*AL71,"") -> 0.006007175 | AK71: =IFERROR(SUM(Q71:X71,AB71,AD71,AG71,AF71)/(1-$AI$13)+(1-$AJ$13)-T71+T73,"") -> 0.99442 | AL71: =IFERROR(SUM(Q71:V71,AC71,(IF(AD71>AE71,AVERAGE(AD71,AE71),AE71)),AF71,,AH71,(IF(SUM(X76)>AA71,AVERAGE(AA71,X76),AA71)))/(1-$AJ$13)+(1-$AI$13)-T71+T73,"") -> 1.0765547 | AM71: =$M$15*Q71 -> 0 | AN71: =$M$15*R71 -> 0 | AO71: =$M$15*S71 -> 0 | AP71: =$M$15*T71 -> 0 | AQ71: =$M$15*#REF! -> #REF! | AR71: =$M$15*U71 -> 0 | AS71: =$M$15*V71 -> #VALUE! | AT71: =$M$15*W71 -> #VALUE! | AU71: =$M$15*X71 -> #VALUE! | AV71: =$M$15*AB71 -> 0 | AW71: =$M$15*AE71 -> 0 | AX71: =$M$15*AG71 -> 0 | AY71: =$M$15*AI71 -> 0 | AZ71: =$M$15*AK71 -> 0 | BB71: CORTE 8 | BC71: V8 | BF71: =IF(BH72="NO",((2*J71)+(2*K71))*'BD GN'!$AU$3,((3*J71)+(2*K71))*'BD GN'!$AU$3) -> 0 | BG71: ='BD GN'!$BB$3*J71*K71 -> 0 | BH71: =((J71*2*BE71)+(K71*2*BE71))*'BD GN'!$AN$4 -> 0 | BL71: =J71*K71*2.5*BJ71 -> 0 | BM71: =BK71+BL71 -> 0 | BN71: =IFERROR((VLOOKUP($C$12,'BD GN'!BD:BM,10,FALSE)*BM71)+$BR$338,"") | CV71: =IFERROR(N71*CU71,"") -> 0 | CX71: =IFERROR(P71*CW71,"") -> 0 | CZ71: =IFERROR(R71*CY71,"") -> 0 | DA71: =CU71+CW71+CY71 -> 0 | DB71: =IFERROR(CV71+CX71+CZ71,"") -> 0 | DC71: =M71-(CU71+CW71+CY71) -> 0 | DD71: =IFERROR(O71-(CV71+CX71+CZ71),"") -> 0 | DI71: =IFERROR(IF(DG71>0,(((N71)/(1+10%+19%*5%)+((N71)/(1+10%+19%*5%))*10%)*DH71),0),0) -> 0 | DJ71: =IFERROR(IF(DG71>0,(N71*DH71),0),0) -> 0 | DK71: =IF(DG71>0,((R71+T71)*DH71),0) -> 0 | DL71: =IF(DG71>0,(Q71*DH71),0) -> 0 | DM71: =IF(DG71>0,(S71*DH71),0) -> 0 | DN71: =IF(DG71>0,(BN71*DH71),0) -> 0 | DO71: =IF(DG71>0,(AF71*DH71),0) -> 0 | DP71: =IF(DG71>0,((DI71)*('BD P&G'!$E$16+'BD P&G'!$E$17+'BD P&G'!$E$18+'BD P&G'!$E$19+'BD P&G'!$E$20+'BD P&G'!$E$21+'BD P&G'!$E$22+'BD P&G'!$E$23)*DH71),0) -> 0 | DQ71: =IFERROR(IF(DG71>0,((DI71*'BD P&G'!$E$7)+(DI71*'BD P&G'!$E$9)+AI71),0),0) -> 0 | DR71: =IFERROR(IF(DG71>0,((DI71*1%)),0),0) -> 0 | DS71: =IFERROR(IF(DG71>0,(((DI71*'BD P&G'!$E$32+DI71*'BD P&G'!$E$33+DI71*'BD P&G'!$E$35+DI71*'BD P&G'!$E$36+DI71*'BD P&G'!$E$37))),0),0) -> 0 | DT71: =IF(DG71>0,(Y71*DH71),0) -> 0 | DU71: =IF(DG71>0,(Z71*DH71),0) -> 0 | DV71: =IF(DG71>0,(Y75*DH71),0) -> 0 | DW71: =IF(DG71>0,(Z75*DH71),0) -> 0 | DX71: =IF(DV71>0,DJ71,0) -> 0 | DY71: =IF(DW71>0,DJ71,0) -> 0
C72: CRISTAL | T72: =IFERROR(T71/$R$353,"") -> 0 | W72: ANGEO | X72: NO | BB72: CORTE 9 | BC72: V9 | BE72: ALFAJÍA | BF72: NO | BG72: LUCETA | BH72: NO
C73: ACABADO ALUMINIO | Q73: SANDBLASTING | R73: NO | T73: =IFERROR(($R$353-8000)*T72,"") -> 0 | W73: FACHADA | X73: NO | BB73: CORTE 10 | BC73: V10 | BE73: =IFERROR(VLOOKUP(D71,'BD M.O'!C:H,4,FALSE),"") | BF73: 2HOJAS
C74: PELÍCULA PROTECCIÓN | D74: PERFILES | F74: X | G74: CRISTAL | I74: =+IF($BG$9="SI","","X") -> X | R74: VIDRIO M2 | S74: =IF(S72="","",S72/(J71*K71)) | W74: =IFERROR(IF(X73="SI",VLOOKUP(D71,'BD M.O'!C:F,4,FALSE),""),"") | X74: FACHADA | Y74: M2 INOX | Z74: M2 ALU | BC74: V11 | BE74: =IFERROR(VLOOKUP(COTIZACIÓN!D71,'BD M.O'!C:I,5,FALSE),"") | BF74: 3HOJAS | DI74: =IFERROR(IF(DG74>0,(((N71)/(1+10%+19%*5%)+((N71)/(1+10%+19%*5%))*10%)*DH74),0),0) -> 0 | DJ74: =IFERROR(IF(DG74>0,(N71*DH74),0),0) -> 0 | DK74: =IF(DG74>0,((R71+T71)*DH74),0) -> 0 | DL74: =IF(DG74>0,(Q71*DH74),0) -> 0 | DM74: =IF(DG74>0,(S71*DH74),0) -> 0 | DN74: =IF(DG74>0,(BN71*DH74),0) -> 0 | DO74: =IF(DG74>0,(AF71*DH74),0) -> 0 | DP74: =IF(DG74>0,((DI74)*('BD P&G'!$E$16+'BD P&G'!$E$17+'BD P&G'!$E$18+'BD P&G'!$E$19+'BD P&G'!$E$20+'BD P&G'!$E$21+'BD P&G'!$E$22+'BD P&G'!$E$23)*DH74),0) -> 0 | DQ74: =IFERROR(IF(DG74>0,((DI74*'BD P&G'!$E$7)+(DI74*'BD P&G'!$E$9)+AI71),0),0) -> 0 | DR74: =IFERROR(IF(DG74>0,((DI74*1%)),0),0) -> 0 | DS74: =IFERROR(IF(DG74>0,(((DI74*'BD P&G'!$E$32+DI74*'BD P&G'!$E$33+DI74*'BD P&G'!$E$35+DI74*'BD P&G'!$E$36+DI74*'BD P&G'!$E$37))),0),0) -> 0 | DT74: =IF(DG74>0,(Y71*DH74),0) -> 0 | DU74: =IF(DG74>0,(Z71*DH74),0) -> 0 | DV74: =IF(DG74>0,(Y75*DH74),0) -> 0 | DW74: =IF(DG74>0,(Z75*DH74),0) -> 0 | DX74: =IF(DV74>0,DJ74,0) -> 0 | DY74: =IF(DW74>0,DJ74,0) -> 0
C75: CERRADURA | D75: =IFERROR(VLOOKUP(D71,'BD GN'!C:E,3,),"") | R75: SISTEMA M2 | S75: =IFERROR(IF(N71="","",N71/W75),"") | W75: =+IF(J71*K71>=1,J71*K71,IF(AND(J71*K71>0,J71*K71<1),1,"")) | X75: AREA | Y75: =IFERROR(IF(D71='BD GN'!$C$25,COTIZACIÓN!W75,IF(D71='BD GN'!$C$26,COTIZACIÓN!W75,IF(D71='BD GN'!$C$27,COTIZACIÓN!W75,IF(COTIZACIÓN!D71='BD GN'!$C$28,COTIZACIÓN!W75,IF(COTIZACIÓN!D71='BD GN'!$C$29,COTIZACIÓN!W75,IF(COTIZACIÓN!D71='BD GN'!$C$35,COTIZACIÓN!W75,IF(COTIZACIÓN!D71='BD GN'!$C$36,COTIZACIÓN!W75,IF(COTIZACIÓN!D71='BD GN'!$C$37,COTIZACIÓN!W75,IF(COTIZACIÓN!D71='BD GN'!$C$38,COTIZACIÓN!W75,IF(COTIZACIÓN!D71='BD GN'!$C$39,COTIZACIÓN!W75,IF(COTIZACIÓN!D71='BD GN'!$C$40,COTIZACIÓN!W75,IF(COTIZACIÓN!D71='BD GN'!$C$41,COTIZACIÓN!W75,IF(COTIZACIÓN!D71='BD GN'!$C$42,COTIZACIÓN!W75,IF(COTIZACIÓN!D71='BD GN'!$C$49,COTIZACIÓN!W75,IF(COTIZACIÓN!D71='BD GN'!$C$50,COTIZACIÓN!W75,IF(COTIZACIÓN!D71='BD GN'!$C$51,COTIZACIÓN!W75,IF(COTIZACIÓN!D71='BD GN'!$C$67,COTIZACIÓN!W75,0))))))))))))))))),0) -> 0 | Z75: =IFERROR(W75-Y75,0) -> 0 | BC75: V12 | BE75: =IFERROR(VLOOKUP(D71,'BD M.O'!C:I,6,FALSE),"") | BF75: 4HOJAS
C76: OBSERVACIONES | D76: N.A | R76: VR REF SIS M2 | S76: =IFERROR(IF($C$12='BD GN'!$CC$1,VLOOKUP(COTIZACIÓN!D71,'BD GN'!CB:CG,2,FALSE),IF(COTIZACIÓN!$C$12='BD GN'!$CD$1,VLOOKUP(COTIZACIÓN!D71,'BD GN'!CB:CG,3,FALSE),IF($C$12='BD GN'!$CE$1,VLOOKUP(COTIZACIÓN!D71,'BD GN'!CB:CG,4,FALSE),IF(COTIZACIÓN!$C$12='BD GN'!$CF$1,VLOOKUP(COTIZACIÓN!D71,'BD GN'!CB:CG,5,FALSE),IF(COTIZACIÓN!$C$12='BD GN'!$CG$1,VLOOKUP(COTIZACIÓN!D71,'BD GN'!CB:CG,6,FALSE),""))))),"-") | W76: TOTAL M.O | X76: =IFERROR(SUM(W71:X71),"") -> 0 | Y76: TOTAL M.O PYG | Z76: =IFERROR(Y71+Z71,"") | BC76: V13 | BE76: =IFERROR(VLOOKUP(D71,'BD M.O'!C:I,7,FALSE),"") | BF76: HOJA ADIC
A77: ÍTEM | B77: UBICACIÓN | C77: CONFIGURACIÓN | D77: DESCRIPCIÓN | J77: AN (MT) | K77: AL (MT) | L77: M2 | M77: CNT | N77: VR UNT | O77: VR TOTAL | Q77: ACCE | R77: ALUMINIO | S77: CRISTAL | T77: % DESP ALU | U77: EMPQ | V77: TRANS | W77: ENSAMBLE | X77: INSTA | Y77: ENSAM PYG | Z77: INST PYG | AA77: TOTAL M.O PYG | AB77: IMPREV | AC77: IMPREV PYG | AD77: BACKOFFICE | AE77: PYG | AF77: VIATICOS | AG77: BENEFICIO | AH77: BENEFICIO PYG | AI77: COMISIÓN | AJ77: IMPUESTOS | AK77: VENTA SIN PYG | AL77: VENTA FINAL | AM77: ACCE | AN77: ALUMINIO | AO77: CRISTAL | AP77: % DESP ALU | AQ77: MAQ | AR77: EMPQ | AS77: TRANS | AT77: ENSAMBLE | AU77: INSTA | AV77: IMPREV | AW77: BACKOFFICE | AX77: UTILIDAD | AY77: COMISIÓN | AZ77: VENTA | BC77: V14 | BE77: Nº MÓDULOS | BF77: =$BF$13 -> VR SILICONA | BG77: =$BG$13 -> VR PELÍCULA | BH77: =$BH$13 -> VR EMBALAJE | BJ77: =$BJ$13 -> ESP. CRISTAL | BK77: ESTRUCTURA | BL77: CRISTAL | BM77: =BM70 -> TOTAL | BN77: VR TRANSP | CK77: OR | CL77: MD | CM77: AD | CN77: EL | CO77: MD | CP77: PL | CQ77: PRO | CR77: DESP | CS77: MT | CT77: ENT | CU77: CNT | CV77: VR TOTAL | CW77: CNT | CX77: VR TOTAL | CY77: CNT | CZ77: VR TOTAL | DA77: CNT | DB77: VR TOTAL | DC77: CNT | DD77: VR TOTAL | DG77: RAD | DH77: CANTIDAD | DI77: SUBTOTAL | DJ77: TOTAL | DK77: ALU | DL77: ACC | DM77: VIDRIO | DN77: TRANSPORTE | DO77: VIATICOS | DP77: BACKOFFICE | DQ77: GAST VENTA | DR77: GAST FINANC | DS77: COSTOS IND | DT77: ENSAMBLE | DU77: INSTALACION | DV77: M2 INOX | DW77: M2 ALU | DX77: VR INOX | DY77: VR ALU
C78: SISTEMA | L78: =J78*K78*M78 -> 0 | N78: =IFERROR(AL78,"") -> 1.0765547 | O78: =IFERROR(N78*M78,"") -> 0 | Q78: =Q79+BF78+($R$350*Q79) -> 0 | R78: =IFERROR(R79+($R$348*R79),"") -> 0 | S78: =+IF(R80="SI",((W82*'BD GN'!$AB$2)+S79)*1,COTIZACIÓN!S79*1)+(P79*S79) -> 0 | T78: =IFERROR(R78*IF(K78<=3,$T$13,15%),"") -> 0 | U78: =BH78+BG78 -> 0 | V78: =IFERROR(BN78,0) | W78: =IFERROR(IF(X80="SI",W81*J78*K78,IF(BE78=3,BE80,IF(BE78=4,BE81,IF(BE78=5,BE82,IF(BE78>5,BE82+(BE83*(BE78-5)),"")))))*0,"") | X78: =IFERROR(IF(X79="NO",(VLOOKUP(D78,'BD M.O'!C:E,3,FALSE))*W82,((VLOOKUP(D78,'BD M.O'!C:E,3,FALSE))+7500)*W82),"") | Y78: =IFERROR($Y$13*AK78,"") -> 0.042084457 | Z78: =IFERROR(($Z$13*AK78)+X78,"") | AA78: =IFERROR(Y78+Z78,"") | AB78: =IFERROR((SUM(Q78:X78)-T78+T80)*$AB$13,"") -> 0 | AC78: =IFERROR(((SUM(Q78:V78,IF(X83>AA78,AVERAGE(X83,AA78),AA78))-T78+T80))*$AB$13,"") -> 0 | AD78: =IFERROR((J78*K78*$BV$14),"") | AE78: =IFERROR($AE$13*AK78,"") -> 0.064010593 | AF78: =IFERROR(($CI$11+$CI$13)*W82,"") | AG78: =IFERROR((SUM(Q78:X78,AB78,AD78,AF78)-T78+T80)*$AG$13,"") -> 0 | AH78: =IFERROR((SUM(Q78:V78,(IF(X83>AA78,AVERAGE(X83,AA78),AA78)),AC78,AE78,AF78)-T78+T80)*$AG$13,"") -> 0.032005296 | AI78: =IFERROR(AL78*$AI$13,"") -> 0.021531093 | AJ78: =IFERROR($AJ$13*AL78,"") -> 0.006007175 | AK78: =IFERROR(SUM(Q78:X78,AB78,AD78,AG78,AF78)/(1-$AI$13)+(1-$AJ$13)-T78+T80,"") -> 0.99442 | AL78: =IFERROR(SUM(Q78:V78,AC78,(IF(AD78>AE78,AVERAGE(AD78,AE78),AE78)),AF78,,AH78,(IF(SUM(X83)>AA78,AVERAGE(AA78,X83),AA78)))/(1-$AJ$13)+(1-$AI$13)-T78+T80,"") -> 1.0765547 | AM78: =$M$15*Q78 -> 0 | AN78: =$M$15*R78 -> 0 | AO78: =$M$15*S78 -> 0 | AP78: =$M$15*T78 -> 0 | AQ78: =$M$15*#REF! -> #REF! | AR78: =$M$15*U78 -> 0 | AS78: =$M$15*V78 -> #VALUE! | AT78: =$M$15*W78 -> #VALUE! | AU78: =$M$15*X78 -> #VALUE! | AV78: =$M$15*AB78 -> 0 | AW78: =$M$15*AE78 -> 0 | AX78: =$M$15*AG78 -> 0 | AY78: =$M$15*AI78 -> 0 | AZ78: =$M$15*AK78 -> 0 | BB78: CORTE 8 | BC78: V8 | BF78: =IF(BH79="NO",((2*J78)+(2*K78))*'BD GN'!$AU$3,((3*J78)+(2*K78))*'BD GN'!$AU$3) -> 0 | BG78: ='BD GN'!$BB$3*J78*K78 -> 0 | BH78: =((J78*2*BE78)+(K78*2*BE78))*'BD GN'!$AN$4 -> 0 | BL78: =J78*K78*2.5*BJ78 -> 0 | BM78: =BK78+BL78 -> 0 | BN78: =IFERROR((VLOOKUP($C$12,'BD GN'!BD:BM,10,FALSE)*BM78)+$BR$338,"") | CV78: =IFERROR(N78*CU78,"") -> 0 | CX78: =IFERROR(P78*CW78,"") -> 0 | CZ78: =IFERROR(R78*CY78,"") -> 0 | DA78: =CU78+CW78+CY78 -> 0 | DB78: =IFERROR(CV78+CX78+CZ78,"") -> 0 | DC78: =M78-(CU78+CW78+CY78) -> 0 | DD78: =IFERROR(O78-(CV78+CX78+CZ78),"") -> 0 | DI78: =IFERROR(IF(DG78>0,(((N78)/(1+10%+19%*5%)+((N78)/(1+10%+19%*5%))*10%)*DH78),0),0) -> 0 | DJ78: =IFERROR(IF(DG78>0,(N78*DH78),0),0) -> 0 | DK78: =IF(DG78>0,((R78+T78)*DH78),0) -> 0 | DL78: =IF(DG78>0,(Q78*DH78),0) -> 0 | DM78: =IF(DG78>0,(S78*DH78),0) -> 0 | DN78: =IF(DG78>0,(BN78*DH78),0) -> 0 | DO78: =IF(DG78>0,(AF78*DH78),0) -> 0 | DP78: =IF(DG78>0,((DI78)*('BD P&G'!$E$16+'BD P&G'!$E$17+'BD P&G'!$E$18+'BD P&G'!$E$19+'BD P&G'!$E$20+'BD P&G'!$E$21+'BD P&G'!$E$22+'BD P&G'!$E$23)*DH78),0) -> 0 | DQ78: =IFERROR(IF(DG78>0,((DI78*'BD P&G'!$E$7)+(DI78*'BD P&G'!$E$9)+AI78),0),0) -> 0 | DR78: =IFERROR(IF(DG78>0,((DI78*1%)),0),0) -> 0 | DS78: =IFERROR(IF(DG78>0,(((DI78*'BD P&G'!$E$32+DI78*'BD P&G'!$E$33+DI78*'BD P&G'!$E$35+DI78*'BD P&G'!$E$36+DI78*'BD P&G'!$E$37))),0),0) -> 0 | DT78: =IF(DG78>0,(Y78*DH78),0) -> 0 | DU78: =IF(DG78>0,(Z78*DH78),0) -> 0 | DV78: =IF(DG78>0,(Y82*DH78),0) -> 0 | DW78: =IF(DG78>0,(Z82*DH78),0) -> 0 | DX78: =IF(DV78>0,DJ78,0) -> 0 | DY78: =IF(DW78>0,DJ78,0) -> 0
C79: CRISTAL | T79: =IFERROR(T78/$R$353,"") -> 0 | W79: ANGEO | X79: NO | BB79: CORTE 9 | BC79: V9 | BE79: ALFAJÍA | BF79: NO | BG79: LUCETA | BH79: NO
C80: ACABADO ALUMINIO | Q80: SANDBLASTING | R80: NO | T80: =IFERROR(($R$353-8000)*T79,"") -> 0 | W80: FACHADA | X80: NO | BB80: CORTE 10 | BC80: V10 | BE80: =IFERROR(VLOOKUP(D78,'BD M.O'!C:H,4,FALSE),"") | BF80: 2HOJAS
C81: PELÍCULA PROTECCIÓN | D81: PERFILES | F81: X | G81: CRISTAL | I81: =+IF($BG$9="SI","","X") -> X | R81: VIDRIO M2 | S81: =IF(S79="","",S79/(J78*K78)) | W81: =IFERROR(IF(X80="SI",VLOOKUP(D78,'BD M.O'!C:F,4,FALSE),""),"") | X81: FACHADA | Y81: M2 INOX | Z81: M2 ALU | BC81: V11 | BE81: =IFERROR(VLOOKUP(COTIZACIÓN!D78,'BD M.O'!C:I,5,FALSE),"") | BF81: 3HOJAS | DI81: =IFERROR(IF(DG81>0,(((N78)/(1+10%+19%*5%)+((N78)/(1+10%+19%*5%))*10%)*DH81),0),0) -> 0 | DJ81: =IFERROR(IF(DG81>0,(N78*DH81),0),0) -> 0 | DK81: =IF(DG81>0,((R78+T78)*DH81),0) -> 0 | DL81: =IF(DG81>0,(Q78*DH81),0) -> 0 | DM81: =IF(DG81>0,(S78*DH81),0) -> 0 | DN81: =IF(DG81>0,(BN78*DH81),0) -> 0 | DO81: =IF(DG81>0,(AF78*DH81),0) -> 0 | DP81: =IF(DG81>0,((DI81)*('BD P&G'!$E$16+'BD P&G'!$E$17+'BD P&G'!$E$18+'BD P&G'!$E$19+'BD P&G'!$E$20+'BD P&G'!$E$21+'BD P&G'!$E$22+'BD P&G'!$E$23)*DH81),0) -> 0 | DQ81: =IFERROR(IF(DG81>0,((DI81*'BD P&G'!$E$7)+(DI81*'BD P&G'!$E$9)+AI78),0),0) -> 0 | DR81: =IFERROR(IF(DG81>0,((DI81*1%)),0),0) -> 0 | DS81: =IFERROR(IF(DG81>0,(((DI81*'BD P&G'!$E$32+DI81*'BD P&G'!$E$33+DI81*'BD P&G'!$E$35+DI81*'BD P&G'!$E$36+DI81*'BD P&G'!$E$37))),0),0) -> 0 | DT81: =IF(DG81>0,(Y78*DH81),0) -> 0 | DU81: =IF(DG81>0,(Z78*DH81),0) -> 0 | DV81: =IF(DG81>0,(Y82*DH81),0) -> 0 | DW81: =IF(DG81>0,(Z82*DH81),0) -> 0 | DX81: =IF(DV81>0,DJ81,0) -> 0 | DY81: =IF(DW81>0,DJ81,0) -> 0
C82: CERRADURA | D82: =IFERROR(VLOOKUP(D78,'BD GN'!C:E,3,),"") | R82: SISTEMA M2 | S82: =IFERROR(IF(N78="","",N78/W82),"") | W82: =+IF(J78*K78>=1,J78*K78,IF(AND(J78*K78>0,J78*K78<1),1,"")) | X82: AREA | Y82: =IFERROR(IF(D78='BD GN'!$C$25,COTIZACIÓN!W82,IF(D78='BD GN'!$C$26,COTIZACIÓN!W82,IF(D78='BD GN'!$C$27,COTIZACIÓN!W82,IF(COTIZACIÓN!D78='BD GN'!$C$28,COTIZACIÓN!W82,IF(COTIZACIÓN!D78='BD GN'!$C$29,COTIZACIÓN!W82,IF(COTIZACIÓN!D78='BD GN'!$C$35,COTIZACIÓN!W82,IF(COTIZACIÓN!D78='BD GN'!$C$36,COTIZACIÓN!W82,IF(COTIZACIÓN!D78='BD GN'!$C$37,COTIZACIÓN!W82,IF(COTIZACIÓN!D78='BD GN'!$C$38,COTIZACIÓN!W82,IF(COTIZACIÓN!D78='BD GN'!$C$39,COTIZACIÓN!W82,IF(COTIZACIÓN!D78='BD GN'!$C$40,COTIZACIÓN!W82,IF(COTIZACIÓN!D78='BD GN'!$C$41,COTIZACIÓN!W82,IF(COTIZACIÓN!D78='BD GN'!$C$42,COTIZACIÓN!W82,IF(COTIZACIÓN!D78='BD GN'!$C$49,COTIZACIÓN!W82,IF(COTIZACIÓN!D78='BD GN'!$C$50,COTIZACIÓN!W82,IF(COTIZACIÓN!D78='BD GN'!$C$51,COTIZACIÓN!W82,IF(COTIZACIÓN!D78='BD GN'!$C$67,COTIZACIÓN!W82,0))))))))))))))))),0) -> 0 | Z82: =IFERROR(W82-Y82,0) -> 0 | BC82: V12 | BE82: =IFERROR(VLOOKUP(D78,'BD M.O'!C:I,6,FALSE),"") | BF82: 4HOJAS
C83: OBSERVACIONES | D83: N.A | R83: VR REF SIS M2 | S83: =IFERROR(IF($C$12='BD GN'!$CC$1,VLOOKUP(COTIZACIÓN!D78,'BD GN'!CB:CG,2,FALSE),IF(COTIZACIÓN!$C$12='BD GN'!$CD$1,VLOOKUP(COTIZACIÓN!D78,'BD GN'!CB:CG,3,FALSE),IF($C$12='BD GN'!$CE$1,VLOOKUP(COTIZACIÓN!D78,'BD GN'!CB:CG,4,FALSE),IF(COTIZACIÓN!$C$12='BD GN'!$CF$1,VLOOKUP(COTIZACIÓN!D78,'BD GN'!CB:CG,5,FALSE),IF(COTIZACIÓN!$C$12='BD GN'!$CG$1,VLOOKUP(COTIZACIÓN!D78,'BD GN'!CB:CG,6,FALSE),""))))),"-") | W83: TOTAL M.O | X83: =IFERROR(SUM(W78:X78),"") -> 0 | Y83: TOTAL M.O PYG | Z83: =IFERROR(Y78+Z78,"") | BC83: V13 | BE83: =IFERROR(VLOOKUP(D78,'BD M.O'!C:I,7,FALSE),"") | BF83: HOJA ADIC
A84: ÍTEM | B84: UBICACIÓN | C84: CONFIGURACIÓN | D84: DESCRIPCIÓN | J84: AN (MT) | K84: AL (MT) | L84: M2 | M84: CNT | N84: VR UNT | O84: VR TOTAL | Q84: ACCE | R84: ALUMINIO | S84: CRISTAL | T84: % DESP ALU | U84: EMPQ | V84: TRANS | W84: ENSAMBLE | X84: INSTA | Y84: ENSAM PYG | Z84: INST PYG | AA84: TOTAL M.O PYG | AB84: IMPREV | AC84: IMPREV PYG | AD84: BACKOFFICE | AE84: PYG | AF84: VIATICOS | AG84: BENEFICIO | AH84: BENEFICIO PYG | AI84: COMISIÓN | AJ84: IMPUESTOS | AK84: VENTA SIN PYG | AL84: VENTA FINAL | AM84: ACCE | AN84: ALUMINIO | AO84: CRISTAL | AP84: % DESP ALU | AQ84: MAQ | AR84: EMPQ | AS84: TRANS | AT84: ENSAMBLE | AU84: INSTA | AV84: IMPREV | AW84: BACKOFFICE | AX84: UTILIDAD | AY84: COMISIÓN | AZ84: VENTA | BC84: V14 | BE84: Nº MÓDULOS | BF84: =$BF$13 -> VR SILICONA | BG84: =$BG$13 -> VR PELÍCULA | BH84: =$BH$13 -> VR EMBALAJE | BJ84: =$BJ$13 -> ESP. CRISTAL | BK84: ESTRUCTURA | BL84: CRISTAL | BM84: =BM77 -> TOTAL | BN84: VR TRANSP | CK84: OR | CL84: MD | CM84: AD | CN84: EL | CO84: MD | CP84: PL | CQ84: PRO | CR84: DESP | CS84: MT | CT84: ENT | CU84: CNT | CV84: VR TOTAL | CW84: CNT | CX84: VR TOTAL | CY84: CNT | CZ84: VR TOTAL | DA84: CNT | DB84: VR TOTAL | DC84: CNT | DD84: VR TOTAL | DG84: RAD | DH84: CANTIDAD | DI84: SUBTOTAL | DJ84: TOTAL | DK84: ALU | DL84: ACC | DM84: VIDRIO | DN84: TRANSPORTE | DO84: VIATICOS | DP84: BACKOFFICE | DQ84: GAST VENTA | DR84: GAST FINANC | DS84: COSTOS IND | DT84: ENSAMBLE | DU84: INSTALACION | DV84: M2 INOX | DW84: M2 ALU | DX84: VR INOX | DY84: VR ALU
C85: SISTEMA | L85: =J85*K85*M85 -> 0 | N85: =IFERROR(AL85,"") -> 1.0765547 | O85: =IFERROR(N85*M85,"") -> 0 | Q85: =Q86+BF85+($R$350*Q86) -> 0 | R85: =IFERROR(R86+($R$348*R86),"") -> 0 | S85: =+IF(R87="SI",((W89*'BD GN'!$AB$2)+S86)*1,COTIZACIÓN!S86*1)+(P86*S86) -> 0 | T85: =IFERROR(R85*IF(K85<=3,$T$13,15%),"") -> 0 | U85: =BH85+BG85 -> 0 | V85: =IFERROR(BN85,0) | W85: =IFERROR(IF(X87="SI",W88*J85*K85,IF(BE85=3,BE87,IF(BE85=4,BE88,IF(BE85=5,BE89,IF(BE85>5,BE89+(BE90*(BE85-5)),"")))))*0,"") | X85: =IFERROR(IF(X86="NO",(VLOOKUP(D85,'BD M.O'!C:E,3,FALSE))*W89,((VLOOKUP(D85,'BD M.O'!C:E,3,FALSE))+7500)*W89),"") | Y85: =IFERROR($Y$13*AK85,"") -> 0.042084457 | Z85: =IFERROR(($Z$13*AK85)+X85,"") | AA85: =IFERROR(Y85+Z85,"") | AB85: =IFERROR((SUM(Q85:X85)-T85+T87)*$AB$13,"") -> 0 | AC85: =IFERROR(((SUM(Q85:V85,IF(X90>AA85,AVERAGE(X90,AA85),AA85))-T85+T87))*$AB$13,"") -> 0 | AD85: =IFERROR((J85*K85*$BV$14),"") | AE85: =IFERROR($AE$13*AK85,"") -> 0.064010593 | AF85: =IFERROR(($CI$11+$CI$13)*W89,"") | AG85: =IFERROR((SUM(Q85:X85,AB85,AD85,AF85)-T85+T87)*$AG$13,"") -> 0 | AH85: =IFERROR((SUM(Q85:V85,(IF(X90>AA85,AVERAGE(X90,AA85),AA85)),AC85,AE85,AF85)-T85+T87)*$AG$13,"") -> 0.032005296 | AI85: =IFERROR(AL85*$AI$13,"") -> 0.021531093 | AJ85: =IFERROR($AJ$13*AL85,"") -> 0.006007175 | AK85: =IFERROR(SUM(Q85:X85,AB85,AD85,AG85,AF85)/(1-$AI$13)+(1-$AJ$13)-T85+T87,"") -> 0.99442 | AL85: =IFERROR(SUM(Q85:V85,AC85,(IF(AD85>AE85,AVERAGE(AD85,AE85),AE85)),AF85,,AH85,(IF(SUM(X90)>AA85,AVERAGE(AA85,X90),AA85)))/(1-$AJ$13)+(1-$AI$13)-T85+T87,"") -> 1.0765547 | AM85: =$M$15*Q85 -> 0 | AN85: =$M$15*R85 -> 0 | AO85: =$M$15*S85 -> 0 | AP85: =$M$15*T85 -> 0 | AQ85: =$M$15*#REF! -> #REF! | AR85: =$M$15*U85 -> 0 | AS85: =$M$15*V85 -> #VALUE! | AT85: =$M$15*W85 -> #VALUE! | AU85: =$M$15*X85 -> #VALUE! | AV85: =$M$15*AB85 -> 0 | AW85: =$M$15*AE85 -> 0 | AX85: =$M$15*AG85 -> 0 | AY85: =$M$15*AI85 -> 0 | AZ85: =$M$15*AK85 -> 0 | BB85: CORTE 8 | BC85: V8 | BF85: =IF(BH86="NO",((2*J85)+(2*K85))*'BD GN'!$AU$3,((3*J85)+(2*K85))*'BD GN'!$AU$3) -> 0 | BG85: ='BD GN'!$BB$3*J85*K85 -> 0 | BH85: =((J85*2*BE85)+(K85*2*BE85))*'BD GN'!$AN$4 -> 0 | BL85: =J85*K85*2.5*BJ85 -> 0 | BM85: =BK85+BL85 -> 0 | BN85: =IFERROR((VLOOKUP($C$12,'BD GN'!BD:BM,10,FALSE)*BM85)+$BR$338,"") | CV85: =IFERROR(N85*CU85,"") -> 0 | CX85: =IFERROR(P85*CW85,"") -> 0 | CZ85: =IFERROR(R85*CY85,"") -> 0 | DA85: =CU85+CW85+CY85 -> 0 | DB85: =IFERROR(CV85+CX85+CZ85,"") -> 0 | DC85: =M85-(CU85+CW85+CY85) -> 0 | DD85: =IFERROR(O85-(CV85+CX85+CZ85),"") -> 0 | DI85: =IFERROR(IF(DG85>0,(((N85)/(1+10%+19%*5%)+((N85)/(1+10%+19%*5%))*10%)*DH85),0),0) -> 0 | DJ85: =IFERROR(IF(DG85>0,(N85*DH85),0),0) -> 0 | DK85: =IF(DG85>0,((R85+T85)*DH85),0) -> 0 | DL85: =IF(DG85>0,(Q85*DH85),0) -> 0 | DM85: =IF(DG85>0,(S85*DH85),0) -> 0 | DN85: =IF(DG85>0,(BN85*DH85),0) -> 0 | DO85: =IF(DG85>0,(AF85*DH85),0) -> 0 | DP85: =IF(DG85>0,((DI85)*('BD P&G'!$E$16+'BD P&G'!$E$17+'BD P&G'!$E$18+'BD P&G'!$E$19+'BD P&G'!$E$20+'BD P&G'!$E$21+'BD P&G'!$E$22+'BD P&G'!$E$23)*DH85),0) -> 0 | DQ85: =IFERROR(IF(DG85>0,((DI85*'BD P&G'!$E$7)+(DI85*'BD P&G'!$E$9)+AI85),0),0) -> 0 | DR85: =IFERROR(IF(DG85>0,((DI85*1%)),0),0) -> 0 | DS85: =IFERROR(IF(DG85>0,(((DI85*'BD P&G'!$E$32+DI85*'BD P&G'!$E$33+DI85*'BD P&G'!$E$35+DI85*'BD P&G'!$E$36+DI85*'BD P&G'!$E$37))),0),0) -> 0 | DT85: =IF(DG85>0,(Y85*DH85),0) -> 0 | DU85: =IF(DG85>0,(Z85*DH85),0) -> 0 | DV85: =IF(DG85>0,(Y89*DH85),0) -> 0 | DW85: =IF(DG85>0,(Z89*DH85),0) -> 0 | DX85: =IF(DV85>0,DJ85,0) -> 0 | DY85: =IF(DW85>0,DJ85,0) -> 0
C86: CRISTAL | T86: =IFERROR(T85/$R$353,"") -> 0 | W86: ANGEO | X86: NO | BB86: CORTE 9 | BC86: V9 | BE86: ALFAJÍA | BF86: NO | BG86: LUCETA | BH86: NO
C87: ACABADO ALUMINIO | Q87: SANDBLASTING | R87: NO | T87: =IFERROR(($R$353-8000)*T86,"") -> 0 | W87: FACHADA | X87: NO | BB87: CORTE 10 | BC87: V10 | BE87: =IFERROR(VLOOKUP(D85,'BD M.O'!C:H,4,FALSE),"") | BF87: 2HOJAS
C88: PELÍCULA PROTECCIÓN | D88: PERFILES | F88: X | G88: CRISTAL | I88: =+IF($BG$9="SI","","X") -> X | R88: VIDRIO M2 | S88: =IF(S86="","",S86/(J85*K85)) | W88: =IFERROR(IF(X87="SI",VLOOKUP(D85,'BD M.O'!C:F,4,FALSE),""),"") | X88: FACHADA | Y88: M2 INOX | Z88: M2 ALU | BC88: V11 | BE88: =IFERROR(VLOOKUP(COTIZACIÓN!D85,'BD M.O'!C:I,5,FALSE),"") | BF88: 3HOJAS | DI88: =IFERROR(IF(DG88>0,(((N85)/(1+10%+19%*5%)+((N85)/(1+10%+19%*5%))*10%)*DH88),0),0) -> 0 | DJ88: =IFERROR(IF(DG88>0,(N85*DH88),0),0) -> 0 | DK88: =IF(DG88>0,((R85+T85)*DH88),0) -> 0 | DL88: =IF(DG88>0,(Q85*DH88),0) -> 0 | DM88: =IF(DG88>0,(S85*DH88),0) -> 0 | DN88: =IF(DG88>0,(BN85*DH88),0) -> 0 | DO88: =IF(DG88>0,(AF85*DH88),0) -> 0 | DP88: =IF(DG88>0,((DI88)*('BD P&G'!$E$16+'BD P&G'!$E$17+'BD P&G'!$E$18+'BD P&G'!$E$19+'BD P&G'!$E$20+'BD P&G'!$E$21+'BD P&G'!$E$22+'BD P&G'!$E$23)*DH88),0) -> 0 | DQ88: =IFERROR(IF(DG88>0,((DI88*'BD P&G'!$E$7)+(DI88*'BD P&G'!$E$9)+AI85),0),0) -> 0 | DR88: =IFERROR(IF(DG88>0,((DI88*1%)),0),0) -> 0 | DS88: =IFERROR(IF(DG88>0,(((DI88*'BD P&G'!$E$32+DI88*'BD P&G'!$E$33+DI88*'BD P&G'!$E$35+DI88*'BD P&G'!$E$36+DI88*'BD P&G'!$E$37))),0),0) -> 0 | DT88: =IF(DG88>0,(Y85*DH88),0) -> 0 | DU88: =IF(DG88>0,(Z85*DH88),0) -> 0 | DV88: =IF(DG88>0,(Y89*DH88),0) -> 0 | DW88: =IF(DG88>0,(Z89*DH88),0) -> 0 | DX88: =IF(DV88>0,DJ88,0) -> 0 | DY88: =IF(DW88>0,DJ88,0) -> 0
C89: CERRADURA | D89: =IFERROR(VLOOKUP(D85,'BD GN'!C:E,3,),"") | R89: SISTEMA M2 | S89: =IFERROR(IF(N85="","",N85/W89),"") | W89: =+IF(J85*K85>=1,J85*K85,IF(AND(J85*K85>0,J85*K85<1),1,"")) | X89: AREA | Y89: =IFERROR(IF(D85='BD GN'!$C$25,COTIZACIÓN!W89,IF(D85='BD GN'!$C$26,COTIZACIÓN!W89,IF(D85='BD GN'!$C$27,COTIZACIÓN!W89,IF(COTIZACIÓN!D85='BD GN'!$C$28,COTIZACIÓN!W89,IF(COTIZACIÓN!D85='BD GN'!$C$29,COTIZACIÓN!W89,IF(COTIZACIÓN!D85='BD GN'!$C$35,COTIZACIÓN!W89,IF(COTIZACIÓN!D85='BD GN'!$C$36,COTIZACIÓN!W89,IF(COTIZACIÓN!D85='BD GN'!$C$37,COTIZACIÓN!W89,IF(COTIZACIÓN!D85='BD GN'!$C$38,COTIZACIÓN!W89,IF(COTIZACIÓN!D85='BD GN'!$C$39,COTIZACIÓN!W89,IF(COTIZACIÓN!D85='BD GN'!$C$40,COTIZACIÓN!W89,IF(COTIZACIÓN!D85='BD GN'!$C$41,COTIZACIÓN!W89,IF(COTIZACIÓN!D85='BD GN'!$C$42,COTIZACIÓN!W89,IF(COTIZACIÓN!D85='BD GN'!$C$49,COTIZACIÓN!W89,IF(COTIZACIÓN!D85='BD GN'!$C$50,COTIZACIÓN!W89,IF(COTIZACIÓN!D85='BD GN'!$C$51,COTIZACIÓN!W89,IF(COTIZACIÓN!D85='BD GN'!$C$67,COTIZACIÓN!W89,0))))))))))))))))),0) -> 0 | Z89: =IFERROR(W89-Y89,0) -> 0 | BC89: V12 | BE89: =IFERROR(VLOOKUP(D85,'BD M.O'!C:I,6,FALSE),"") | BF89: 4HOJAS
C90: OBSERVACIONES | D90: N.A | R90: VR REF SIS M2 | S90: =IFERROR(IF($C$12='BD GN'!$CC$1,VLOOKUP(COTIZACIÓN!D85,'BD GN'!CB:CG,2,FALSE),IF(COTIZACIÓN!$C$12='BD GN'!$CD$1,VLOOKUP(COTIZACIÓN!D85,'BD GN'!CB:CG,3,FALSE),IF($C$12='BD GN'!$CE$1,VLOOKUP(COTIZACIÓN!D85,'BD GN'!CB:CG,4,FALSE),IF(COTIZACIÓN!$C$12='BD GN'!$CF$1,VLOOKUP(COTIZACIÓN!D85,'BD GN'!CB:CG,5,FALSE),IF(COTIZACIÓN!$C$12='BD GN'!$CG$1,VLOOKUP(COTIZACIÓN!D85,'BD GN'!CB:CG,6,FALSE),""))))),"-") | W90: TOTAL M.O | X90: =IFERROR(SUM(W85:X85),"") -> 0 | Y90: TOTAL M.O PYG | Z90: =IFERROR(Y85+Z85,"") | BC90: V13 | BE90: =IFERROR(VLOOKUP(D85,'BD M.O'!C:I,7,FALSE),"") | BF90: HOJA ADIC
A91: ÍTEM | B91: UBICACIÓN | C91: CONFIGURACIÓN | D91: DESCRIPCIÓN | J91: AN (MT) | K91: AL (MT) | L91: M2 | M91: CNT | N91: VR UNT | O91: VR TOTAL | Q91: ACCE | R91: ALUMINIO | S91: CRISTAL | T91: % DESP ALU | U91: EMPQ | V91: TRANS | W91: ENSAMBLE | X91: INSTA | Y91: ENSAM PYG | Z91: INST PYG | AA91: TOTAL M.O PYG | AB91: IMPREV | AC91: IMPREV PYG | AD91: BACKOFFICE | AE91: PYG | AF91: VIATICOS | AG91: BENEFICIO | AH91: BENEFICIO PYG | AI91: COMISIÓN | AJ91: IMPUESTOS | AK91: VENTA SIN PYG | AL91: VENTA FINAL | AM91: ACCE | AN91: ALUMINIO | AO91: CRISTAL | AP91: % DESP ALU | AQ91: MAQ | AR91: EMPQ | AS91: TRANS | AT91: ENSAMBLE | AU91: INSTA | AV91: IMPREV | AW91: BACKOFFICE | AX91: UTILIDAD | AY91: COMISIÓN | AZ91: VENTA | BC91: V14 | BE91: Nº MÓDULOS | BF91: =$BF$13 -> VR SILICONA | BG91: =$BG$13 -> VR PELÍCULA | BH91: =$BH$13 -> VR EMBALAJE | BJ91: =$BJ$13 -> ESP. CRISTAL | BK91: ESTRUCTURA | BL91: CRISTAL | BM91: =BM84 -> TOTAL | BN91: VR TRANSP | CK91: OR | CL91: MD | CM91: AD | CN91: EL | CO91: MD | CP91: PL | CQ91: PRO | CR91: DESP | CS91: MT | CT91: ENT | CU91: CNT | CV91: VR TOTAL | CW91: CNT | CX91: VR TOTAL | CY91: CNT | CZ91: VR TOTAL | DA91: CNT | DB91: VR TOTAL | DC91: CNT | DD91: VR TOTAL | DG91: RAD | DH91: CANTIDAD | DI91: SUBTOTAL | DJ91: TOTAL | DK91: ALU | DL91: ACC | DM91: VIDRIO | DN91: TRANSPORTE | DO91: VIATICOS | DP91: BACKOFFICE | DQ91: GAST VENTA | DR91: GAST FINANC | DS91: COSTOS IND | DT91: ENSAMBLE | DU91: INSTALACION | DV91: M2 INOX | DW91: M2 ALU | DX91: VR INOX | DY91: VR ALU
C92: SISTEMA | L92: =J92*K92*M92 -> 0 | N92: =IFERROR(AL92,"") -> 1.0765547 | O92: =IFERROR(N92*M92,"") -> 0 | Q92: =Q93+BF92+($R$350*Q93) -> 0 | R92: =IFERROR(R93+($R$348*R93),"") -> 0 | S92: =+IF(R94="SI",((W96*'BD GN'!$AB$2)+S93)*1,COTIZACIÓN!S93*1)+(P93*S93) -> 0 | T92: =IFERROR(R92*IF(K92<=3,$T$13,15%),"") -> 0 | U92: =BH92+BG92 -> 0 | V92: =IFERROR(BN92,0) | W92: =IFERROR(IF(X94="SI",W95*J92*K92,IF(BE92=3,BE94,IF(BE92=4,BE95,IF(BE92=5,BE96,IF(BE92>5,BE96+(BE97*(BE92-5)),"")))))*0,"") | X92: =IFERROR(IF(X93="NO",(VLOOKUP(D92,'BD M.O'!C:E,3,FALSE))*W96,((VLOOKUP(D92,'BD M.O'!C:E,3,FALSE))+7500)*W96),"") | Y92: =IFERROR($Y$13*AK92,"") -> 0.042084457 | Z92: =IFERROR(($Z$13*AK92)+X92,"") | AA92: =IFERROR(Y92+Z92,"") | AB92: =IFERROR((SUM(Q92:X92)-T92+T94)*$AB$13,"") -> 0 | AC92: =IFERROR(((SUM(Q92:V92,IF(X97>AA92,AVERAGE(X97,AA92),AA92))-T92+T94))*$AB$13,"") -> 0 | AD92: =IFERROR((J92*K92*$BV$14),"") | AE92: =IFERROR($AE$13*AK92,"") -> 0.064010593 | AF92: =IFERROR(($CI$11+$CI$13)*W96,"") | AG92: =IFERROR((SUM(Q92:X92,AB92,AD92,AF92)-T92+T94)*$AG$13,"") -> 0 | AH92: =IFERROR((SUM(Q92:V92,(IF(X97>AA92,AVERAGE(X97,AA92),AA92)),AC92,AE92,AF92)-T92+T94)*$AG$13,"") -> 0.032005296 | AI92: =IFERROR(AL92*$AI$13,"") -> 0.021531093 | AJ92: =IFERROR($AJ$13*AL92,"") -> 0.006007175 | AK92: =IFERROR(SUM(Q92:X92,AB92,AD92,AG92,AF92)/(1-$AI$13)+(1-$AJ$13)-T92+T94,"") -> 0.99442 | AL92: =IFERROR(SUM(Q92:V92,AC92,(IF(AD92>AE92,AVERAGE(AD92,AE92),AE92)),AF92,,AH92,(IF(SUM(X97)>AA92,AVERAGE(AA92,X97),AA92)))/(1-$AJ$13)+(1-$AI$13)-T92+T94,"") -> 1.0765547 | AM92: =$M$15*Q92 -> 0 | AN92: =$M$15*R92 -> 0 | AO92: =$M$15*S92 -> 0 | AP92: =$M$15*T92 -> 0 | AQ92: =$M$15*#REF! -> #REF! | AR92: =$M$15*U92 -> 0 | AS92: =$M$15*V92 -> #VALUE! | AT92: =$M$15*W92 -> #VALUE! | AU92: =$M$15*X92 -> #VALUE! | AV92: =$M$15*AB92 -> 0 | AW92: =$M$15*AE92 -> 0 | AX92: =$M$15*AG92 -> 0 | AY92: =$M$15*AI92 -> 0 | AZ92: =$M$15*AK92 -> 0 | BB92: CORTE 8 | BC92: V8 | BF92: =IF(BH93="NO",((2*J92)+(2*K92))*'BD GN'!$AU$3,((3*J92)+(2*K92))*'BD GN'!$AU$3) -> 0 | BG92: ='BD GN'!$BB$3*J92*K92 -> 0 | BH92: =((J92*2*BE92)+(K92*2*BE92))*'BD GN'!$AN$4 -> 0 | BL92: =J92*K92*2.5*BJ92 -> 0 | BM92: =BK92+BL92 -> 0 | BN92: =IFERROR((VLOOKUP($C$12,'BD GN'!BD:BM,10,FALSE)*BM92)+$BR$338,"") | CV92: =IFERROR(N92*CU92,"") -> 0 | CX92: =IFERROR(P92*CW92,"") -> 0 | CZ92: =IFERROR(R92*CY92,"") -> 0 | DA92: =CU92+CW92+CY92 -> 0 | DB92: =IFERROR(CV92+CX92+CZ92,"") -> 0 | DC92: =M92-(CU92+CW92+CY92) -> 0 | DD92: =IFERROR(O92-(CV92+CX92+CZ92),"") -> 0 | DI92: =IFERROR(IF(DG92>0,(((N92)/(1+10%+19%*5%)+((N92)/(1+10%+19%*5%))*10%)*DH92),0),0) -> 0 | DJ92: =IFERROR(IF(DG92>0,(N92*DH92),0),0) -> 0 | DK92: =IF(DG92>0,((R92+T92)*DH92),0) -> 0 | DL92: =IF(DG92>0,(Q92*DH92),0) -> 0 | DM92: =IF(DG92>0,(S92*DH92),0) -> 0 | DN92: =IF(DG92>0,(BN92*DH92),0) -> 0 | DO92: =IF(DG92>0,(AF92*DH92),0) -> 0 | DP92: =IF(DG92>0,((DI92)*('BD P&G'!$E$16+'BD P&G'!$E$17+'BD P&G'!$E$18+'BD P&G'!$E$19+'BD P&G'!$E$20+'BD P&G'!$E$21+'BD P&G'!$E$22+'BD P&G'!$E$23)*DH92),0) -> 0 | DQ92: =IFERROR(IF(DG92>0,((DI92*'BD P&G'!$E$7)+(DI92*'BD P&G'!$E$9)+AI92),0),0) -> 0 | DR92: =IFERROR(IF(DG92>0,((DI92*1%)),0),0) -> 0 | DS92: =IFERROR(IF(DG92>0,(((DI92*'BD P&G'!$E$32+DI92*'BD P&G'!$E$33+DI92*'BD P&G'!$E$35+DI92*'BD P&G'!$E$36+DI92*'BD P&G'!$E$37))),0),0) -> 0 | DT92: =IF(DG92>0,(Y92*DH92),0) -> 0 | DU92: =IF(DG92>0,(Z92*DH92),0) -> 0 | DV92: =IF(DG92>0,(Y96*DH92),0) -> 0 | DW92: =IF(DG92>0,(Z96*DH92),0) -> 0 | DX92: =IF(DV92>0,DJ92,0) -> 0 | DY92: =IF(DW92>0,DJ92,0) -> 0
C93: CRISTAL | T93: =IFERROR(T92/$R$353,"") -> 0 | W93: ANGEO | X93: NO | BB93: CORTE 9 | BC93: V9 | BE93: ALFAJÍA | BF93: NO | BG93: LUCETA | BH93: NO
C94: ACABADO ALUMINIO | Q94: SANDBLASTING | R94: NO | T94: =IFERROR(($R$353-8000)*T93,"") -> 0 | W94: FACHADA | X94: NO | BB94: CORTE 10 | BC94: V10 | BE94: =IFERROR(VLOOKUP(D92,'BD M.O'!C:H,4,FALSE),"") | BF94: 2HOJAS
C95: PELÍCULA PROTECCIÓN | D95: PERFILES | F95: X | G95: CRISTAL | I95: =+IF($BG$9="SI","","X") -> X | R95: VIDRIO M2 | S95: =IF(S93="","",S93/(J92*K92)) | W95: =IFERROR(IF(X94="SI",VLOOKUP(D92,'BD M.O'!C:F,4,FALSE),""),"") | X95: FACHADA | Y95: M2 INOX | Z95: M2 ALU | BC95: V11 | BE95: =IFERROR(VLOOKUP(COTIZACIÓN!D92,'BD M.O'!C:I,5,FALSE),"") | BF95: 3HOJAS | DI95: =IFERROR(IF(DG95>0,(((N92)/(1+10%+19%*5%)+((N92)/(1+10%+19%*5%))*10%)*DH95),0),0) -> 0 | DJ95: =IFERROR(IF(DG95>0,(N92*DH95),0),0) -> 0 | DK95: =IF(DG95>0,((R92+T92)*DH95),0) -> 0 | DL95: =IF(DG95>0,(Q92*DH95),0) -> 0 | DM95: =IF(DG95>0,(S92*DH95),0) -> 0 | DN95: =IF(DG95>0,(BN92*DH95),0) -> 0 | DO95: =IF(DG95>0,(AF92*DH95),0) -> 0 | DP95: =IF(DG95>0,((DI95)*('BD P&G'!$E$16+'BD P&G'!$E$17+'BD P&G'!$E$18+'BD P&G'!$E$19+'BD P&G'!$E$20+'BD P&G'!$E$21+'BD P&G'!$E$22+'BD P&G'!$E$23)*DH95),0) -> 0 | DQ95: =IFERROR(IF(DG95>0,((DI95*'BD P&G'!$E$7)+(DI95*'BD P&G'!$E$9)+AI92),0),0) -> 0 | DR95: =IFERROR(IF(DG95>0,((DI95*1%)),0),0) -> 0 | DS95: =IFERROR(IF(DG95>0,(((DI95*'BD P&G'!$E$32+DI95*'BD P&G'!$E$33+DI95*'BD P&G'!$E$35+DI95*'BD P&G'!$E$36+DI95*'BD P&G'!$E$37))),0),0) -> 0 | DT95: =IF(DG95>0,(Y92*DH95),0) -> 0 | DU95: =IF(DG95>0,(Z92*DH95),0) -> 0 | DV95: =IF(DG95>0,(Y96*DH95),0) -> 0 | DW95: =IF(DG95>0,(Z96*DH95),0) -> 0 | DX95: =IF(DV95>0,DJ95,0) -> 0 | DY95: =IF(DW95>0,DJ95,0) -> 0
C96: CERRADURA | D96: =IFERROR(VLOOKUP(D92,'BD GN'!C:E,3,),"") | R96: SISTEMA M2 | S96: =IFERROR(IF(N92="","",N92/W96),"") | W96: =+IF(J92*K92>=1,J92*K92,IF(AND(J92*K92>0,J92*K92<1),1,"")) | X96: AREA | Y96: =IFERROR(IF(D92='BD GN'!$C$25,COTIZACIÓN!W96,IF(D92='BD GN'!$C$26,COTIZACIÓN!W96,IF(D92='BD GN'!$C$27,COTIZACIÓN!W96,IF(COTIZACIÓN!D92='BD GN'!$C$28,COTIZACIÓN!W96,IF(COTIZACIÓN!D92='BD GN'!$C$29,COTIZACIÓN!W96,IF(COTIZACIÓN!D92='BD GN'!$C$35,COTIZACIÓN!W96,IF(COTIZACIÓN!D92='BD GN'!$C$36,COTIZACIÓN!W96,IF(COTIZACIÓN!D92='BD GN'!$C$37,COTIZACIÓN!W96,IF(COTIZACIÓN!D92='BD GN'!$C$38,COTIZACIÓN!W96,IF(COTIZACIÓN!D92='BD GN'!$C$39,COTIZACIÓN!W96,IF(COTIZACIÓN!D92='BD GN'!$C$40,COTIZACIÓN!W96,IF(COTIZACIÓN!D92='BD GN'!$C$41,COTIZACIÓN!W96,IF(COTIZACIÓN!D92='BD GN'!$C$42,COTIZACIÓN!W96,IF(COTIZACIÓN!D92='BD GN'!$C$49,COTIZACIÓN!W96,IF(COTIZACIÓN!D92='BD GN'!$C$50,COTIZACIÓN!W96,IF(COTIZACIÓN!D92='BD GN'!$C$51,COTIZACIÓN!W96,IF(COTIZACIÓN!D92='BD GN'!$C$67,COTIZACIÓN!W96,0))))))))))))))))),0) -> 0 | Z96: =IFERROR(W96-Y96,0) -> 0 | BC96: V12 | BE96: =IFERROR(VLOOKUP(D92,'BD M.O'!C:I,6,FALSE),"") | BF96: 4HOJAS
C97: OBSERVACIONES | D97: N.A | R97: VR REF SIS M2 | S97: =IFERROR(IF($C$12='BD GN'!$CC$1,VLOOKUP(COTIZACIÓN!D92,'BD GN'!CB:CG,2,FALSE),IF(COTIZACIÓN!$C$12='BD GN'!$CD$1,VLOOKUP(COTIZACIÓN!D92,'BD GN'!CB:CG,3,FALSE),IF($C$12='BD GN'!$CE$1,VLOOKUP(COTIZACIÓN!D92,'BD GN'!CB:CG,4,FALSE),IF(COTIZACIÓN!$C$12='BD GN'!$CF$1,VLOOKUP(COTIZACIÓN!D92,'BD GN'!CB:CG,5,FALSE),IF(COTIZACIÓN!$C$12='BD GN'!$CG$1,VLOOKUP(COTIZACIÓN!D92,'BD GN'!CB:CG,6,FALSE),""))))),"-") | W97: TOTAL M.O | X97: =IFERROR(SUM(W92:X92),"") -> 0 | Y97: TOTAL M.O PYG | Z97: =IFERROR(Y92+Z92,"") | BC97: V13 | BE97: =IFERROR(VLOOKUP(D92,'BD M.O'!C:I,7,FALSE),"") | BF97: HOJA ADIC
A98: ÍTEM | B98: UBICACIÓN | C98: CONFIGURACIÓN | D98: DESCRIPCIÓN | J98: AN (MT) | K98: AL (MT) | L98: M2 | M98: CNT | N98: VR UNT | O98: VR TOTAL | Q98: ACCE | R98: ALUMINIO | S98: CRISTAL | T98: % DESP ALU | U98: EMPQ | V98: TRANS | W98: ENSAMBLE | X98: INSTA | Y98: ENSAM PYG | Z98: INST PYG | AA98: TOTAL M.O PYG | AB98: IMPREV | AC98: IMPREV PYG | AD98: BACKOFFICE | AE98: PYG | AF98: VIATICOS | AG98: BENEFICIO | AH98: BENEFICIO PYG | AI98: COMISIÓN | AJ98: IMPUESTOS | AK98: VENTA SIN PYG | AL98: VENTA FINAL | AM98: ACCE | AN98: ALUMINIO | AO98: CRISTAL | AP98: % DESP ALU | AQ98: MAQ | AR98: EMPQ | AS98: TRANS | AT98: ENSAMBLE | AU98: INSTA | AV98: IMPREV | AW98: BACKOFFICE | AX98: UTILIDAD | AY98: COMISIÓN | AZ98: VENTA | BC98: V14 | BE98: Nº MÓDULOS | BF98: =$BF$13 -> VR SILICONA | BG98: =$BG$13 -> VR PELÍCULA | BH98: =$BH$13 -> VR EMBALAJE | BJ98: =$BJ$13 -> ESP. CRISTAL | BK98: ESTRUCTURA | BL98: CRISTAL | BM98: =BM91 -> TOTAL | BN98: VR TRANSP | CK98: OR | CL98: MD | CM98: AD | CN98: EL | CO98: MD | CP98: PL | CQ98: PRO | CR98: DESP | CS98: MT | CT98: ENT | CU98: CNT | CV98: VR TOTAL | CW98: CNT | CX98: VR TOTAL | CY98: CNT | CZ98: VR TOTAL | DA98: CNT | DB98: VR TOTAL | DC98: CNT | DD98: VR TOTAL | DG98: RAD | DH98: CANTIDAD | DI98: SUBTOTAL | DJ98: TOTAL | DK98: ALU | DL98: ACC | DM98: VIDRIO | DN98: TRANSPORTE | DO98: VIATICOS | DP98: BACKOFFICE | DQ98: GAST VENTA | DR98: GAST FINANC | DS98: COSTOS IND | DT98: ENSAMBLE | DU98: INSTALACION | DV98: M2 INOX | DW98: M2 ALU | DX98: VR INOX | DY98: VR ALU
C99: SISTEMA | L99: =J99*K99*M99 -> 0 | N99: =IFERROR(AL99,"") -> 1.0765547 | O99: =IFERROR(N99*M99,"") -> 0 | Q99: =Q100+BF99+($R$350*Q100) -> 0 | R99: =IFERROR(R100+($R$348*R100),"") -> 0 | S99: =+IF(R101="SI",((W103*'BD GN'!$AB$2)+S100)*1,COTIZACIÓN!S100*1)+(P100*S100) -> 0 | T99: =IFERROR(R99*IF(K99<=3,$T$13,15%),"") -> 0 | U99: =BH99+BG99 -> 0 | V99: =IFERROR(BN99,0) | W99: =IFERROR(IF(X101="SI",W102*J99*K99,IF(BE99=3,BE101,IF(BE99=4,BE102,IF(BE99=5,BE103,IF(BE99>5,BE103+(BE104*(BE99-5)),"")))))*0,"") | X99: =IFERROR(IF(X100="NO",(VLOOKUP(D99,'BD M.O'!C:E,3,FALSE))*W103,((VLOOKUP(D99,'BD M.O'!C:E,3,FALSE))+7500)*W103),"") | Y99: =IFERROR($Y$13*AK99,"") -> 0.042084457 | Z99: =IFERROR(($Z$13*AK99)+X99,"") | AA99: =IFERROR(Y99+Z99,"") | AB99: =IFERROR((SUM(Q99:X99)-T99+T101)*$AB$13,"") -> 0 | AC99: =IFERROR(((SUM(Q99:V99,IF(X104>AA99,AVERAGE(X104,AA99),AA99))-T99+T101))*$AB$13,"") -> 0 | AD99: =IFERROR((J99*K99*$BV$14),"") | AE99: =IFERROR($AE$13*AK99,"") -> 0.064010593 | AF99: =IFERROR(($CI$11+$CI$13)*W103,"") | AG99: =IFERROR((SUM(Q99:X99,AB99,AD99,AF99)-T99+T101)*$AG$13,"") -> 0 | AH99: =IFERROR((SUM(Q99:V99,(IF(X104>AA99,AVERAGE(X104,AA99),AA99)),AC99,AE99,AF99)-T99+T101)*$AG$13,"") -> 0.032005296 | AI99: =IFERROR(AL99*$AI$13,"") -> 0.021531093 | AJ99: =IFERROR($AJ$13*AL99,"") -> 0.006007175 | AK99: =IFERROR(SUM(Q99:X99,AB99,AD99,AG99,AF99)/(1-$AI$13)+(1-$AJ$13)-T99+T101,"") -> 0.99442 | AL99: =IFERROR(SUM(Q99:V99,AC99,(IF(AD99>AE99,AVERAGE(AD99,AE99),AE99)),AF99,,AH99,(IF(SUM(X104)>AA99,AVERAGE(AA99,X104),AA99)))/(1-$AJ$13)+(1-$AI$13)-T99+T101,"") -> 1.0765547 | AM99: =$M$15*Q99 -> 0 | AN99: =$M$15*R99 -> 0 | AO99: =$M$15*S99 -> 0 | AP99: =$M$15*T99 -> 0 | AQ99: =$M$15*#REF! -> #REF! | AR99: =$M$15*U99 -> 0 | AS99: =$M$15*V99 -> #VALUE! | AT99: =$M$15*W99 -> #VALUE! | AU99: =$M$15*X99 -> #VALUE! | AV99: =$M$15*AB99 -> 0 | AW99: =$M$15*AE99 -> 0 | AX99: =$M$15*AG99 -> 0 | AY99: =$M$15*AI99 -> 0 | AZ99: =$M$15*AK99 -> 0 | BB99: CORTE 8 | BC99: V8 | BF99: =IF(BH100="NO",((2*J99)+(2*K99))*'BD GN'!$AU$3,((3*J99)+(2*K99))*'BD GN'!$AU$3) -> 0 | BG99: ='BD GN'!$BB$3*J99*K99 -> 0 | BH99: =((J99*2*BE99)+(K99*2*BE99))*'BD GN'!$AN$4 -> 0 | BL99: =J99*K99*2.5*BJ99 -> 0 | BM99: =BK99+BL99 -> 0 | BN99: =IFERROR((VLOOKUP($C$12,'BD GN'!BD:BM,10,FALSE)*BM99)+$BR$338,"") | CV99: =IFERROR(N99*CU99,"") -> 0 | CX99: =IFERROR(P99*CW99,"") -> 0 | CZ99: =IFERROR(R99*CY99,"") -> 0 | DA99: =CU99+CW99+CY99 -> 0 | DB99: =IFERROR(CV99+CX99+CZ99,"") -> 0 | DC99: =M99-(CU99+CW99+CY99) -> 0 | DD99: =IFERROR(O99-(CV99+CX99+CZ99),"") -> 0 | DI99: =IFERROR(IF(DG99>0,(((N99)/(1+10%+19%*5%)+((N99)/(1+10%+19%*5%))*10%)*DH99),0),0) -> 0 | DJ99: =IFERROR(IF(DG99>0,(N99*DH99),0),0) -> 0 | DK99: =IF(DG99>0,((R99+T99)*DH99),0) -> 0 | DL99: =IF(DG99>0,(Q99*DH99),0) -> 0 | DM99: =IF(DG99>0,(S99*DH99),0) -> 0 | DN99: =IF(DG99>0,(BN99*DH99),0) -> 0 | DO99: =IF(DG99>0,(AF99*DH99),0) -> 0 | DP99: =IF(DG99>0,((DI99)*('BD P&G'!$E$16+'BD P&G'!$E$17+'BD P&G'!$E$18+'BD P&G'!$E$19+'BD P&G'!$E$20+'BD P&G'!$E$21+'BD P&G'!$E$22+'BD P&G'!$E$23)*DH99),0) -> 0 | DQ99: =IFERROR(IF(DG99>0,((DI99*'BD P&G'!$E$7)+(DI99*'BD P&G'!$E$9)+AI99),0),0) -> 0 | DR99: =IFERROR(IF(DG99>0,((DI99*1%)),0),0) -> 0 | DS99: =IFERROR(IF(DG99>0,(((DI99*'BD P&G'!$E$32+DI99*'BD P&G'!$E$33+DI99*'BD P&G'!$E$35+DI99*'BD P&G'!$E$36+DI99*'BD P&G'!$E$37))),0),0) -> 0 | DT99: =IF(DG99>0,(Y99*DH99),0) -> 0 | DU99: =IF(DG99>0,(Z99*DH99),0) -> 0 | DV99: =IF(DG99>0,(Y103*DH99),0) -> 0 | DW99: =IF(DG99>0,(Z103*DH99),0) -> 0 | DX99: =IF(DV99>0,DJ99,0) -> 0 | DY99: =IF(DW99>0,DJ99,0) -> 0
C100: CRISTAL | T100: =IFERROR(T99/$R$353,"") -> 0 | W100: ANGEO | X100: NO | BB100: CORTE 9 | BC100: V9 | BE100: ALFAJÍA | BF100: NO | BG100: LUCETA | BH100: NO
C101: ACABADO ALUMINIO | Q101: SANDBLASTING | R101: NO | T101: =IFERROR(($R$353-8000)*T100,"") -> 0 | W101: FACHADA | X101: NO | BB101: CORTE 10 | BC101: V10 | BE101: =IFERROR(VLOOKUP(D99,'BD M.O'!C:H,4,FALSE),"") | BF101: 2HOJAS
...

Sheet P&G
B3: P&G | AE3: PRESUPUESTO ANUAL COMPAÑÍA | AJ3: PRESUPUESTO PROYECTO (ESENCIAL) | AQ3: PRESUPUESTO PROYECTO (SG BIOCONFORT) | AX3: PRESUPUESTO PROYECTO ((SIGNATURE APERTURA MULTIPLE) | BE3: PRESUPUESTO PROYECTO ((SIGNATURE CAMBIO ACABADO)
B5: INGRESOS | C5: % | D5: COSTO | E5: % | F5: UTILIDAD B | G5: % | H5: GASTOS V | I5: % | J5: GASTOS ADM | K5: % | L5: COSTOS INDIRECTOS | M5: % | N5: GASTOS TOTALES | O5: % | P5: UTILIDAD A.IMP | Q5: % | R5: IMPREVISTOS | S5: % | T5: EBITDA | U5: % | V5: IMPUESTOS | W5: % | X5: GASTOS FINANCIEROS | Y5: % | Z5: UTILIDAD NETA | AA5: % | AE5: RUBRO | AF5: VALOR ABSOLUTO | AG5: VR X M2 | AH5: % | AJ5: VALOR ABSOLUTO | AK5: VR X M2 | AL5: % | AN5: VARIACION VS PPTO ANUAL COMPAÑÍA | AQ5: VALOR ABSOLUTO | AR5: VR X M2 | AS5: % | AU5: VARIACION VS PPTO ANUAL COMPAÑÍA | AX5: VALOR ABSOLUTO | AY5: VR X M2 | AZ5: % | BB5: VARIACION VS PPTO ANUAL COMPAÑÍA | BE5: VALOR ABSOLUTO | BF5: VR X M2 | BG5: % | BI5: VARIACION VS PPTO ANUAL COMPAÑÍA
B6: =COTIZACIÓN!O341 -> 0 | C6: 1 | D6: =COTIZACIÓN!Q336+COTIZACIÓN!R336+COTIZACIÓN!S336+COTIZACIÓN!T336 -> 0 | E6: =IFERROR(D6/$B$6,"0%") -> 0% | F6: =B6-D6 -> 0 | G6: =IFERROR(F6/$B$6,"0%") -> 0% | H6: =((COTIZACIÓN!O341)*('BD P&G'!E7+'BD P&G'!E9+'BD P&G'!E10+'BD P&G'!E11))+COTIZACIÓN!AI336 -> 0 | I6: =IFERROR(H6/$B$6,"0%") -> 0% | J6: =(COTIZACIÓN!O341)*('BD P&G'!E16+'BD P&G'!E17+'BD P&G'!E18+'BD P&G'!E19+'BD P&G'!E20+'BD P&G'!E21+'BD P&G'!E22+'BD P&G'!E23) -> 0 | K6: =IFERROR(J6/$B$6,"0%") -> 0% | L6: =((COTIZACIÓN!O341)*('BD P&G'!E32+'BD P&G'!E33+'BD P&G'!E35+'BD P&G'!E36+'BD P&G'!E37+'BD P&G'!E39+'BD P&G'!E34+'BD P&G'!E38))+COTIZACIÓN!U336+COTIZACIÓN!V336+COTIZACIÓN!AA336+COTIZACIÓN!AF336 -> 0 | M6: =IFERROR(L6/$B$6,"0%") -> 0% | N6: =H6+J6+L6+R6+X6 -> 0 | O6: =IFERROR(N6/$B$6,"0%") -> 0% | P6: =F6-N6 -> 0 | Q6: =IFERROR(P6/$B$6,"0%") -> 0% | R6: =COTIZACIÓN!AC336 -> 0 | S6: =IFERROR(R6/$B$6,"0%") -> 0% | T6: =P6-(COTIZACIÓN!O341*'BD P&G'!E36) -> 0 | U6: =IFERROR(T6/$B$6,"0%") -> 0% | V6: =(B6*5%)+COTIZACIÓN!AJ336 -> 0 | W6: =IFERROR(V6/$B$6,"0%") -> 0% | X6: =COTIZACIÓN!O343*1% -> 0 | Y6: =IFERROR(X6/$B$6,"0%") -> 0% | Z6: =P6-V6 -> 0 | AA6: =IFERROR(Z6/$B$6,"0%") -> 0% | AE6: INGRESOS | AF6: 14335654400 | AG6: =AF6/17941 -> 799044.33 | AH6: 1 | AJ6: =COTIZACIÓN!O343 -> 0 | AK6: =AJ6/COTIZACIÓN!$F$339 -> #DIV/0! | AL6: 1 | AN6: =AK6-AG6 -> #DIV/0! | AO6: =(AK6/AG6)-100% -> #DIV/0! | AQ6: =COTIZACIÓN!AC363 -> 1.1502546 | AR6: =AQ6/COTIZACIÓN!$F$339 -> #DIV/0! | AS6: 1 | AU6: =AR6-$AG$6 -> #DIV/0! | AV6: =(AR6/$AG$6)-100% -> #DIV/0! | AX6: =COTIZACIÓN!AC364 -> 1.1502546 | AY6: =AX6/COTIZACIÓN!$F$339 -> #DIV/0! | AZ6: 1 | BB6: =AY6-$AG$6 -> #DIV/0! | BC6: =(AY6/$AG$6)-100% -> #DIV/0! | BE6: =COTIZACIÓN!AC365 -> 1.1502546 | BF6: =BE6/COTIZACIÓN!$F$339 -> #DIV/0! | BG6: 1 | BI6: =BF6-$AG$6 -> #DIV/0! | BJ6: =(BF6/$AG$6)-100% -> #DIV/0!
B8: TIPO CLIENTE | C8: UTN | D8: OBSERVACION | V8: =P6*35% -> 0 | AE8: MATERIA PRIMA | AF8: 4861081296 | AG8: =AF8/17941 -> 270948.18 | AH8: =AG8/$AG$6 -> 0.3390903 | AJ8: =COTIZACIÓN!$Q$336+COTIZACIÓN!$R$336+COTIZACIÓN!$S$336+COTIZACIÓN!$T$336 -> 0 | AK8: =AJ8/COTIZACIÓN!$F$339 -> #DIV/0! | AL8: =AK8/$AK$6 -> #DIV/0! | AN8: =AK8-AG8 -> #DIV/0! | AO8: =(AK8/AG8)-100% -> #DIV/0! | AQ8: =COTIZACIÓN!$Q$355+COTIZACIÓN!$R$355+COTIZACIÓN!$S$355+COTIZACIÓN!$T$355 -> 0 | AR8: =AQ8/COTIZACIÓN!$F$339 -> #DIV/0! | AS8: =AR8/$AR$6 -> #DIV/0! | AU8: =AR8-$AG$8 -> #DIV/0! | AV8: =(AR8/$AG$8)-100% -> #DIV/0! | AX8: =COTIZACIÓN!$Q$357+COTIZACIÓN!$R$357+COTIZACIÓN!$S$357+COTIZACIÓN!$T$357 -> 0 | AY8: =AX8/COTIZACIÓN!$F$339 -> #DIV/0! | AZ8: =AY8/$AY$6 -> #DIV/0! | BB8: =AY8-$AG$8 -> #DIV/0! | BC8: =(AY8/$AG$8)-100% -> #DIV/0! | BE8: =COTIZACIÓN!$Q$359+COTIZACIÓN!$R$359+COTIZACIÓN!$S$359+COTIZACIÓN!$T$359 -> 0 | BF8: =BE8/COTIZACIÓN!$F$339 -> #DIV/0! | BG8: =BF8/$BF$6 -> #DIV/0! | BI8: =BF8-$AG$8 -> #DIV/0! | BJ8: =(BF8/$AG$8)-100% -> #DIV/0!
B9: CLIENTE T1 | C9: 0.25 | D9: CLIENTE GERENCIA | V9: =(B6*5%)*35% -> 0 | AE9: M.O PRODUCCION | AF9: 1025656123 | AG9: =AF9/17941 -> 57168.281 | AH9: =AG9/$AG$6 -> 0.071545818 | AJ9: =(COTIZACIÓN!$Y$336)/2 -> 0 | AK9: =AJ9/COTIZACIÓN!$F$339 -> #DIV/0! | AL9: =AK9/$AK$6 -> #DIV/0! | AN9: =AK9-AG9 -> #DIV/0! | AO9: =(AK9/AG9)-100% -> #DIV/0! | AQ9: =(COTIZACIÓN!$Y$355)/2 -> 0.021042229 | AR9: =AQ9/COTIZACIÓN!$F$339 -> #DIV/0! | AS9: =AR9/$AR$6 -> #DIV/0! | AU9: =AR9-$AG$9 -> #DIV/0! | AV9: =(AR9/$AG$9)-100% -> #DIV/0! | AX9: =(COTIZACIÓN!$Y$357)/2 -> 0.021042229 | AY9: =AX9/COTIZACIÓN!$F$339 -> #DIV/0! | AZ9: =AY9/$AY$6 -> #DIV/0! | BB9: =AY9-$AG$9 -> #DIV/0! | BC9: =(AY9/$AG$9)-100% -> #DIV/0! | BE9: =(COTIZACIÓN!$Y$359)/2 -> 0.021042229 | BF9: =BE9/COTIZACIÓN!$F$339 -> #DIV/0! | BG9: =BF9/$BF$6 -> #DIV/0! | BI9: =BF9-$AG$9 -> #DIV/0! | BJ9: =(BF9/$AG$9)-100% -> #DIV/0!
B10: CLIENTE T2 | C10: 0.2 | D10: CLIENTE RECURRENTE, VALORA CALIDAD | V10: =V8-V9 -> 0 | AE10: M.O TECNICA | AF10: 275198492 | AG10: =AF10/17941 -> 15339.083 | AH10: =AG10/$AG$6 -> 0.019196786 | AJ10: =(COTIZACIÓN!$Y$336)/2 -> 0 | AK10: =AJ10/COTIZACIÓN!$F$339 -> #DIV/0! | AL10: =AK10/$AK$6 -> #DIV/0! | AN10: =AK10-AG10 -> #DIV/0! | AO10: =(AK10/AG10)-100% -> #DIV/0! | AQ10: =(COTIZACIÓN!$Y$355)/2 -> 0.021042229 | AR10: =AQ10/COTIZACIÓN!$F$339 -> #DIV/0! | AS10: =AR10/$AR$6 -> #DIV/0! | AU10: =AR10-$AG$10 -> #DIV/0! | AV10: =(AR10/$AG$10)-100% -> #DIV/0! | AX10: =(COTIZACIÓN!$Y$357)/2 -> 0.021042229 | AY10: =AX10/COTIZACIÓN!$F$339 -> #DIV/0! | AZ10: =AY10/$AY$6 -> #DIV/0! | BB10: =AY10-$AG$10 -> #DIV/0! | BC10: =(AY10/$AG$10)-100% -> #DIV/0! | BE10: =(COTIZACIÓN!$Y$359)/2 -> 0.021042229 | BF10: =BE10/COTIZACIÓN!$F$339 -> #DIV/0! | BG10: =BF10/$BF$6 -> #DIV/0! | BI10: =BF10-$AG$10 -> #DIV/0! | BJ10: =(BF10/$AG$10)-100% -> #DIV/0!
B11: CLIENTE T3 | C11: 0.15 | D11: CLIENTE QUE BUSCA SOLO PRECIO | V11: =V10*21.5% -> 0 | AE11: M.O INSTALACION | AF11: 331289692 | AG11: =AF11/17941 -> 18465.509 | AH11: =AG11/$AG$6 -> 0.023109492 | AJ11: =COTIZACIÓN!$Z$336 -> 0 | AK11: =AJ11/COTIZACIÓN!$F$339 -> #DIV/0! | AL11: =AK11/$AK$6 -> #DIV/0! | AN11: =AK11-AG11 -> #DIV/0! | AO11: =(AK11/AG11)-100% -> #DIV/0! | AQ11: =COTIZACIÓN!$Z$355 -> 0.0058166709 | AR11: =AQ11/COTIZACIÓN!$F$339 -> #DIV/0! | AS11: =AR11/$AR$6 -> #DIV/0! | AU11: =AR11-$AG$11 -> #DIV/0! | AV11: =(AR11/$AG$11)-100% -> #DIV/0! | AX11: =COTIZACIÓN!$Z$357 -> 0.0058166709 | AY11: =AX11/COTIZACIÓN!$F$339 -> #DIV/0! | AZ11: =AY11/$AY$6 -> #DIV/0! | BB11: =AY11-$AG$11 -> #DIV/0! | BC11: =(AY11/$AG$11)-100% -> #DIV/0! | BE11: =COTIZACIÓN!$Z$359 -> 0.0058166709 | BF11: =BE11/COTIZACIÓN!$F$339 -> #DIV/0! | BG11: =BF11/$BF$6 -> #DIV/0! | BI11: =BF11-$AG$11 -> #DIV/0! | BJ11: =(BF11/$AG$11)-100% -> #DIV/0!
V12: =V9+V11 -> 0 | AE12: COSTOS INDIRECTOS | AF12: 1184102667 | AG12: =AF12/17941 -> 65999.814 | AH12: =AG12/$AG$6 -> 0.082598438 | AJ12: =((AJ6)*('BD P&G'!$E$32+'BD P&G'!$E$33+'BD P&G'!$E$34+'BD P&G'!$E$35+'BD P&G'!$E$36+'BD P&G'!$E$37+'BD P&G'!$E$38+'BD P&G'!$E$39))+COTIZACIÓN!$U$336+COTIZACIÓN!$V$336+COTIZACIÓN!$AF$336+COTIZACIÓN!$AC$336 -> 0 | AK12: =AJ12/COTIZACIÓN!$F$339 -> #DIV/0! | AL12: =AK12/$AK$6 -> #DIV/0! | AN12: =AK12-AG12 -> #DIV/0! | AO12: =(AK12/AG12)-100% -> #DIV/0! | AQ12: =((AQ6)*('BD P&G'!$E$32+'BD P&G'!$E$33+'BD P&G'!$E$34+'BD P&G'!$E$35+'BD P&G'!$E$36+'BD P&G'!$E$37+'BD P&G'!$E$38+'BD P&G'!$E$39))+COTIZACIÓN!$U$355+COTIZACIÓN!$V$355+COTIZACIÓN!$AF$355+COTIZACIÓN!$AC$355 -> #VALUE! | AR12: =AQ12/COTIZACIÓN!$F$339 -> #VALUE! | AS12: =AR12/$AR$6 -> #VALUE! | AU12: =AR12-$AG$12 -> #VALUE! | AV12: =(AR12/$AG$12)-100% -> #VALUE! | AX12: =((AX6)*('BD P&G'!$E$32+'BD P&G'!$E$33+'BD P&G'!$E$34+'BD P&G'!$E$35+'BD P&G'!$E$36+'BD P&G'!$E$37+'BD P&G'!$E$38+'BD P&G'!$E$39))+COTIZACIÓN!$U$357+COTIZACIÓN!$V$357+COTIZACIÓN!$AF$357+COTIZACIÓN!$AC$357 -> #VALUE! | AY12: =AX12/COTIZACIÓN!$F$339 -> #VALUE! | AZ12: =AY12/$AY$6 -> #VALUE! | BB12: =AY12-$AG$12 -> #VALUE! | BC12: =(AY12/$AG$12)-100% -> #VALUE! | BE12: =((BE6)*('BD P&G'!$E$32+'BD P&G'!$E$33+'BD P&G'!$E$34+'BD P&G'!$E$35+'BD P&G'!$E$36+'BD P&G'!$E$37+'BD P&G'!$E$38+'BD P&G'!$E$39))+COTIZACIÓN!$U$359+COTIZACIÓN!$V$359+COTIZACIÓN!$AF$359+COTIZACIÓN!$AC$359 -> #VALUE! | BF12: =BE12/COTIZACIÓN!$F$339 -> #VALUE! | BG12: =BF12/$BF$6 -> #VALUE! | BI12: =BF12-$AG$12 -> #VALUE! | BJ12: =(BF12/$AG$12)-100% -> #VALUE!
V13: =V12/B6 -> #DIV/0! | AE13: TOTAL COSTO | AF13: =SUM(AF8:AF12) -> 7677328270 | AG13: =SUM(AG8:AG12) -> 427920.87 | AH13: =SUM(AH8:AH12) -> 0.53554083 | AJ13: =SUM(AJ8:AJ12) -> 0 | AK13: =SUM(AK8:AK12) -> #DIV/0! | AL13: =SUM(AL8:AL12) -> #DIV/0! | AN13: =AK13-AG13 -> #DIV/0! | AO13: =(AK13/AG13)-100% -> #DIV/0! | AQ13: =SUM(AQ8:AQ12) -> #VALUE! | AR13: =SUM(AR8:AR12) -> #DIV/0! | AS13: =SUM(AS8:AS12) -> #DIV/0! | AU13: =AR13-$AG$13 -> #DIV/0! | AV13: =(AR13/$AG$13)-100% -> #DIV/0! | AX13: =SUM(AX8:AX12) -> #VALUE! | AY13: =SUM(AY8:AY12) -> #DIV/0! | AZ13: =SUM(AZ8:AZ12) -> #DIV/0! | BB13: =AY13-$AG$13 -> #DIV/0! | BC13: =(AY13/$AG$13)-100% -> #DIV/0! | BE13: =SUM(BE8:BE12) -> #VALUE! | BF13: =SUM(BF8:BF12) -> #DIV/0! | BG13: =SUM(BG8:BG12) -> #DIV/0! | BI13: =BF13-$AG$13 -> #DIV/0! | BJ13: =(BF13/$AG$13)-100% -> #DIV/0!
AE15: UTILIDAD BRUTA OPERACIONAL | AF15: =AF6-AF13 -> 6658326130 | AG15: =AF15/17941 -> 371123.47 | AH15: =AG15/$AG$6 -> 0.46445917 | AJ15: =AJ6-AJ13 -> 0 | AK15: =AK6-AK13 -> #DIV/0! | AL15: =AL6-AL13 -> #DIV/0! | AN15: =AK15-AG15 -> #DIV/0! | AO15: =(AK15/AG15)-100% -> #DIV/0! | AQ15: =AQ6-AQ13 -> #VALUE! | AR15: =AR6-AR13 -> #DIV/0! | AS15: =AS6-AS13 -> #DIV/0! | AU15: =AR15-$AG$15 -> #DIV/0! | AV15: =(AR15/$AG$15)-100% -> #DIV/0! | AX15: =AX6-AX13 -> #VALUE! | AY15: =AY6-AY13 -> #DIV/0! | AZ15: =AZ6-AZ13 -> #DIV/0! | BB15: =AY15-$AG$15 -> #DIV/0! | BC15: =(AY15/$AG$15)-100% -> #DIV/0! | BE15: =BE6-BE13 -> #VALUE! | BF15: =BF6-BF13 -> #DIV/0! | BG15: =BG6-BG13 -> #DIV/0! | BI15: =BF15-$AG$15 -> #DIV/0! | BJ15: =(BF15/$AG$15)-100% -> #DIV/0!
AE17: GASTOS ADM | AF17: 1450771136 | AG17: =AF17/17941 -> 80863.449 | AH17: =AG17/$AG$6 -> 0.1012002 | AJ17: =(AJ6)*('BD P&G'!$E$16+'BD P&G'!$E$17+'BD P&G'!$E$18+'BD P&G'!$E$19+'BD P&G'!$E$20+'BD P&G'!$E$21+'BD P&G'!$E$22+'BD P&G'!$E$23) -> 0 | AK17: =AJ17/COTIZACIÓN!$F$339 -> #DIV/0! | AL17: =AK17/$AK$6 -> #DIV/0! | AN17: =AK17-AG17 -> #DIV/0! | AO17: =(AK17/AG17)-100% -> #DIV/0! | AQ17: =(AQ6)*('BD P&G'!$E$16+'BD P&G'!$E$17+'BD P&G'!$E$18+'BD P&G'!$E$19+'BD P&G'!$E$20+'BD P&G'!$E$21+'BD P&G'!$E$22+'BD P&G'!$E$23) -> 0.031270174 | AR17: =AQ17/COTIZACIÓN!$F$339 -> #DIV/0! | AS17: =AR17/$AR$6 -> #DIV/0! | AU17: =AR17-$AG$17 -> #DIV/0! | AV17: =(AR17/$AG$17)-100% -> #DIV/0! | AX17: =(AX6)*('BD P&G'!$E$16+'BD P&G'!$E$17+'BD P&G'!$E$18+'BD P&G'!$E$19+'BD P&G'!$E$20+'BD P&G'!$E$21+'BD P&G'!$E$22+'BD P&G'!$E$23) -> 0.031270174 | AY17: =AX17/COTIZACIÓN!$F$339 -> #DIV/0! | AZ17: =AY17/$AY$6 -> #DIV/0! | BB17: =AY17-$AG$17 -> #DIV/0! | BC17: =(AY17/$AG$17)-100% -> #DIV/0! | BE17: =(BE6)*('BD P&G'!$E$16+'BD P&G'!$E$17+'BD P&G'!$E$18+'BD P&G'!$E$19+'BD P&G'!$E$20+'BD P&G'!$E$21+'BD P&G'!$E$22+'BD P&G'!$E$23) -> 0.031270174 | BF17: =BE17/COTIZACIÓN!$F$339 -> #DIV/0! | BG17: =BF17/$BF$6 -> #DIV/0! | BI17: =BF17-$AG$17 -> #DIV/0! | BJ17: =(BF17/$AG$17)-100% -> #DIV/0!
AE18: GASTOS VENTAS | AF18: 953555227 | AG18: =AF18/17941 -> 53149.503 | AH18: =AG18/$AG$6 -> 0.066516338 | AJ18: =(AJ6*('BD P&G'!$E$7+'BD P&G'!$E$9+'BD P&G'!$E$10+'BD P&G'!$E$11))+COTIZACIÓN!$AI$336 -> 0 | AK18: =AJ18/COTIZACIÓN!$F$339 -> #DIV/0! | AL18: =AK18/$AK$6 -> #DIV/0! | AN18: =AK18-AG18 -> #DIV/0! | AO18: =(AK18/AG18)-100% -> #DIV/0! | AQ18: =(AQ6*('BD P&G'!$E$7+'BD P&G'!$E$9+'BD P&G'!$E$10+'BD P&G'!$E$11))+COTIZACIÓN!$AI$355 -> 0.053325478 | AR18: =AQ18/COTIZACIÓN!$F$339 -> #DIV/0! | AS18: =AR18/$AR$6 -> #DIV/0! | AU18: =AR18-$AG$18 -> #DIV/0! | AV18: =(AR18/$AG$18)-100% -> #DIV/0! | AX18: =(AX6*('BD P&G'!$E$7+'BD P&G'!$E$9+'BD P&G'!$E$10+'BD P&G'!$E$11))+COTIZACIÓN!$AI$357 -> 0.053325478 | AY18: =AX18/COTIZACIÓN!$F$339 -> #DIV/0! | AZ18: =AY18/$AY$6 -> #DIV/0! | BB18: =AY18-$AG$18 -> #DIV/0! | BC18: =(AY18/$AG$18)-100% -> #DIV/0! | BE18: =(BE6*('BD P&G'!$E$7+'BD P&G'!$E$9+'BD P&G'!$E$10+'BD P&G'!$E$11))+COTIZACIÓN!$AI$359 -> 0.053325478 | BF18: =BE18/COTIZACIÓN!$F$339 -> #DIV/0! | BG18: =BF18/$BF$6 -> #DIV/0! | BI18: =BF18-$AG$18 -> #DIV/0! | BJ18: =(BF18/$AG$18)-100% -> #DIV/0!
AE19: GASTOS FINANCIEROS | AF19: 79805418 | AG19: =AF19/17941 -> 4448.2146 | AH19: =AG19/$AG$6 -> 0.0055669184 | AJ19: =(COTIZACIÓN!$O$343)*1% -> 0 | AK19: =AJ19/COTIZACIÓN!$F$339 -> #DIV/0! | AL19: =AK19/$AK$6 -> #DIV/0! | AN19: =AK19-AG19 -> #DIV/0! | AO19: =(AK19/AG19)-100% -> #DIV/0! | AQ19: =(COTIZACIÓN!$O$343+COTIZACIÓN!$BD$355)*1% -> 0.011502546 | AR19: =AQ19/COTIZACIÓN!$F$339 -> #DIV/0! | AS19: =AR19/$AR$6 -> #DIV/0! | AU19: =AR19-$AG$19 -> #DIV/0! | AV19: =(AR19/$AG$19)-100% -> #DIV/0! | AX19: =(COTIZACIÓN!$O$343+COTIZACIÓN!$BD$357)*1% -> 0 | AY19: =AX19/COTIZACIÓN!$F$339 -> #DIV/0! | AZ19: =AY19/$AY$6 -> #DIV/0! | BB19: =AY19-$AG$19 -> #DIV/0! | BC19: =(AY19/$AG$19)-100% -> #DIV/0! | BE19: =(COTIZACIÓN!$O$343+COTIZACIÓN!$BD$359)*1% -> 0 | BF19: =BE19/COTIZACIÓN!$F$339 -> #DIV/0! | BG19: =BF19/$BF$6 -> #DIV/0! | BI19: =BF19-$AG$19 -> #DIV/0! | BJ19: =(BF19/$AG$19)-100% -> #DIV/0!
AE20: TOTAL GASTOS | AF20: =SUM(AF17:AF19) -> 2484131781 | AG20: =SUM(AG17:AG19) -> 138461.17 | AH20: =SUM(AH17:AH19) -> 0.17328346 | AJ20: =SUM(AJ17:AJ19) -> 0 | AK20: =SUM(AK17:AK19) -> #DIV/0! | AL20: =SUM(AL17:AL19) -> #DIV/0! | AN20: =AK20-AG20 -> #DIV/0! | AO20: =(AK20/AG20)-100% -> #DIV/0! | AQ20: =SUM(AQ17:AQ19) -> 0.096098198 | AR20: =SUM(AR17:AR19) -> #DIV/0! | AS20: =SUM(AS17:AS19) -> #DIV/0! | AU20: =AR20-$AG$20 -> #DIV/0! | AV20: =(AR20/$AG$20)-100% -> #DIV/0! | AX20: =SUM(AX17:AX19) -> 0.084595652 | AY20: =SUM(AY17:AY19) -> #DIV/0! | AZ20: =SUM(AZ17:AZ19) -> #DIV/0! | BB20: =AY20-$AG$20 -> #DIV/0! | BC20: =(AY20/$AG$20)-100% -> #DIV/0! | BE20: =SUM(BE17:BE19) -> 0.084595652 | BF20: =SUM(BF17:BF19) -> #DIV/0! | BG20: =SUM(BG17:BG19) -> #DIV/0! | BI20: =BF20-$AG$20 -> #DIV/0! | BJ20: =(BF20/$AG$20)-100% -> #DIV/0!
AE22: UTILIDAD ANTES DE IMPUESTOS | AF22: =AF6-AF13-AF20 -> 4174194349 | AG22: =AF22/17941 -> 232662.3 | AH22: =AG22/$AG$6 -> 0.29117571 | AJ22: =AJ6-AJ13-AJ20 -> 0 | AK22: =AK6-AK13-AK20 -> #DIV/0! | AL22: =AL6-AL13-AL20 -> #DIV/0! | AN22: =AK22-AG22 -> #DIV/0! | AO22: =(AK22/AG22)-100% -> #DIV/0! | AQ22: =AQ6-AQ13-AQ20 -> #VALUE! | AR22: =AR6-AR13-AR20 -> #DIV/0! | AS22: =AS6-AS13-AS20 -> #DIV/0! | AU22: =AR22-$AG$22 -> #DIV/0! | AV22: =(AR22/$AG$22)-100% -> #DIV/0! | AX22: =AX6-AX13-AX20 -> #VALUE! | AY22: =AY6-AY13-AY20 -> #DIV/0! | AZ22: =AZ6-AZ13-AZ20 -> #DIV/0! | BB22: =AY22-$AG$22 -> #DIV/0! | BC22: =(AY22/$AG$22)-100% -> #DIV/0! | BE22: =BE6-BE13-BE20 -> #VALUE! | BF22: =BF6-BF13-BF20 -> #DIV/0! | BG22: =BG6-BG13-BG20 -> #DIV/0! | BI22: =BF22-$AG$22 -> #DIV/0! | BJ22: =(BF22/$AG$22)-100% -> #DIV/0!
AE24: IMPUESTOS | AF24: 444405286 | AG24: =AF24/17941 -> 24770.374 | AH24: =AG24/$AG$6 -> 0.031 | AJ24: =(AJ6*5%)+COTIZACIÓN!$AJ$336 -> 0 | AK24: =AJ24/COTIZACIÓN!$F$339 -> #DIV/0! | AL24: =AK24/$AK$6 -> #DIV/0! | AN24: =AK24-AG24 -> #DIV/0! | AO24: =(AK24/AG24)-100% -> #DIV/0! | AQ24: =(AQ6*5%)+COTIZACIÓN!$AJ$355 -> 0.063931153 | AR24: =AQ24/COTIZACIÓN!$F$339 -> #DIV/0! | AS24: =AR24/$AR$6 -> #DIV/0! | AU24: =AR24-$AG$24 -> #DIV/0! | AV24: =(AR24/$AG$24)-100% -> #DIV/0! | AX24: =(AX6*5%)+COTIZACIÓN!$AJ$357 -> 0.063931153 | AY24: =AX24/COTIZACIÓN!$F$339 -> #DIV/0! | AZ24: =AY24/$AY$6 -> #DIV/0! | BB24: =AY24-$AG$24 -> #DIV/0! | BC24: =(AY24/$AG$24)-100% -> #DIV/0! | BE24: =(BE6*5%)+COTIZACIÓN!$AJ$359 -> 0.063931153 | BF24: =BE24/COTIZACIÓN!$F$339 -> #DIV/0! | BG24: =BF24/$BF$6 -> #DIV/0! | BI24: =BF24-$AG$24 -> #DIV/0! | BJ24: =(BF24/$AG$24)-100% -> #DIV/0!
AE26: UTILIDAD NETA | AF26: =AF22-AF24 -> 3729789063 | AG26: =AF26/17941 -> 207891.93 | AH26: =AH22-AH24 -> 0.26017571 | AJ26: =AJ22-AJ24 -> 0 | AK26: =AK22-AK24 -> #DIV/0! | AL26: =AL22-AL24 -> #DIV/0! | AN26: =AK26-AG26 -> #DIV/0! | AO26: =(AK26/AG26)-100% -> #DIV/0! | AQ26: =AQ22-AQ24 -> #VALUE! | AR26: =AR22-AR24 -> #DIV/0! | AS26: =AS22-AS24 -> #DIV/0! | AU26: =AR26-$AG$26 -> #DIV/0! | AV26: =(AR26/$AG$26)-100% -> #DIV/0! | AX26: =AX22-AX24 -> #VALUE! | AY26: =AY22-AY24 -> #DIV/0! | AZ26: =AZ22-AZ24 -> #DIV/0! | BB26: =AY26-$AG$26 -> #DIV/0! | BC26: =(AY26/$AG$26)-100% -> #DIV/0! | BE26: =BE22-BE24 -> #VALUE! | BF26: =BF22-BF24 -> #DIV/0! | BG26: =BG22-BG24 -> #DIV/0! | BI26: =BF26-$AG$26 -> #DIV/0! | BJ26: =(BF26/$AG$26)-100% -> #DIV/0!
